Workbook

Sheet Instructions
A1: Pilot v3 QA review
A3: What to do
A4: 1. On the Review sheet, the top 20 rows (priority = TRUE, shaded) are a stratified sample: 5 filter-rejected pairs, 5 repaired pairs, and 10 other passed pairs across question types. Review those (about 20 minutes).
A5: 2. Pick accept or reject in human_verdict (yellow, dropdown). If rejecting, pick a reject_category and add a short note.
A6: 3. Review BLIND first. The last three columns (claude_verdict, claude_category, claude_note) hold Claude's pre-screen and are collapsed. Expand them (the + above them) only after you finish your 20 rows, then compare.
A7: 4. The Agreement sheet updates automatically: you vs the automatic filters, and you vs Claude's pre-screen.
A9: Accept a pair only if all three are true
A10: Correct: the answer is fully supported by the evidence, with nothing added.
A11: Standalone: the question makes sense to someone who has never seen the source.
A12: Worth learning: it is about the domain (responsible AI, higher education), not trivia, study methodology or bibliography.
A14: Reject categories
A15: incorrect - answer contradicts or misreads the evidence
... A23: Save (keep .xlsx), copy into the project as data/qa_pairs/pilot_review_v3_reviewed.xlsx, and ask Claude Code to merge human_verdict, reject_category and human_notes by qa_id (sheet "Review").

Sheet Review
A1: # | B1: priority | C1: human_verdict | D1: reject_category | E1: human_notes | F1: question | G1: answer | H1: evidence | I1: citation | J1: passed_filters | K1: repaired | L1: reject_reason | M1: q_type | N1: difficulty | O1: dimension | P1: grounding | Q1: value | R1: judge_rationale | S1: paraphrase_1 | T1: paraphrase_2 | U1: origin | V1: qa_id | W1: claude_verdict | X1: claude_category | Y1: claude_note
A2: 1 | B2: =TRUE() -> TRUE | F2: Why is the concentration of top-ranked universities in a few regions of the world not simply a matter of the best institutions naturally rising to the top? | G2: Scholars of educational, health or other inequalities have long noted that underlying structures invariably create, maintain and often exacerbate social inequalities. In other words, it is not about the cream rising to the top, but about a system in which the cream identifies itself as better and uses systemic processes to stay there. | H2: Scholars of educational, health, or other inequalities, though, have long noted that underlying structures invariably create, maintain and often exacerbate social inequalities. In other words, it is not about the cream rising to the top, but rather about the presence of a system in which the cream identifies itself as better and utilises systemic processes to stay there. | I2: Socially Responsible Higher Education, p. 96 | J2: =TRUE() -> TRUE | K2: =TRUE() -> TRUE | M2: explanation | N2: medium | O2: equity_accessibility | P2: 5 | Q2: 4 | R2: The answer restates the quoted evidence almost verbatim, with only trivial rewording. The evidence does not itself mention regional concentration of rankings, but the answer makes no claim about it. | The question is self-contained and does not refer to any unseen source or context. | value: It covers a useful critical perspective on structural inequality in global university rankings. | S2: Why is the dominance of a few regions in world university rankings not just a case of merit naturally rising? | T2: Why can the dominance of a handful of world regions among top-ranked universities not be explained merely by the best institutions naturally ascending to the top? | U2: pilot | V2: budd-l-hall-rajesh-2021-socially-responsible:0055:q2 | W2: accept | Y2: Non-AI content (Socially Responsible HE book); these chunks have ai_score=0 and are excluded from full_v1 anyway.
A3: 2 | B3: =TRUE() -> TRUE | F3: What technique conceals confidential information in a way that does not affect the overall outcome of an AI system's decision-making process? | G3: Data masking is the technique in which confidential information is concealed in a way that does not affect the overall outcome of the decision-making process. | H3: This can be achieved through techniques such as data masking, where confidential information is concealed in a way that does not affect the overall outcome of the decisionmaking process. | I3: Towards Ethical and Socially Responsible Explainable AI, p. 103 | J3: =TRUE() -> TRUE | K3: =TRUE() -> TRUE | M3: factual | N3: easy | O3: privacy_security | P3: 5 | Q3: 4 | R3: The answer restates the evidence almost verbatim: data masking conceals confidential information without affecting the overall outcome of decision-making. | The question names the concept (concealing confidential information in AI decision-making) without referring to an unseen source. | value: Data masking is a useful privacy-preserving technique relevant to responsible AI. | S3: Which technique hides confidential data without changing the overall outcome of an AI system's decision-making? | T3: Which approach hides sensitive information within an AI system without changing the final result of its decision-making? | U3: pilot | V3: towards-ethical:0051:q2 | W3: accept
A4: 3 | B4: =TRUE() -> TRUE | F4: In ethical explainable AI, what does it mean for an AI system to be transparent and auditable? | G4: Transparency requires clear and understandable explanations of the system's decision-making processes, the data used, and the outcomes produced. Being auditable means that the decision-making processes can be traced and verified by relevant parties. | H4: This requires clear and understandable explanations of the decision-making processes, the data used, and the outcomes produced by the system. It also requires ensuring that the system is auditable, meaning that the decision-making processes can be traced and verified by relevant parties [9]. | I4: Towards Ethical and Socially Responsible Explainable AI, p. 104 | J4: =TRUE() -> TRUE | K4: =TRUE() -> TRUE | M4: definition | N4: medium | O4: governance | P4: 4 | Q4: 4 | R4: The answer closely restates the evidence. However, the evidence refers only to "this", so tying the explanation requirement specifically to transparency is a slight assumption. | The question is self-contained and clearly names the concepts it asks about. | value: Transparency and auditability are useful core concepts in responsible AI. | S4: What do transparency and auditability require of an AI system in ethical explainable AI? | T4: In ethical explainable AI, what must be in place for an AI system to count as transparent and as auditable? | U4: pilot | V4: towards-ethical:0051:q4 | W4: accept
A5: 4 | B5: =TRUE() -> TRUE | F5: A university is deploying an AI admissions-screening tool that processes applicants' personal data and affects individuals' lives. What accountability practices on data privacy and algorithmic bias apply? | G5: The organization should adhere to data privacy laws such as the GDPR in the European Union or the CCPA in the United States, implementing robust data protection measures, obtaining necessary consents, and enabling users to exercise their privacy rights. It should also implement measures to identify and mitigate algorithmic bias, particularly in applications that affect individuals' lives such as hiring or lending decisions, and regularly audit algorithms for fairness. | H5: Data Privacy Compliance: Adhere to data privacy laws such as the General Data Protection Regulation (GDPR) in the European Union or the California Consumer Privacy Act (CCPA) in the United States [31]. Implement robust data protection measures, obtain necessary consents, and enable users to exercise their privacy rights. … Algorithmic Bias Mitigation: Implement measures to identify and mitigate algorithmic bias, particularly in applications that impact individuals' lives, such as hiring or lending decisions. Regularly audit algorithms for fairness. | I5: Towards Ethical and Socially Responsible Explainable AI, pp. 171-172 | J5: =TRUE() -> TRUE | K5: =FALSE() -> FALSE | M5: application | N5: hard | O5: privacy_security | P5: 4 | Q5: 4 | R5: The answer restates the evidence nearly verbatim. Applying general guidance to a university admissions scenario is a mild framing, but the answer itself adds no unsupported claims. | The scenario is self-contained and uses no source references. Acronyms appear only in the answer. | value: These are useful accountability practices on privacy and bias for AI deployment. | S5: A university plans to use an AI tool to screen admissions applications using personal data, with consequences for people's lives. Which data privacy and bias-related accountability practices should it follow? | T5: A university is rolling out an AI tool to screen admissions applications, which handles applicants' personal data and influences their lives. Which accountability practices relating to data privacy and algorithmic bias are relevant? | U5: pilot | V5: towards-ethical:0090:q0 | W5: accept
A6: 5 | B6: =TRUE() -> TRUE | F6: Which regulation should healthcare AI systems comply with as an example of sector-specific regulation? | G6: Healthcare AI systems should comply with Health Insurance Portability and Accountability Act (HIPAA) regulations. Organizations should be aware of sector-specific regulations that may apply to AI applications. | H6: Sector-Specific Regulations: Be aware of sector-specific regulations that may apply to AI applications. For instance, healthcare AI systems should comply with Health Insurance Portability and Accountability Act (HIPAA) regulations. | I6: Towards Ethical and Socially Responsible Explainable AI, p. 172 | J6: =TRUE() -> TRUE | K6: =FALSE() -> FALSE | M6: factual | N6: easy | O6: privacy_security | P6: 5 | Q6: 3 | R6: Both statements are directly stated in the evidence: be aware of sector-specific regulations, and healthcare AI should comply with HIPAA. | The question is self-contained and needs no reference to an unseen source. | value: This is a basic compliance example that is only tangential to AI in higher education. | S6: As an example of a sector-specific rule for AI, which regulations must healthcare AI systems comply with? | T6: As an instance of sector-specific regulation, which law must AI systems used in healthcare comply with? | U6: pilot | V6: towards-ethical:0090:q4 | W6: accept
A7: 6 | B7: =TRUE() -> TRUE | F7: A nursing school wants to roll out generative AI for assessment generation and clinical simulation while keeping students' trust and the school's standards intact. What do the 2025 PAGER scoping review's recommendations on ChatGPT in nursing education say it should do? | G7: Implementation should follow evidence-based approaches in assessment generation and clinical simulation development, aligning with established pedagogical frameworks to enhance rather than replace effective teaching practices. Nursing education also needs a comprehensive framework that balances innovation with academic integrity in assessment and clinical training, sets clear data privacy and security standards, and ensures compliance with educational regulations. Developing technical and ethical competencies is crucial, especially for upholding academic integrity and ensuring equitable student access. | H7: Implementation should follow evidence-based approaches in assessment generation and clinical simulation development, aligning with established pedagogical frameworks to enhance rather than replace effective teaching practices. … The findings indicate the necessity of establishing a comprehensive system that balances innovation with academic integrity in nursing assessment and clinical training. These frameworks should establish clear data privacy and security standards guidelines and ensure compliance with educational regulations (Foronda and Porter, 2024). … Systematic documentation and evaluation of implementation experiences will contribute to developing best practices. Developing technical and ethical competencies is crucial, especially for upholding academic integrity and ensuring equitable student access. Cross-institutional collaboration should be encouraged to share implementation strategies and lessons learned. | I7: Patterns, advances, and gaps in using ChatGPT and similar technologies in nursing education: A PAGER scoping review, p. 8 | J7: =TRUE() -> TRUE | K7: =FALSE() -> FALSE | M7: application | N7: hard | O7: teaching_learning | P7: 4 | Q7: 4 | R7: The answer closely restates the evidence. The only changes are trivial rewordings, such as "framework" for "system". | The question identifies the source by its content (a 2025 PAGER scoping review on ChatGPT in nursing education) and sets out a clear scenario. | value: These are practical, domain-relevant recommendations for responsibly implementing generative AI in nursing education. | S7: If a nursing school introduces generative AI for assessment generation and clinical simulation, what approach does the PAGER scoping review on nursing education recommend it take? | T7: A school of nursing intends to introduce generative AI to generate assessments and run clinical simulations, while preserving student trust and its own standards. What steps does the 2025 PAGER scoping review on ChatGPT in nursing education advise it to take? | U7: pilot | V7: patterns-advances-and-gaps-in-using-chatgpt-and:0016:q0 | W7: accept
A8: 7 | B8: =TRUE() -> TRUE | F8: According to a PAGER scoping review of ChatGPT and similar technologies in nursing education, why should nursing curricula pair content on critical thinking with ethical guidelines? | G8: Authors emphasise the need for content that develops critical thinking abilities alongside the establishment of ethical guidelines in order to ensure responsible AI use. | H8: Building on this foundation, authors emphasise the need for content that develops critical thinking abilities alongside the establishment of ethical guidelines to ensure responsible AI use (Alkhaqani, 2023b; Archibald and Clark, 2023; Athilingam and He, 2024). | I8: Patterns, advances, and gaps in using ChatGPT and similar technologies in nursing education: A PAGER scoping review, p. 7 | J8: =TRUE() -> TRUE | K8: =FALSE() -> FALSE | M8: explanation | N8: medium | O8: student_ai_literacy | P8: 5 | Q8: 4 | R8: The answer restates the evidence nearly verbatim: content developing critical thinking alongside ethical guidelines is needed to ensure responsible AI use. | The question names the specific review by its content (a PAGER scoping review of ChatGPT in nursing education). The phrase 'according to' does presuppose a source, but here it identifies a named work, which is acceptable. | value: A useful curricular recommendation for responsible AI use in nursing education. | S8: In the PAGER scoping review on GenAI in nursing education, what is the purpose of developing critical thinking abilities alongside ethical guidelines in nursing content? | T8: Why does the PAGER scoping review of GenAI in nursing education call for nursing content that builds critical thinking together with ethical guidelines? | U8: pilot | V8: patterns-advances-and-gaps-in-using-chatgpt-and:0013:q0 | W8: accept
A9: 8 | B9: =TRUE() -> TRUE | F9: What technical improvements to GenAI do nursing education studies recommend in the PAGER scoping review? | G9: Technical recommendations focus on improving GenAI's accuracy and reducing bias by refining models to better reflect nursing standards and classification systems. | H9: Technical recommendations focus on improving GenAI's accuracy and reducing bias by refining models to reflect nursing standards and classification systems better (Gosak et al., 2024; Ye, 2024). | I9: Patterns, advances, and gaps in using ChatGPT and similar technologies in nursing education: A PAGER scoping review, p. 7 | J9: =TRUE() -> TRUE | K9: =FALSE() -> FALSE | M9: factual | N9: easy | O9: procurement_technology | P9: 5 | Q9: 4 | R9: The answer restates the evidence almost verbatim; every claim (accuracy, bias reduction, refining models to reflect nursing standards and classification systems) is directly stated. | The question names the PAGER scoping review and the topic, GenAI in nursing education, and does not refer to unseen context. PAGER is a named framework, so the question is acceptable as it stands. | value: These are useful, fairly specific recommendations about GenAI accuracy and bias in nursing education. | S9: Which technical recommendations for GenAI in nursing education are made in the PAGER scoping review? | T9: In the PAGER scoping review of GenAI in nursing education, what do technical recommendations focus on? | U9: pilot | V9: patterns-advances-and-gaps-in-using-chatgpt-and:0013:q2 | W9: accept
A10: 9 | B10: =TRUE() -> TRUE | F10: How do AI-driven entrepreneurial simulation systems improve students' ability to handle complex business scenarios? | G10: These simulation systems let students practice entrepreneurial decision-making in a low-risk environment and give them instant feedback, which improves their ability to handle complex business scenarios. | H10: For instance, AI-driven entrepreneurial simulation systems enable students to practice entrepreneurial decision-making in a low-risk environment, providing instant feedback and improving their ability to handle complex business scenarios (Chen et al., 2022; Mavlutova et al., 2020; Nowak, 2020). | I10: Toward understanding the role of generative AI in entrepreneurship education: A systematic review, p. 14 | J10: =TRUE() -> TRUE | K10: =FALSE() -> FALSE | M10: explanation | N10: medium | O10: teaching_learning | P10: 5 | Q10: 4 | R10: The answer directly restates the evidence: practice in a low-risk environment, instant feedback, and improved handling of complex scenarios. | The question names the technology by its content and does not refer to any unseen source. | value: This is useful and somewhat specific knowledge about how AI is applied in entrepreneurship education. | S10: Why do AI-driven entrepreneurial simulation systems help students deal better with complex business scenarios? | T10: By what means do AI-driven entrepreneurial simulations strengthen students' handling of complex business scenarios? | U10: pilot | V10: toward-understanding-the-role-of-generative-ai:0024:q2 | W10: accept
A11: 10 | B11: =TRUE() -> TRUE | F11: What shift in AI-powered learning models in entrepreneurship education has been observed, and what benefit may it bring? | G11: AI-powered learning models in entrepreneurship education are shifting from traditional static courses toward more personalized, immersive, and data-driven approaches. This may contribute to improved student learning experiences and knowledge acquisition. | H11: AIpowered learning models in EE are increasingly shifting from traditional static courses toward more personalized, immersive, and datadriven approaches, which may contribute to improved student learning experiences and knowledge acquisition. | I11: Toward understanding the role of generative AI in entrepreneurship education: A systematic review, p. 14 | J11: =TRUE() -> TRUE | K11: =FALSE() -> FALSE | M11: definition | N11: medium | O11: teaching_learning | P11: 5 | Q11: 4 | R11: The answer restates the evidence almost verbatim, covering both the shift toward personalized, immersive, data-driven approaches and the potential benefit. It adds nothing beyond what the evidence says. | The question names its topic, AI-powered learning models in entrepreneurship education, explicitly and does not refer to any unseen source. | value: This is useful domain knowledge about how AI is changing pedagogy in one specific field of higher education. | S11: How are AI-powered learning models in entrepreneurship education changing compared with traditional courses, and what may this improve? | T11: What change is occurring in entrepreneurship education learning models powered by AI, and what outcomes might it contribute to? | U11: pilot | V11: toward-understanding-the-role-of-generative-ai:0024:q3 | W11: accept
A12: 11 | B12: =TRUE() -> TRUE | F12: How might cultural and contextual settings affect the effectiveness of generative-AI-enabled entrepreneurship education, and which macro-level factors are proposed as influences? | G12: The effectiveness of generative-AI-enabled entrepreneurship education is proposed to vary across cultural and contextual settings. This variation is influenced by macro-level factors such as government support, economic conditions, and cultural norms. | H12: Research Proposition 2: The effectiveness of GAI-enabled EE varies across cultural and contextual settings, influenced by macro-level factors such as government support, economic conditions, and cultural norms. Future research could apply HLM and Hofstede's Cultural Dimensions Theory to examine how uncertainty avoidance, collectivism, and digital infrastructure moderate learners' trust in GAI and their collaborative behaviors. | I12: Toward understanding the role of generative AI in entrepreneurship education: A systematic review, p. 19 | J12: =TRUE() -> TRUE | K12: =TRUE() -> TRUE | M12: explanation | N12: medium | O12: equity_accessibility | P12: 5 | Q12: 4 | R12: The answer directly restates Research Proposition 2, including the three macro-level factors named in the evidence. | The question names its topic by content and has no source references or undefined acronyms. | value: This is a useful proposition about contextual influences on AI-enabled entrepreneurship education, though somewhat specific. | S12: In what way could cultural and contextual settings change how effective generative-AI-enabled entrepreneurship education is, and which macro-level factors are proposed to influence it? | T12: Which macro-level factors are proposed to make the effectiveness of generative-AI-enabled entrepreneurship education vary across cultural and contextual settings? | U12: pilot | V12: toward-understanding-the-role-of-generative-ai:0033:q4 | W12: accept
A13: 12 | B13: =TRUE() -> TRUE | F13: What does the AI competency work of Celik (2023) do with the TPACK model, and what is its purpose? | G13: Celik (2023) extended the TPACK model to include AI competencies for teacher development. | H13: Celik (2023) extended the TPACK model to include AI competencies for teacher development, while Long and Magerko (2020) focusing on K-12 and Carolus et al. (2023) focusing on citizens' competencies, using literature reviews to shape their frameworks. | I13: Be AIware! An AI Competency Model for K-12 Education, p. 3 | J13: =TRUE() -> TRUE | K13: =FALSE() -> FALSE | M13: definition | N13: medium | O13: faculty_readiness | P13: 5 | Q13: 4 | R13: The answer directly restates the evidence that Celik (2023) extended TPACK to include AI competencies for teacher development. | The question names a specific study (Celik 2023) and a named model, and it does not refer to unseen context. TPACK is a widely known acronym in educational technology. | value: It is useful domain knowledge about an AI competency framework for teacher development. | S13: How did Celik (2023) extend the TPACK model, and for what purpose? | T13: What addition did Celik (2023) make to the TPACK model, and what was it meant to support? | U13: pilot | V13: be-aiware-an-ai-competency-model-for-k-12:0004:q1 | W13: accept
A14: 13 | B14: =TRUE() -> TRUE | F14: Why must general claims of AI grading efficacy be tempered by task-specific evaluation? | G14: AI grading performance varies by task type, discipline, and contextual alignment with assessment rubrics. Because of this variation, general claims of AI efficacy must be tempered by task-specific evaluation. AI performs reliably in structured tasks, but its accuracy declines in open-ended or creative assignments that require nuanced contextual understanding. | H14: Empirical evidence indicates that AI grading performance varies by task type, discipline, and contextual alignment with assessment rubrics, suggesting that general claims of AI efficacy must be tempered by task-specific evaluation (Condor, 2024). … While AI performs reliably in structured tasks, its accuracy declines in openended or creative assignments, where nuanced contextual understanding is required (Lo et al., 2025). | I14: Reliable but not rigorous: Evaluating ChatGPT's reliability, validity, and bias in automated academic grading, p. 2 | J14: =TRUE() -> TRUE | K14: =TRUE() -> TRUE | M14: explanation | N14: medium | O14: assessment | P14: 4 | Q14: 4 | R14: Every statement is supported by the evidence. The answer only lightly rewords the source and adds a causal link that the evidence's "suggesting that" already implies. | The question is self-contained and clear without needing the source. | value: This is useful knowledge about the limits of AI grading reliability in assessment. | S14: Why should broad claims that AI grading works be qualified by evaluating specific tasks? | T14: What reason is there for qualifying general claims about the efficacy of AI grading through task-specific evaluation? | U14: extra:assessment | V14: reliable-but-not-rigorous-evaluating-chatgpt-s:0002:q3 | W14: accept
A15: 14 | B15: =TRUE() -> TRUE | F15: Why does a lack of comprehensive frameworks for preparing faculty for AI matter for higher education institutions? | G15: Many higher education institutions lack comprehensive frameworks to prepare faculty for emerging technological challenges such as AI. This gap undermines their ability to integrate AI into teaching, research, and service, thereby constraining institutional responsiveness to societal needs. | H15: Despite their strategic role, many HEIs lack comprehensive frameworks to prepare faculty for emerging technological challenges such as artificial intelligence. This gap undermines their ability to integrate AI into teaching, research, and service, thereby constraining institutional responsiveness to societal needs (Sued, 2022). | I15: Stakeholder engagement and strategic innovation in higher education through AI competency, p. 4 | J15: =TRUE() -> TRUE | K15: =FALSE() -> FALSE | M15: explanation | N15: medium | O15: faculty_readiness | P15: 5 | Q15: 4 | R15: Both sentences of the answer restate the evidence almost word for word. Nothing is added. | The question is self-contained and does not refer to any source or unseen context. | value: It covers a relevant institutional point about faculty AI readiness and its consequences. | S15: What are the consequences for universities when they lack comprehensive frameworks to prepare faculty for AI? | T15: How does the absence of comprehensive faculty AI-preparation frameworks affect higher education institutions? | U15: extra:leadership_strategy | V15: stakeholder-engagement-and-strategic-innovation:0006:q3 | W15: accept
A16: 15 | B16: =TRUE() -> TRUE | F16: Why should faculty development be integrated as a governance strategy in higher education institutions? | G16: Recognition of faculty as agents of transformation must be translated into capacity-building initiatives and resource allocation that enable faculty to act effectively. When integrated as a governance strategy, faculty development strengthens institutional capacity to address external challenges and contributes to broader societal and economic goals. | H16: In the context of AI, this recognition must be translated into capacity-building initiatives and resource allocation that enable faculty to act effectively. Faculty development, when integrated as a governance strategy, strengthens institutional capacity to address external challenges and contributes to broader societal and economic goals (Syed et al., 2024). | I16: Stakeholder engagement and strategic innovation in higher education through AI competency, p. 4 | J16: =TRUE() -> TRUE | K16: =FALSE() -> FALSE | M16: explanation | N16: medium | O16: governance | P16: 4 | Q16: 4 | R16: The evidence supports the answer. The answer only adds "of faculty as agents of transformation" to define the recognition, which the evidence implies but does not quote. It also drops the "in the context of AI" qualifier. | The question is clear without the source and does not refer to any unseen context. | value: This is a useful institutional governance point about building faculty capacity for AI. | S16: How does treating faculty development as a governance strategy benefit universities? | T16: What is the benefit of integrating faculty development into the governance of higher education institutions? | U16: extra:leadership_strategy | V16: stakeholder-engagement-and-strategic-innovation:0006:q4 | W16: accept
A17: 16 | B17: =TRUE() -> TRUE | F17: In Peruvian law schools, what function do free legal aid clinics often serve for students? | G17: Free legal aid clinics often function as alternatives to internships, where students can get educational credit and recognition for internship work. This was the case in 27 institutions. | H17: First, it is interesting to note that of the 31 institutions surveyed, only 3 have implemented public interest clinics, while the remainder have opted for free legal aid clinics. The latter often function as alternatives to internships, where students can get educational credit and recognition for internship work (27 institutions). | I17: Socially Responsible Higher Education, p. 222 | J17: =FALSE() -> FALSE | K17: =FALSE() -> FALSE | L17: low_value(2) | M17: definition | N17: easy | O17: teaching_learning | P17: 5 | Q17: 2 | R17: Every statement in the answer is directly stated in the evidence. This includes the alternative-to-internship function, the educational credit and recognition, and the figure of 27 institutions. | The question names its context (Peruvian law schools, free legal aid clinics) and does not rely on any unseen source. | value: This is a narrow detail about Peruvian legal clinical education, with no connection to AI or responsible AI. | S17: What role do free legal aid clinics often play for students at Peruvian law schools? | T17: How do Peruvian law students often use free legal aid clinics in relation to internships? | U17: pilot | V17: budd-l-hall-rajesh-2021-socially-responsible:0120:q2 | W17: reject | X17: low_value | Y17: Agree with filter (low value).
A18: 17 | B18: =TRUE() -> TRUE | F18: Which areas of law do Peruvian free legal aid clinics cover most, and how many of 31 clinics deal with civil law? | G18: Of the 31 clinics, 24 provided services in family law and 16 provided representation in criminal law cases. Only 15 indicated that they deal with civil law cases, an unusual number given that civil law is the most common area of practice in Peru. | H18: Out of the 31 clinics, 24 free legal aid clinics provided services in family law and 16 provided representation in criminal law cases. Surprisingly, only 15 of the clinics indicated that they deal with civil law cases - an unusual number given that civil law is the most common area of practice in Peru. | I18: Socially Responsible Higher Education, p. 223 | J18: =FALSE() -> FALSE | K18: =FALSE() -> FALSE | L18: not_standalone(judge);low_value(2) | M18: factual | N18: easy | O18: general | P18: 5 | Q18: 2 | R18: Every figure and the remark about civil law being Peru's most common area of practice are stated directly in the evidence. | The question refers to a specific sample of 31 clinics without naming the survey or study it comes from, so it presupposes unseen context. | value: These are sample-specific survey counts about Peruvian legal aid clinics, unrelated to responsible AI. | S18: Among 31 Peruvian free legal aid clinics, which legal areas are most common, and how many handle civil law cases? | T18: What areas of law do most Peruvian free legal aid clinics serve, and how many of the 31 take civil law cases? | U18: pilot | V18: budd-l-hall-rajesh-2021-socially-responsible:0120:q4 | W18: reject | X18: low_value | Y18: Agree with filter (low value).
A19: 18 | B19: =TRUE() -> TRUE | F19: According to a 2017 ENARSU Network study of 50 Peruvian universities, what share considered social responsibility in higher education a central pillar of their institution? | G19: Only 43% of the 50 universities surveyed considered social responsibility in higher education a central pillar in their institution. The same report found that only 36% were incorporating it into curriculums and campus life. | H19: In line with this finding, a 2017 study by Peru's ENARSU Network (Network of the National Meeting on Social Responsibility in Higher Education) found that only 43% of the 50 universities surveyed considered SRHEI as a central pillar in their institution (Stojnic Chávez & Jungbluth Melgar, 2017, p. 4). This last report also found that only 36% of universities studied were incorporating SRHEI into curriculums and campus life (Stojnic Chávez & Jungbluth Melgar, 2017, pp. 5-6). | I19: Socially Responsible Higher Education, p. 220 | J19: =FALSE() -> FALSE | K19: =FALSE() -> FALSE | L19: low_value(2) | M19: factual | N19: easy | O19: monitoring_improvement | P19: 5 | Q19: 2 | R19: Both the 43% figure and the 36% curriculum and campus-life figure are directly stated in the evidence. | The question names the specific study by year, network and sample, so it is clear without the source; ENARSU works as a proper name. | value: A single regional survey statistic on university social responsibility, only tangentially about AI in higher education. | S19: In the 2017 ENARSU Network survey of 50 Peruvian universities, what percentage treated social responsibility in higher education as a central pillar? | T19: What proportion of the 50 Peruvian universities surveyed by the ENARSU Network in 2017 regarded social responsibility in higher education as a central institutional pillar? | U19: pilot | V19: budd-l-hall-rajesh-2021-socially-responsible:0118:q1 | W19: reject | X19: low_value | Y19: Agree with filter (low value).
A20: 19 | B20: =TRUE() -> TRUE | F20: Which kinds of earlier, pre-2022 studies were considered eligible in a review of generative AI in entrepreneurship education? | G20: Earlier studies were eligible if they focused on algorithmic foundations, prototype generative systems, or theoretical frameworks directly relevant to the functionalities later embodied in generative tools. This applied particularly to those published prior to 2022, before the public release of large-scale GAI platforms such as ChatGPT and DALL-E. | H20: Earlier studies that focused on algorithmic foundations, prototype generative systems, or theoretical frameworks directly relevant to the functionalities later embodied in generative tools were considered eligible for inclusion particularly those published prior to 2022, before the public release of large-scale GAI platforms such as ChatGPT and DALL-E. | I20: Toward understanding the role of generative AI in entrepreneurship education: A systematic review, p. 3 | J20: =FALSE() -> FALSE | K20: =FALSE() -> FALSE | L20: low_value(2) | M20: definition | N20: medium | O20: general | P20: 5 | Q20: 2 | R20: The answer restates the evidence nearly verbatim: the three study types, the pre-2022 timing, and the reference to ChatGPT and DALL-E. | The question names the review by its topic (generative AI in entrepreneurship education), which is acceptable, and it uses no source-dependent wording. | value: This covers review inclusion criteria, which is research methodology and of low domain value. | S20: What types of studies published before 2022 counted as eligible in a review of generative AI in entrepreneurship education? | T20: In a review on generative AI in entrepreneurship education, which earlier studies were eligible for inclusion? | U20: pilot | V20: toward-understanding-the-role-of-generative-ai:0005:q2 | W20: reject | X20: low_value | Y20: Agree with filter (low value).
A21: 20 | B21: =TRUE() -> TRUE | F21: What method did Leidig et al. (2020) use to ensure expert consensus on digital competencies for information systems programs? | G21: Leidig et al. (2020) used a Delphi method, ensuring expert consensus on digital competencies for information systems programs. | H21: Ng et al. (2023) addressed post-pandemic education through a literature review, while Leidig et al. (2020) used a Delphi method, ensuring expert consensus on digital competencies for information systems programs. | I21: Be AIware! An AI Competency Model for K-12 Education, p. 3 | J21: =FALSE() -> FALSE | K21: =FALSE() -> FALSE | L21: low_value(2) | M21: factual | N21: easy | O21: general | P21: 5 | Q21: 2 | R21: The answer restates the evidence almost verbatim: Leidig et al. (2020) used a Delphi method to ensure expert consensus. | The question names the specific study by its authors and topic, and it does not refer to any unseen context. | value: The pair concerns the research methodology of a single study, which has low domain value. | S21: How did Leidig et al. (2020) achieve expert consensus on digital competencies for information systems programs? | T21: Which method did Leidig et al. (2020) employ to establish expert agreement on digital competencies for information systems programs? | U21: pilot | V21: be-aiware-an-ai-competency-model-for-k-12:0004:q4 | W21: reject | X21: low_value | Y21: Agree with filter (low value).
A22: 21 | B22: =FALSE() -> FALSE | F22: A ministry of education in Argentina wants to improve inclusion in universities and notes that enrollment has grown steadily. Which inclusion policies has Argentina relied on, and what problem persists among lower-income young people? | G22: Argentina's main inclusion policies in university education have been territorial expansion of offerings and sustained enrollment growth, along with some scholarship and tutoring programmes. Even so, dropout remains high, particularly among young people from lower-income socioeconomic sectors. | H22: One of the main policies of inclusion in the Argentine university system has been the territorial expansion of offerings and the sustained increase in enrollment, along with some scholarship and tutoring programmes for courses. … However, as García de Fanelli (2014, p. 290) points out, levels of abandonment are high, particularly for young people from lower-income socioeconomic sectors, given that "[higher education] is associated with the cultural capital of the family and with the possibilities of young people having access to quality high school education". | I22: Socially Responsible Higher Education, p. 50 | J22: =TRUE() -> TRUE | K22: =FALSE() -> FALSE | M22: application | N22: hard | O22: equity_accessibility | P22: 4 | Q22: 3 | R22: Every claim in the answer matches the evidence: territorial expansion, enrollment growth, scholarships and tutoring, and high dropout among lower-income youth. 'Dropout' is only a trivial rewording of 'abandonment'. | The question sets up its own scenario and names Argentina directly, with no reference to an unseen source. | value: Higher education inclusion policy is relevant context, but the pair covers one country only and is not about AI. | S22: An Argentine education ministry sees steadily rising university enrollment and wants greater inclusion. What main inclusion policies has the country used, and what difficulty remains for young people from lower-income backgrounds? | T22: Suppose Argentine policymakers review university inclusion after years of enrollment growth. Which policies have been the main inclusion tools, and what issue still affects lower-income youth? | U22: pilot | V22: budd-l-hall-rajesh-2021-socially-responsible:0027:q0 | W22: accept | Y22: Non-AI content (Socially Responsible HE book); these chunks have ai_score=0 and are excluded from full_v1 anyway.
A23: 22 | B23: =FALSE() -> FALSE | F23: Why does dropout from Argentine higher education remain high among young people from lower-income sectors? | G23: According to García de Fanelli, higher education is associated with the cultural capital of the family and with the possibilities of young people having access to quality high school education. Because of this, levels of abandonment are high, particularly for young people from lower-income socioeconomic sectors. | H23: However, as García de Fanelli (2014, p. 290) points out, levels of abandonment are high, particularly for young people from lower-income socioeconomic sectors, given that "[higher education] is associated with the cultural capital of the family and with the possibilities of young people having access to quality high school education". | I23: Socially Responsible Higher Education, p. 50 | J23: =TRUE() -> TRUE | K23: =FALSE() -> FALSE | M23: explanation | N23: medium | O23: equity_accessibility | P23: 5 | Q23: 3 | R23: The answer directly restates the evidence's causal explanation (family cultural capital and access to quality high school education) and attributes it to García de Fanelli. | The question is self-contained and clearly asks about the causes of dropout among lower-income youth in Argentine higher education. | value: It concerns the institutional equity context of higher education but is narrow and not about AI. | S23: Why do lower-income young people in Argentina continue to drop out of higher education at high levels? | T23: What accounts for the continued high dropout rates in Argentine higher education among young people from lower-income sectors? | U23: pilot | V23: budd-l-hall-rajesh-2021-socially-responsible:0027:q1 | W23: accept | Y23: Non-AI content (Socially Responsible HE book); these chunks have ai_score=0 and are excluded from full_v1 anyway.
A24: 23 | B24: =FALSE() -> FALSE | F24: Why do Brazilian higher education institutions differ so much and why do the students who access them face unequal conditions? | G24: The historical evolution of Brazil's national higher education system was marked by structuring inequalities in the country's economic, social and cultural formation. These inequalities were decisive in the complexity and heterogeneity of institutions and in the inequality of the students who accessed that level of schooling. | H24: Higher education in Brazil began late, compared to other Latin American countries. The establishment of the first university, the University of Brazil, dates back to 1920. The historical evolution of the national system of higher education was marked by the structuring inequalities in Brazil's economic, social and cultural formation, which were decisive in the complexity and heterogeneity of institutions and in the inequality of the students who accessed that level of schooling. | I24: Socially Responsible Higher Education, p. 50 | J24: =TRUE() -> TRUE | K24: =FALSE() -> FALSE | M24: explanation | N24: medium | O24: equity_accessibility | P24: 5 | Q24: 3 | R24: Both sentences of the answer directly restate the evidence's claim that structuring inequalities in Brazil's economic, social and cultural formation shaped institutional heterogeneity and student inequality. | The question names Brazil and higher education explicitly and does not refer to any unseen source. | value: This is institutional context for higher education, but it is narrow and not specifically about AI. | S24: What historical factor made Brazil's higher education institutions complex and heterogeneous and its students unequal? | T24: How did Brazil's historical formation lead to institutional heterogeneity and unequal student access in higher education? | U24: pilot | V24: budd-l-hall-rajesh-2021-socially-responsible:0027:q2 | W24: accept | Y24: Non-AI content (Socially Responsible HE book); these chunks have ai_score=0 and are excluded from full_v1 anyway.
A25: 24 | B25: =FALSE() -> FALSE | F25: How are Brazilian higher education institutions divided between public and private types? | G25: Public institutions (federal, state or municipal) belong to the state, and registration in them is free of charge, as determined by the Federal Constitution of 1988. Private institutions may be for-profit or non-profit, or even denominational. | H25: Public institutions (federal, state or municipal) belong to the state, and registrations to it are free of charge, as determined in the Federal Constitution of 1988, while private institutions may be for-profit or non-profit (or even denominational). | I25: Socially Responsible Higher Education, p. 50 | J25: =TRUE() -> TRUE | K25: =FALSE() -> FALSE | M25: definition | N25: easy | O25: general | P25: 5 | Q25: 3 | R25: Every statement in the answer is directly stated in the evidence: public types, free enrollment under the 1988 Constitution, and the private for-profit, non-profit and denominational types. | The question names Brazil and the topic explicitly and does not depend on any unseen source. | value: This is institutional context relevant to higher education, but it is narrow and not about AI. | S25: What are the categories of public and private higher education institutions in Brazil? | T25: In Brazil, how is the higher education sector split between public and private institutions? | U25: pilot | V25: budd-l-hall-rajesh-2021-socially-responsible:0027:q3 | W25: accept | Y25: Non-AI content (Socially Responsible HE book); these chunks have ai_score=0 and are excluded from full_v1 anyway.
A26: 25 | B26: =FALSE() -> FALSE | F26: What does Article 130 of Peru's Law 30220 require every university to create? | G26: Article 130 obliges every Peruvian university to create a University Social Service Programme (Programa de Servicio Social Universitario). Through it, students apply knowledge in a way that improves the quality of life of people in traditionally marginalised groups. | H26: Article 130 establishes the obligation to implement SRHEI. Per this article, every university should create a Programa de Servicio Social Universitario (University Social Service Programme), through which students apply knowledge in a way that improves the quality of life of people in traditionally marginalised groups. | I26: Socially Responsible Higher Education, p. 220 | J26: =TRUE() -> TRUE | K26: =FALSE() -> FALSE | M26: factual | N26: easy | O26: governance | P26: 4 | Q26: 3 | R26: The answer restates the evidence closely; 'obliges' slightly strengthens the evidence's 'should', which is trivial given the article establishes an obligation. | The question names the specific law and article and does not rely on unseen context. | value: This is a narrow, country-specific legal detail about university social responsibility, not about AI directly. | S26: Under Article 130 of Peru's Law 30220, what programme must each university set up? | T26: Which programme does Article 130 of Peruvian Law 30220 oblige all universities to implement? | U26: pilot | V26: budd-l-hall-rajesh-2021-socially-responsible:0118:q0 | W26: accept | Y26: Non-AI content (Socially Responsible HE book); these chunks have ai_score=0 and are excluded from full_v1 anyway.
A27: 26 | B27: =FALSE() -> FALSE | F27: What did a 2018 study by the Latin American Social Responsibility in Higher Education Union (URSULA) find about how Peruvian universities executed socially responsible initiatives? | G27: A 2018 study by the Latin American Social Responsibility in Higher Education Union (URSULA) found that all 18 Peruvian universities surveyed had difficulty executing socially responsible initiatives, with results below the regional average. | H27: In fact, a 2018 study by Unión de Responsabilidad Social Universitaria Latinoamericana - URSULA (Latin American Social Responsibility in Higher Education Union) found that all 18 Peruvian universities surveyed had difficulty in executing socially responsible initiatives, with results below the regional average (p. 17). | I27: Socially Responsible Higher Education, p. 220 | J27: =TRUE() -> TRUE | K27: =TRUE() -> TRUE | M27: factual | N27: easy | O27: leadership_strategy | P27: 5 | Q27: 3 | R27: The answer restates the evidence exactly: all 18 Peruvian universities surveyed had difficulty, with results below the regional average. | The question names the specific study and organization by its content, so it is clear without the source. | value: It is a narrow, region-specific finding about university social responsibility and is only tangentially about AI. | S27: What were the findings of the 2018 Latin American Social Responsibility in Higher Education Union (URSULA) study on Peruvian universities' execution of socially responsible initiatives? | T27: What was the finding of the Latin American Social Responsibility in Higher Education Union (URSULA) in its 2018 study regarding the way Peruvian universities carried out socially responsible initiatives? | U27: pilot | V27: budd-l-hall-rajesh-2021-socially-responsible:0118:q2 | W27: accept | Y27: Non-AI content (Socially Responsible HE book); these chunks have ai_score=0 and are excluded from full_v1 anyway.
A28: 27 | B28: =FALSE() -> FALSE | F28: A Peruvian university plans to meet its legal duties under Law 30220 only by managing the impact of its operations, as in Article 124. Would this satisfy the Act, given the principles and obligations in Articles 5, 6 and 130? | G28: Scholars analysing Law 30220 posit that the Act obliges all universities to construct all their programmes with a social responsibility component. They argue that a university focusing strictly on managing impact, as per Article 124 read on its own, would not be compliant with the principles and obligations set out in Articles 5, 6 and 130. Articles 5 and 6 make pluralism, inclusion, intercultural dialogue and commitment to the country's development guiding principles, and Article 130 obliges every university to create a University Social Service Programme. | H28: Taking the values set out in Articles 5 and 6 as a starting point, we posit that the Act in fact obliges all universities to construct all their programmes with a social responsibility component. This because if a university were to focus strictly on managing impact, as per article 124 of the Act read on its own, it would not be compliant of the principles and obligations set out in Articles 5, 6 and 130. … Articles 5 and 6 establish that pluralism, inclusion, intercultural dialogue and commitment to the country's development are the guiding principles of higher education, and universities should strive to interact with the community and engage in socially relevant teaching and research. … Article 130 establishes the obligation to implement SRHEI. Per this article, every university should create a Programa de Servicio Social Universitario (University Social Service Programme), through which students apply knowledge in a way that improves the quality of life of people in traditionally marginalised groups. | I28: Socially Responsible Higher Education, pp. 219-220 | J28: =TRUE() -> TRUE | K28: =TRUE() -> TRUE | M28: application | N28: hard | O28: governance | P28: 5 | Q28: 4 | R28: Every statement in the answer is directly stated in the evidence. This covers the claim that all programmes need a social responsibility component, the non-compliance of a strict impact-management approach, the guiding principles in Articles 5 and 6, and the University Social Service Programme required by Article 130. | The question names Law 30220 and the specific articles. It is understandable without having seen the source. | value: This is useful but somewhat jurisdiction-specific knowledge about how Peruvian law frames university social responsibility. | S28: If a university in Peru focuses strictly on impact management under Article 124 of Law 30220, would that comply with the Act's principles and obligations in Articles 5, 6 and 130? | T28: Would a Peruvian university that relies solely on managing its impact per Article 124 of Law 30220 be compliant, considering Articles 5, 6 and 130? | U28: pilot | V28: budd-l-hall-rajesh-2021-socially-responsible:0118:q3 | W28: accept | Y28: Non-AI content (Socially Responsible HE book); these chunks have ai_score=0 and are excluded from full_v1 anyway.
A29: 28 | B29: =FALSE() -> FALSE | F29: Why has implementation of the social responsibility obligations in Peru's Law 30220 been uneven and difficult? | G29: This may be due in large part to the lack of further regulations, policies or government-sponsored programmes accompanying the Act. Universities without the necessary expertise or resources to create or enhance such programmes received no state-sponsored support. | H29: However, the obligations set out in the Act have had a disparate and difficult implementation. This may be due in large part to the lack of further regulations, policies or government sponsored programmes to accompany the Act. Where universities did not have the necessary expertise or resources to create or enhance SRHEI programmes within their institutions, there was no statesponsored support for their implementation. | I29: Socially Responsible Higher Education, p. 220 | J29: =TRUE() -> TRUE | K29: =FALSE() -> FALSE | M29: factual | N29: easy | O29: leadership_strategy | P29: 4 | Q29: 3 | R29: The answer restates the evidence closely, with only minor rewording (e.g., 'such programmes' for SRHEI programmes). | The question names Peru's Law 30220 and its social responsibility obligations explicitly and does not rely on any unseen source. | value: University social responsibility policy is relevant institutional context, but this is a narrow, country-specific point that is not about AI. | S29: What is the main suggested reason for the disparate and difficult implementation of Law 30220's social responsibility obligations in Peru? | T29: Why have Peruvian universities struggled to implement the social responsibility duties set by Law 30220? | U29: pilot | V29: budd-l-hall-rajesh-2021-socially-responsible:0118:q4 | W29: accept | Y29: Non-AI content (Socially Responsible HE book); these chunks have ai_score=0 and are excluded from full_v1 anyway.
A30: 29 | B30: =FALSE() -> FALSE | F30: How are the top 300 universities in the Times Higher Education World University Rankings distributed geographically? | G30: Of the purportedly top 300 universities, 270 (90%) are located in Europe, North America, Australia and New Zealand. Of the remainder, 25 are from a small number of East Asian countries and only 5 are from the rest of the world. The entire continent of Africa is represented by three institutions, all in South Africa, and there is only one university from the whole of Latin America, one from the Middle East, and none from Central Asia. | H30: Taking the Times Higher Education (THE) World University Rankings (THE, 2020) as an example, of the purportedly 'top 300' universities in the world, 270 (90%) are located in Europe, North America, Australia and New Zealand. Of the remainder, 25 are from a small number of East Asian countries and there are only 5 from the rest of the world. … The entire continent of Africa is represented by three institutions, all of which are in South Africa. There is only one university from the whole of Latin America, one from the Middle East, and not a single institution from Central Asia. | I30: Socially Responsible Higher Education, p. 95 | J30: =TRUE() -> TRUE | K30: =TRUE() -> TRUE | M30: definition | N30: medium | O30: equity_accessibility | P30: 5 | Q30: 3 | R30: Every figure and claim in the answer is stated directly in the evidence, with only minor rewording. | The question names the specific ranking explicitly and needs no other context, though it omits the 2020 edition year. | value: It illustrates global inequity in higher education rankings, which is relevant context but a fairly specific data point. | S30: What does the geographic distribution of the top 300 universities in the Times Higher Education World University Rankings look like? | T30: In the Times Higher Education World University Rankings, where are the top 300 universities located? | U30: pilot | V30: budd-l-hall-rajesh-2021-socially-responsible:0055:q0 | W30: accept | Y30: Non-AI content (Socially Responsible HE book); these chunks have ai_score=0 and are excluded from full_v1 anyway.
A31: 30 | B31: =FALSE() -> FALSE | F31: A university leader in Nairobi is told that global rankings are a neutral measure of quality and that their institution should simply accept its absence from the top. What do the Times Higher Education rankings' geographic patterns and the message they imply say about this claim? | G31: In the Times Higher Education rankings, the whole of Africa is represented by only three institutions, all in South Africa, and the ARWU and QS rankings are only a few percentage points more geographically inclusive. The message these rankings send is that 'world class' status, quality or excellence are highly concentrated in specific places and, by implication, not present in others. | H31: The entire continent of Africa is represented by three institutions, all of which are in South Africa. There is only one university from the whole of Latin America, one from the Middle East, and not a single institution from Central Asia. … THE is not alone in this bias - the Academic Ranking of World Universities (ARWU, 2019) and QS World University Rankings (QS, 2019) are more geographically inclusive, but only by a few percentage points. … The message seems clear - 'world class' status, 'quality', or 'excellence' are highly concentrated in specific places. It is therefore, by implication, not present in others. | I31: Socially Responsible Higher Education, pp. 95-96 | J31: =TRUE() -> TRUE | K31: =FALSE() -> FALSE | M31: application | N31: hard | O31: equity_accessibility | P31: 4 | Q31: 4 | R31: Every statement is in the evidence. Tying the Africa count to Times Higher Education specifically is inferred from 'THE is not alone in this bias' rather than stated outright. | The scenario is self-contained and names the Times Higher Education rankings explicitly, with no reference to an unseen source. | value: It covers a useful critique of geographic bias in global university rankings and its implications for institutions outside the top. | S31: A Kenyan university leader hears that world rankings neutrally measure quality and that being absent from the top is just a fact. What do the geographic patterns of the Times Higher Education rankings and their implied message say about it? | T31: A Nairobi university leader hears that global rankings objectively measure quality and that the institution should just accept not being near the top. What do the geographic patterns in the Times Higher Education rankings, and the message they imply, say about that claim? | U31: pilot | V31: budd-l-hall-rajesh-2021-socially-responsible:0055:q1 | W31: accept | Y31: Non-AI content (Socially Responsible HE book); these chunks have ai_score=0 and are excluded from full_v1 anyway.
A32: 31 | B32: =FALSE() -> FALSE | F32: In critiques of global university rankings such as the Times Higher Education World University Rankings, what does it mean to say that rankings are a question of sovereignty and control? | G32: It means that the balance of power, and therefore status and funding, rests in the hands of a small minority of majority white countries and institutions. | H32: As we will see, rankings are a question of sovereignty, of control, where the balance of power - and therefore status and funding - rests in the hands of a small minority of majority white countries and institutions. | I32: Socially Responsible Higher Education, p. 96 | J32: =TRUE() -> TRUE | K32: =TRUE() -> TRUE | M32: definition | N32: medium | O32: equity_accessibility | P32: 5 | Q32: 3 | R32: The answer restates the evidence almost verbatim: the balance of power, and therefore status and funding, rests with a small minority of majority white countries and institutions. | The question names the topic (critiques of global university rankings such as the Times Higher Education rankings) and needs no unseen source to be understood. | value: It is relevant institutional context about higher education power structures, but only loosely tied to AI and fairly narrow. | S32: What is meant by describing global university rankings as a matter of sovereignty and control? | T32: When global university rankings are called a question of sovereignty and control, what does that claim mean? | U32: pilot | V32: budd-l-hall-rajesh-2021-socially-responsible:0055:q3 | W32: accept | Y32: Non-AI content (Socially Responsible HE book); these chunks have ai_score=0 and are excluded from full_v1 anyway.
A33: 32 | B33: =FALSE() -> FALSE | F33: What is the message about 'world class' status that global university rankings imply, given how concentrated their top universities are? | G33: The message seems to be that 'world class' status, quality or excellence are highly concentrated in specific places. By implication, they are not present in others. | H33: The message seems clear - 'world class' status, 'quality', or 'excellence' are highly concentrated in specific places. It is therefore, by implication, not present in others. | I33: Socially Responsible Higher Education, p. 96 | J33: =TRUE() -> TRUE | K33: =FALSE() -> FALSE | M33: definition | N33: medium | O33: equity_accessibility | P33: 4 | Q33: 4 | R33: The answer closely restates the evidence, changing only 'seems clear' to 'seems'. That is trivial rewording. | The question names global university rankings and their concentration. It does not depend on any unseen source. | value: It gives a useful critical insight into global rankings in higher education, though it is only loosely tied to AI. | S33: What do global university rankings imply about where 'world class' quality or excellence is found? | T33: Given how concentrated the top universities in global rankings are, what message do those rankings convey about what counts as 'world class' status? | U33: pilot | V33: budd-l-hall-rajesh-2021-socially-responsible:0055:q4 | W33: accept | Y33: Non-AI content (Socially Responsible HE book); these chunks have ai_score=0 and are excluded from full_v1 anyway.
A34: 33 | B34: =FALSE() -> FALSE | F34: A university is deploying an AI system that handles student financial aid records, and it wants the system's decisions to be trustworthy without exposing sensitive financial data. What approaches can it use to balance transparency and confidentiality? | G34: Data masking can be used, which conceals confidential information in a way that does not affect the overall outcome of the decision-making process, helping the system stay transparent while protecting confidential data. Another approach is to use explainable AI models that explain the system's decisions without revealing confidential data. | H34: This can be achieved through techniques such as data masking, where confidential information is concealed in a way that does not affect the overall outcome of the decisionmaking process. … Another approach is to use explainable AI models that provide an explanation for the decisions made by the system without revealing confidential data [94, 95]. | I34: Towards Ethical and Socially Responsible Explainable AI, p. 103 | J34: =TRUE() -> TRUE | K34: =FALSE() -> FALSE | M34: application | N34: hard | O34: privacy_security | P34: 4 | Q34: 4 | R34: Both techniques, data masking and explainable AI, are stated in the evidence. The phrase "helping the system stay transparent while protecting confidential data" is a minor connective gloss implied by the context. | The question sets up a self-contained scenario and does not refer to any source. | value: These are useful, practical techniques for balancing transparency and privacy in AI systems used in higher education. | S34: A university's AI system processes sensitive student financial aid data. How can the institution remain transparent about decisions while keeping that data confidential? | T34: What techniques can a university use so that an AI system working with confidential student financial records stays transparent while protecting the data? | U34: pilot | V34: towards-ethical:0051:q0 | W34: accept
A35: 34 | B35: =FALSE() -> FALSE | F35: Why does the required level of transparency in an AI system depend on the context in which it is used? | G35: The level of transparency required varies with context. In areas such as medical diagnosis or financial decision-making, a high level of transparency may be necessary to build trust and ensure accountability. In areas such as national security or defense, confidentiality may be paramount, and transparency may need to be limited to protect sensitive information. | H35: For example, the level of transparency required may vary depending on the context in which the AI system is used. In some cases, such as medical diagnosis or financial decision-making, a high level of transparency may be necessary to build trust and ensure accountability. In other cases, such as national security or defense, confidentiality may be paramount, and transparency may need to be limited to protect sensitive information [1, 9, 12]. | I35: Towards Ethical and Socially Responsible Explainable AI, p. 104 | J35: =TRUE() -> TRUE | K35: =FALSE() -> FALSE | M35: explanation | N35: medium | O35: governance | P35: 5 | Q35: 4 | R35: Every statement in the answer closely restates the evidence. This covers the context-dependence of transparency, the medical and financial examples tied to trust and accountability, and the security and defense examples tied to confidentiality. | The question is self-contained and makes no reference to a source. | value: It is useful responsible-AI knowledge about the context-dependent trade-offs of transparency. | S35: Why can transparency requirements for AI differ from one application setting to another? | T35: How does the context of use change how much transparency an AI system needs? | U35: pilot | V35: towards-ethical:0051:q1 | W35: accept
A36: 35 | B36: =FALSE() -> FALSE | F36: Why is it essential to establish clear guidelines and standards for confidentiality and transparency in AI development and deployment? | G36: The definition of what constitutes confidential information may vary depending on the stakeholders involved. What a company considers confidential may differ from what a regulatory body or the public considers confidential. Therefore, clear guidelines and standards for confidentiality and transparency should be established in the development and deployment of AI systems. | H36: Another challenge is that the definition of what constitutes confidential information may vary depending on the stakeholders involved [96]. For example, what is considered confidential information by a company may be different from what is considered confidential information by a regulatory body or the public. Therefore, it is essential to establish clear guidelines and standards for confidentiality and transparency in the development and deployment of AI systems [97, 98]. | I36: Towards Ethical and Socially Responsible Explainable AI, p. 104 | J36: =TRUE() -> TRUE | K36: =FALSE() -> FALSE | M36: explanation | N36: medium | O36: governance | P36: 5 | Q36: 4 | R36: Every statement in the answer is directly stated in the evidence, with only minor rewording. | The question is self-contained and needs no reference to the source. | value: It covers a useful responsible-AI governance point about confidentiality versus transparency across stakeholders. | S36: Why do AI systems need clear standards on confidentiality and transparency? | T36: What challenge makes clear confidentiality and transparency guidelines necessary for AI systems? | U36: pilot | V36: towards-ethical:0051:q3 | W36: accept
A37: 36 | B37: =FALSE() -> FALSE | F37: Why do ethical and social responsibility practices matter for AI accountability beyond legal compliance? | G37: Beyond legal requirements, ethical and social responsibility considerations are paramount in AI development. Ethical guidelines and practices enhance accountability by addressing the broader societal impact of AI technologies. | H37: Beyond legal requirements, ethical and social responsibility considerations are paramount in AI development. Ethical guidelines and practices enhance accountability by addressing the broader societal impact of AI technologies. | I37: Towards Ethical and Socially Responsible Explainable AI, p. 172 | J37: =TRUE() -> TRUE | K37: =FALSE() -> FALSE | M37: explanation | N37: medium | O37: governance | P37: 5 | Q37: 4 | R37: The answer reproduces the evidence verbatim, so every statement is directly supported. | The question is self-contained and refers to no unseen source or context. | value: It covers a useful responsible-AI concept about accountability beyond legal compliance, though the treatment is fairly generic. | S37: In what way do ethics and social responsibility considerations strengthen AI accountability beyond what the law requires? | T37: Beyond meeting legal requirements, what is the importance of ethical and social responsibility practices for holding AI accountable? | U37: pilot | V37: towards-ethical:0090:q1 | W37: accept
A38: 37 | B38: =FALSE() -> FALSE | F38: A university's AI office wants to build ethical accountability into its AI projects. Which practices for assessing impacts and preparing staff apply? | G38: It should conduct ethical impact assessments to evaluate how AI systems may affect different societal groups, assessing potential risks and benefits and taking steps to minimize harm. It should also provide AI ethics training to developers, data scientists, and decision-makers involved in AI projects, fostering a culture of ethical awareness and responsibility within the organization. | H38: Ethical Impact Assessment: Conduct ethical impact assessments to evaluate how AI systems may affect different societal groups. Assess potential risks and benefits and take steps to minimize harm. … AI Ethics Training: Provide AI ethics training to developers, data scientists, and decision-makers involved in AI projects. Foster a culture of ethical awareness and responsibility within the organization. | I38: Towards Ethical and Socially Responsible Explainable AI, p. 172 | J38: =TRUE() -> TRUE | K38: =FALSE() -> FALSE | M38: application | N38: hard | O38: governance | P38: 5 | Q38: 4 | R38: Every statement in the answer is taken almost verbatim from the evidence on ethical impact assessments and AI ethics training. | The question names a clear scenario and asks for specific practices without referring to any unseen source. | value: Concrete responsible-AI governance practices that are relevant to university AI offices. | S38: What ethical accountability practices on impact assessment and staff preparation should a university AI office adopt for its AI projects? | T38: A university AI office aims to embed ethical accountability in its AI work. What should it do regarding impact assessment and training? | U38: pilot | V38: towards-ethical:0090:q2 | W38: accept
A39: 38 | B39: =FALSE() -> FALSE | F39: What three elements does accountability in AI development and deployment encompass? | G39: Accountability is a fundamental principle in the development and deployment of AI systems. It encompasses legal and regulatory compliance, ethical considerations, and defining liability and responsibility. | H39: Accountability is a fundamental principle in the development and deployment of AI systems. It encompasses legal and regulatory compliance, ethical considerations, and defining liability and responsibility [4, 9, 12, 14, 27]. | I39: Towards Ethical and Socially Responsible Explainable AI, p. 171 | J39: =TRUE() -> TRUE | K39: =FALSE() -> FALSE | M39: factual | N39: easy | O39: governance | P39: 5 | Q39: 4 | R39: The answer restates the evidence verbatim, without adding any claims. | The question is self-contained and does not refer to any unseen source. | value: It covers a core responsible-AI principle, though the list is fairly specific. | S39: In the development and deployment of AI, what are the three components that make up accountability? | T39: Accountability in AI development and deployment is made up of which three elements? | U39: pilot | V39: towards-ethical:0090:q3 | W39: accept
A40: 39 | B40: =FALSE() -> FALSE | F40: Why does the PAGER scoping review of ChatGPT in nursing education say that developing technical and ethical competencies is crucial? | G40: Developing technical and ethical competencies is crucial especially for upholding academic integrity and ensuring equitable student access. Systematic documentation and evaluation of implementation experiences will contribute to developing best practices, and cross-institutional collaboration should be encouraged to share strategies and lessons learned. | H40: Systematic documentation and evaluation of implementation experiences will contribute to developing best practices. Developing technical and ethical competencies is crucial, especially for upholding academic integrity and ensuring equitable student access. Cross-institutional collaboration should be encouraged to share implementation strategies and lessons learned. | I40: Patterns, advances, and gaps in using ChatGPT and similar technologies in nursing education: A PAGER scoping review, p. 8 | J40: =TRUE() -> TRUE | K40: =FALSE() -> FALSE | M40: explanation | N40: medium | O40: faculty_readiness | P40: 5 | Q40: 4 | R40: Every statement in the answer restates the evidence nearly verbatim. The extra points on documentation and cross-institutional collaboration are also stated in the evidence, though they go beyond the question. | The question names a specific study, the PAGER scoping review of ChatGPT in nursing education, by its content, so a reader without the source understands what is asked. | value: It gives a useful recommendation linking AI competencies to academic integrity and equitable access. | S40: What is the reason the PAGER scoping review of ChatGPT in nursing education gives for the importance of developing technical and ethical competencies? | T40: In the PAGER scoping review of ChatGPT in nursing education, why is building technical and ethical competencies called crucial? | U40: pilot | V40: patterns-advances-and-gaps-in-using-chatgpt-and:0016:q1 | W40: accept
A41: 40 | B41: =FALSE() -> FALSE | F41: What should a comprehensive framework for generative AI in nursing education contain, based on findings from a PAGER scoping review of GenAI in nursing education? | G41: It should be a comprehensive system that balances innovation with academic integrity in nursing assessment and clinical training. Such frameworks should establish clear data privacy and security standards and guidelines, and ensure compliance with educational regulations. | H41: The findings indicate the necessity of establishing a comprehensive system that balances innovation with academic integrity in nursing assessment and clinical training. These frameworks should establish clear data privacy and security standards guidelines and ensure compliance with educational regulations (Foronda and Porter, 2024). | I41: Patterns, advances, and gaps in using ChatGPT and similar technologies in nursing education: A PAGER scoping review, p. 8 | J41: =TRUE() -> TRUE | K41: =TRUE() -> TRUE | M41: definition | N41: medium | O41: governance | P41: 5 | Q41: 4 | R41: The answer restates the evidence nearly verbatim: balancing innovation with academic integrity, data privacy and security standards, and regulatory compliance. | The question names the review by its content and its PAGER framework, and needs no unseen context. Expanding the PAGER acronym would help, but the question remains understandable. | value: These are useful recommendations on governance frameworks for GenAI in nursing education. | S41: Which elements should a comprehensive framework for generative AI in nursing education include, per a PAGER scoping review of GenAI in nursing education? | T41: What components does a PAGER scoping review of GenAI in nursing education find necessary in a comprehensive generative AI framework for nursing education? | U41: pilot | V41: patterns-advances-and-gaps-in-using-chatgpt-and:0016:q2 | W41: accept
A42: 41 | B42: =FALSE() -> FALSE | F42: What do the PAGER scoping review's recommendations say incentive structures for generative AI in nursing education should promote? | G42: Incentive structures should promote equitable access to GenAI technologies across diverse settings, with particular attention to underserved populations and low-resource settings. Targeted strategies are needed for bridging digital divides and maximising global applicability. | H42: To address identified disparities, incentive structures should promote equitable access to GenAI technologies across diverse settings, with particular attention to underserved populations and low-resource settings. Targeted strategies are needed for bridging digital divides and maximising global applicability. | I42: Patterns, advances, and gaps in using ChatGPT and similar technologies in nursing education: A PAGER scoping review, p. 8 | J42: =TRUE() -> TRUE | K42: =FALSE() -> FALSE | M42: definition | N42: easy | O42: equity_accessibility | P42: 5 | Q42: 4 | R42: The answer reproduces the evidence nearly verbatim, with no added claims. | The question names a specific study (the PAGER scoping review on GenAI in nursing education) and asks a clear question about it, without relying on unseen context. | value: Equitable access to GenAI in education is a useful responsible-AI recommendation, though it is specific to nursing education. | S42: What goal should incentive structures for generative AI serve in nursing education, per the PAGER scoping review? | T42: In the PAGER scoping review of generative AI in nursing education, what outcomes do the recommended incentive structures aim to encourage? | U42: pilot | V42: patterns-advances-and-gaps-in-using-chatgpt-and:0016:q3 | W42: accept
A43: 42 | B43: =FALSE() -> FALSE | F43: What kind of research does the PAGER scoping review say should be given priority when comparing generative AI with traditional nursing teaching? | G43: Comparative effectiveness research between AI-enhanced and conventional teaching methods should be given priority. Longitudinal studies are also needed to evaluate the impact of GenAI use on student outcomes and ethical decision-making. | H43: Longitudinal studies are needed to evaluate the impact of GenAI use on student outcomes and ethical decision-making. Comparative effectiveness research between AI-enhanced and conventional teaching methods should be given priority. | I43: Patterns, advances, and gaps in using ChatGPT and similar technologies in nursing education: A PAGER scoping review, p. 8 | J43: =TRUE() -> TRUE | K43: =FALSE() -> FALSE | M43: factual | N43: easy | O43: monitoring_improvement | P43: 5 | Q43: 4 | R43: Both statements are taken directly from the evidence. | The question names the PAGER scoping review and asks a clear question without presupposing unseen context. | value: It is a useful research-priority recommendation on generative AI in nursing education. | S43: Which type of research does the PAGER scoping review say should be prioritised regarding AI-enhanced versus conventional nursing teaching? | T43: Which type of research should be prioritized, as the PAGER scoping review sees it, when generative AI is compared against traditional approaches to teaching nursing? | U43: pilot | V43: patterns-advances-and-gaps-in-using-chatgpt-and:0016:q4 | W43: accept
A44: 43 | B44: =FALSE() -> FALSE | F44: How do studies in the PAGER scoping review of GenAI in nursing education suggest balancing innovation with established teaching when integrating AI into the curriculum? | G44: Studies recommend systematically integrating AI into nursing education while preserving traditional teaching methods. Balance between innovation and established pedagogical practices is maintained through ethics and data literacy integration. Such integration can also strengthen student writing skills. | H44: Moving from training to curriculum design, studies recommend systematically integrating AI into nursing education while preserving traditional teaching methods, noting that such integration can strengthen student writing skills (Parker et al., 2023) while maintaining balance between innovation and established pedagogical practices through ethics and data literacy integration (Alkhaqani, 2023a; Allen and Woodnutt, 2023; Castonguay et al., 2023; De Gagne et al., 2024). | I44: Patterns, advances, and gaps in using ChatGPT and similar technologies in nursing education: A PAGER scoping review, p. 7 | J44: =TRUE() -> TRUE | K44: =FALSE() -> FALSE | M44: explanation | N44: medium | O44: teaching_learning | P44: 5 | Q44: 4 | R44: Every statement in the answer is directly stated in the evidence: systematic integration while preserving traditional methods, balance through ethics and data literacy integration, and strengthened writing skills. | The question names the PAGER scoping review of GenAI in nursing education by its content, so it is understandable without the source. The acronyms PAGER and GenAI are common enough in context. | value: It gives a useful recommendation on integrating AI into a nursing curriculum while keeping established pedagogy. | S44: What do nursing education studies in the PAGER scoping review recommend for integrating AI into the curriculum while keeping established pedagogy? | T44: In the PAGER scoping review, how should AI be integrated into nursing education so that innovation and established pedagogical practice stay balanced? | U44: pilot | V44: patterns-advances-and-gaps-in-using-chatgpt-and:0013:q1 | W44: accept
A45: 44 | B45: =FALSE() -> FALSE | F45: A nursing school wants to launch short-term training on generative AI and to set rules for its use in research. What should a 2025 scoping review of generative AI in nursing education say the training focuses on, and what kind of policy guidance does it call for? | G45: Short-term training should focus on developing AI literacy and digital proficiency among faculty and students, with prompt engineering as an essential curriculum component. Policy recommendations call for clear standards for AI implementation through comprehensive guidelines with regular updates. These include ethical protocols for AI in qualitative and mixed-methods research that address academic integrity and ensure transparent GenAI use. | H45: Short-term training initiatives should focus on developing AI literacy and digital proficiency among faculty and students, incorporating prompt engineering as an essential curriculum component (O'Connor et al., 2024). … Policy recommendations highlight the importance of establishing clear standards for AI implementation through comprehensive guideline development with regular updates. This includes developing ethical protocols for AI implementation in qualitative and mixed-methods research (Lyon, 2023) that address academic integrity and ensure transparent GenAI use (Abdulai and Hung, 2023; Abujaber et al., 2023; Alkhaqani, 2023a,b). | I45: Patterns, advances, and gaps in using ChatGPT and similar technologies in nursing education: A PAGER scoping review, p. 7 | J45: =TRUE() -> TRUE | K45: =TRUE() -> TRUE | M45: application | N45: hard | O45: governance | P45: 5 | Q45: 4 | R45: Every statement in the answer closely restates the evidence: the training focus, prompt engineering, regularly updated guidelines, and ethical protocols for research. | The question identifies the source by its content (a 2025 scoping review of generative AI in nursing education) and gives the scenario, so it is understandable without seeing the source. | value: These are useful, actionable recommendations on AI literacy training and AI policy in nursing education. | S45: A nursing school is preparing brief generative AI training sessions and wants rules governing AI use in research. According to a 2025 scoping review of generative AI in nursing education, what should the training concentrate on and what policy guidance is needed? | T45: If a nursing school sets up short-term generative AI training and research-use policies, what does a 2025 scoping review of generative AI in nursing education say the training should focus on, and what policy guidance does it call for? | U45: pilot | V45: patterns-advances-and-gaps-in-using-chatgpt-and:0013:q3 | W45: borderline | X45: unclear | Y45: Repaired question is ungrammatical ('What should a 2025 scoping review ... say').
A46: 45 | B46: =FALSE() -> FALSE | F46: What do institutional recommendations in the PAGER scoping review say about equity and access in GenAI for nursing education, and what do they aim to achieve? | G46: Institutional recommendations include developing policies and inclusive tools to ensure equity, access, and support for diverse user needs. This is intended to reduce language barriers and improve geographic access to resources. | H46: Beyond technical aspects, institutional recommendations include developing policies and inclusive tools to ensure equity, access, and support for diverse user needs (Abujaber et al., 2023), thereby reducing language barriers and improving geographic access to resources (Abujaber et al., 2023; Fontenot, 2023; Hsu, 2023; Huh, 2023). | I46: Patterns, advances, and gaps in using ChatGPT and similar technologies in nursing education: A PAGER scoping review, p. 7 | J46: =TRUE() -> TRUE | K46: =FALSE() -> FALSE | M46: explanation | N46: medium | O46: equity_accessibility | P46: 5 | Q46: 4 | R46: Both statements in the answer are taken directly from the evidence sentence. | The question names the PAGER scoping review by content and is clear without seeing the source; 'GenAI' is a common abbreviation. | value: Useful recommendation on equity and access in AI use for nursing education. | S46: Regarding equity and access to GenAI in nursing education, what do the institutional recommendations in the PAGER scoping review state, and what goals do they aim to achieve? | T46: What do the PAGER scoping review's institutional recommendations propose on equity and access for GenAI in nursing education, and what are they intended to accomplish? | U46: pilot | V46: patterns-advances-and-gaps-in-using-chatgpt-and:0013:q4 | W46: accept
A47: 46 | B47: =FALSE() -> FALSE | F47: What four major domains of generative AI use in entrepreneurship education were identified in a systematic review of 50 peer-reviewed articles? | G47: The four domains were personalized and adaptive instruction, simulation-based entrepreneurial training, ethical and psychological concerns, and ecosystem integration through intelligent systems. | H47: The findings reveal four major domains in GAIenabled EE: personalized and adaptive instruction, simulation-based entrepreneurial training, ethical and psychological concerns, and ecosystem integration through intelligent systems. | I47: Toward understanding the role of generative AI in entrepreneurship education: A systematic review, p. 1 | J47: =TRUE() -> TRUE | K47: =FALSE() -> FALSE | M47: factual | N47: easy | O47: teaching_learning | P47: 5 | Q47: 4 | R47: The answer lists exactly the four domains stated in the evidence. The '50 articles' detail appears only in the question, not in the answer. | The question identifies the study by its content (a systematic review of 50 peer-reviewed articles) and uses no source-dependent phrasing or undefined acronyms. | value: It is a useful framework for generative AI use in entrepreneurship education, though somewhat specific. | S47: Which four domains of generative AI use in entrepreneurship education emerged from a systematic review of 50 peer-reviewed articles? | T47: A systematic review of 50 peer-reviewed articles on generative AI in entrepreneurship education found which four major domains? | U47: pilot | V47: toward-understanding-the-role-of-generative-ai:0000:q0 | W47: accept
A48: 47 | B48: =FALSE() -> FALSE | F48: A business school is redesigning its entrepreneurship curriculum to include generative AI tools. Beyond teaching students to use the tools well, what capacities should the curriculum aim to foster? | G48: A systematic review of generative AI in entrepreneurship education advocates designing curricula that foster not only technical proficiency but also critical thinking, creativity, and ethical reasoning. | H48: It advocates for designing GAI-integrated curricula that foster not only technical proficiency but also critical thinking, creativity, and ethical reasoning. | I48: Toward understanding the role of generative AI in entrepreneurship education: A systematic review, p. 1 | J48: =TRUE() -> TRUE | K48: =FALSE() -> FALSE | M48: application | N48: hard | O48: teaching_learning | P48: 4 | Q48: 4 | R48: The capacities listed match the evidence. However, attributing them to 'a systematic review of generative AI in entrepreneurship education' adds a source description the quoted evidence does not give; it only says 'It'. | The question sets up a self-contained scenario and does not refer to any unseen source. | value: A useful curriculum-design recommendation for integrating AI responsibly in higher education. | S48: When a business school builds generative AI into its entrepreneurship curriculum, what should it foster in students besides technical proficiency? | T48: A university adds generative AI to its entrepreneurship courses. Besides technical skill, which capacities should the curriculum develop? | U48: pilot | V48: toward-understanding-the-role-of-generative-ai:0000:q1 | W48: accept
A49: 48 | B49: =FALSE() -> FALSE | F49: A university leadership team and policymakers are planning to integrate generative AI into entrepreneurship education. What should educators, policymakers and researchers emphasize, according to a systematic review of the field? | G49: The review emphasizes the importance of ethical guidance, digital equity, and cross-contextual adaptability for educators, policymakers, and researchers. | H49: Furthermore, the study discusses actionable implications for educators, policymakers, and researchers, emphasizing the importance of ethical guidance, digital equity, and cross-contextual adaptability. | I49: Toward understanding the role of generative AI in entrepreneurship education: A systematic review, p. 1 | J49: =TRUE() -> TRUE | K49: =FALSE() -> FALSE | M49: application | N49: hard | O49: equity_accessibility | P49: 5 | Q49: 4 | R49: The answer directly restates the evidence: ethical guidance, digital equity and cross-contextual adaptability, emphasized for educators, policymakers and researchers. | The question identifies the source by its content, a systematic review of generative AI in entrepreneurship education, and is understandable without the source. | value: These are useful, if general, recommendations for responsibly integrating generative AI into higher education. | S49: What implications does a systematic review of generative AI in entrepreneurship education have for educators, policymakers, and researchers planning its integration? | T49: When a university's leadership and policymakers prepare to bring generative AI into entrepreneurship education, what should educators, policymakers and researchers focus on, based on a systematic review of this area? | U49: pilot | V49: toward-understanding-the-role-of-generative-ai:0000:q2 | W49: accept
A50: 49 | B50: =FALSE() -> FALSE | F50: Why is the long-term impact of generative AI on entrepreneurial competence, mindset, and outcomes considered uncertain? | G50: Most studies are either conceptual or limited to small-scale exploratory evidence. As a result, the long-term impact of generative AI on entrepreneurial competence, mindset, and outcomes remains uncertain and calls for empirical caution. | H50: Although promising use cases are identified, most studies are either conceptual or limited to small-scale exploratory evidence. As such, the longterm impact of GAI on entrepreneurial competence, mindset, and outcomes remains uncertain and calls for empirical caution. | I50: Toward understanding the role of generative AI in entrepreneurship education: A systematic review, p. 1 | J50: =TRUE() -> TRUE | K50: =FALSE() -> FALSE | M50: explanation | N50: medium | O50: monitoring_improvement | P50: 5 | Q50: 4 | R50: The answer restates the evidence almost verbatim. It notes that most studies are conceptual or small-scale exploratory, so the long-term impact remains uncertain. | The question is self-contained. It names generative AI and the specific entrepreneurial dimensions, with no reference to an unseen source. | value: It conveys a useful point about the limits of evidence on generative AI in entrepreneurship education. | S50: Why does the long-term effect of generative AI on entrepreneurial competence, mindset, and outcomes remain unclear? | T50: What is the reason that the lasting effects of generative AI on entrepreneurial competence, mindset, and outcomes remain unclear? | U50: pilot | V50: toward-understanding-the-role-of-generative-ai:0000:q3 | W50: accept
A51: 50 | B51: =FALSE() -> FALSE | F51: What limitation has been noted in research on how AI may support student motivation in entrepreneurship education? | G51: Specific research has explored how AI may support student motivation, but it has offered limited discussion of entrepreneurship education's pedagogical models and instructional strategies. | H51: Likewise, specific research has explored how AI may support student motivation, but it has offered limited discussion on EE's pedagogical models and instructional strategies (Artemova, 2024). | I51: Toward understanding the role of generative AI in entrepreneurship education: A systematic review, p. 3 | J51: =TRUE() -> TRUE | K51: =FALSE() -> FALSE | M51: factual | N51: easy | O51: teaching_learning | P51: 5 | Q51: 3 | R51: The answer restates the evidence directly, expanding EE to entrepreneurship education, which is a trivial clarification. | The question is clear without the source and needs no further context. | value: It identifies a narrow research gap in AI and entrepreneurship education, which is acceptable but limited. | S51: What gap exists in studies exploring AI support for student motivation in entrepreneurship education? | T51: What has research on AI and student motivation in entrepreneurship education discussed only to a limited extent? | U51: pilot | V51: toward-understanding-the-role-of-generative-ai:0005:q4 | W51: accept
A52: 51 | B52: =FALSE() -> FALSE | F52: What three core dimensions through which generative AI enhances entrepreneurship education were identified in a systematic review of 50 papers? | G52: The review identified three core dimensions: teaching and learning, entrepreneurial capabilities, and the entrepreneurial ecosystem. | H52: This study systematically reviewed 50 relevant papers and identified three core dimensions of GAI enhancing EE: teaching and learning, entrepreneurial capabilities, and the entrepreneurial ecosystem. | I52: Toward understanding the role of generative AI in entrepreneurship education: A systematic review, p. 14 | J52: =TRUE() -> TRUE | K52: =FALSE() -> FALSE | M52: factual | N52: easy | O52: general | P52: 5 | Q52: 4 | R52: The answer directly restates the three dimensions named in the evidence. | The question identifies the study by its content (a systematic review of 50 papers) and uses no undefined acronyms or references to unseen context. | value: A useful framework for how generative AI supports entrepreneurship education, though somewhat specific. | S52: A systematic review of 50 papers on generative AI in entrepreneurship education identified which three core dimensions of enhancement? | T52: Which three dimensions of generative AI's enhancement of entrepreneurship education emerged from a 50-paper systematic review? | U52: pilot | V52: toward-understanding-the-role-of-generative-ai:0024:q0 | W52: accept
A53: 52 | B53: =FALSE() -> FALSE | F53: A university entrepreneurship program wants students to build confidence in business model development and market analysis. What can AI-powered business plan evaluation systems offer, and what effect on students is reported? | G53: AI-powered business plan evaluation systems provide intelligent feedback that helps students better understand critical aspects of business model development and market analysis. This in turn increases their entrepreneurial confidence. | H53: For example, AI-powered business plan evaluation systems provide intelligent feedback, helping students better understand critical aspects of business model development and market analysis, thereby increasing their entrepreneurial confidence (Lesinskis et al., 2023; T. Nuseir et al., 2020). | I53: Toward understanding the role of generative AI in entrepreneurship education: A systematic review, p. 14 | J53: =TRUE() -> TRUE | K53: =FALSE() -> FALSE | M53: application | N53: hard | O53: teaching_learning | P53: 5 | Q53: 4 | R53: The answer restates the evidence almost verbatim: intelligent feedback, better understanding of business model development and market analysis, and increased entrepreneurial confidence. | The question sets up a concrete scenario and names the technology, with no reference to an unseen source. | value: This is a useful, somewhat specific application of AI feedback in entrepreneurship education. | S53: An entrepreneurship program at a university aims to strengthen students' confidence regarding business models and market analysis. What do AI-powered business plan evaluation systems provide, and with what reported result? | T53: In a university entrepreneurship program aiming to strengthen students' confidence in developing business models and analyzing markets, what do AI-powered business plan evaluation systems provide, and what impact on students has been reported? | U53: pilot | V53: toward-understanding-the-role-of-generative-ai:0024:q1 | W53: accept
A54: 53 | B54: =FALSE() -> FALSE | F54: An entrepreneurship instructor is limited by class time and office hours and also wants students to make better-informed business decisions. Which AI tools and effects are reported for these needs? | G54: LLM-based intelligent question-answering tools remove classroom constraints related to time and instructor availability, making learning more autonomous and flexible. AI-supported data-driven market analysis and AI-powered risk assessment enable students to make more rational business decisions based on comprehensive information, improving their adaptability to market changes. | H54: Additionally, intelligent question-answering tools based on LLMs remove traditional classroom constraints related to time and instructor availability, making learning more autonomous and flexible (Liang & Bai, 2024; Torres Ortega et al., 2025). … Furthermore, AI-supported data-driven market analysis and AI-powered risk assessment enable students to make more rational business decisions based on comprehensive information, improving their adaptability to market changes (Obschonka & Audretsch, 2020; Townsend & Hunt, 2019). | I54: Toward understanding the role of generative AI in entrepreneurship education: A systematic review, p. 14 | J54: =TRUE() -> TRUE | K54: =FALSE() -> FALSE | M54: application | N54: hard | O54: teaching_learning | P54: 5 | Q54: 4 | R54: Every statement in the answer directly restates the two quoted sentences about LLM-based question-answering tools, data-driven market analysis and AI-powered risk assessment. | The scenario is self-contained, and 'reported' refers generally to published findings rather than to an unseen text. | value: It covers useful, somewhat specific applications of AI in entrepreneurship education. | S54: How might an entrepreneurship instructor with limited class time and availability use AI to support learning and better student business decisions, according to reported findings? | T54: What AI tools address instructor-availability limits and improve students' business decision-making in entrepreneurship education? | U54: pilot | V54: toward-understanding-the-role-of-generative-ai:0024:q4 | W54: accept
A55: 54 | B55: =FALSE() -> FALSE | F55: Why might the literature on generative AI in entrepreneurship education give a skewed picture of its effects, and what should future studies do about it? | G55: Publication bias may lead to an overrepresentation of generative AI's positive effects while underreporting drawbacks such as increased student dependence, academic integrity concerns, and ethical challenges. Future studies should incorporate unpublished datasets, industry reports, and real-world educational experiments to provide a more balanced perspective. | H55: Potential publication bias may also lead to an overrepresentation of GAI's positive effects, while underreporting its drawbacks, such as increased student dependence, concerns about academic integrity, and ethical challenges. … Future studies should incorporate unpublished datasets, industry reports, and real-world educational experiments to provide a more balanced perspective. | I55: Toward understanding the role of generative AI in entrepreneurship education: A systematic review, p. 19 | J55: =TRUE() -> TRUE | K55: =FALSE() -> FALSE | M55: explanation | N55: medium | O55: general | P55: 5 | Q55: 4 | R55: Every statement in the answer is directly restated from the evidence, with no additions. | The question names its topic, generative AI in entrepreneurship education, and does not refer to any unseen source. | value: It is a useful point about evidence bias in research on AI in education and how to correct it. | S55: How could publication bias distort what is known about generative AI in entrepreneurship education, and what remedy should future research adopt? | T55: What distortion could publication bias introduce into research on generative AI in entrepreneurship education, and how should future studies counter it? | U55: pilot | V55: toward-understanding-the-role-of-generative-ai:0033:q0 | W55: accept
A56: 55 | B56: =FALSE() -> FALSE | F56: Why is it uncertain whether findings on generative AI in entrepreneurship education apply beyond universities, and what research would help? | G56: Most reviewed studies focus on higher education, particularly at the university level, so applicability to vocational training, informal learning, or culturally diverse educational environments remains uncertain. Expanding research to include longitudinal and cross-cultural analyses would provide deeper insights into the sustained impact and adaptability of generative-AI-enabled entrepreneurship education. | H56: Second, the generalizability of the findings is limited by the fact that most reviewed studies focus on higher education, particularly at the university level. The applicability of these approaches to other contexts, such as vocational training, informal learning, or culturally diverse educational environments, remains uncertain. Expanding research to include longitudinal and cross-cultural analyses would provide deeper insights into the sustained impact and adaptability of GAI-enabled EE. | I56: Toward understanding the role of generative AI in entrepreneurship education: A systematic review, p. 19 | J56: =TRUE() -> TRUE | K56: =FALSE() -> FALSE | M56: explanation | N56: medium | O56: general | P56: 5 | Q56: 3 | R56: Every statement in the answer is restated directly from the evidence. That covers the university focus, the uncertain applicability to vocational, informal and culturally diverse settings, and the call for longitudinal and cross-cultural research. | The question names its topic, generative AI in entrepreneurship education, by content. It does not refer to an unseen source or use undefined acronyms. | value: This is a narrow review-limitation point about research scope, though it touches on the generalizability of findings about AI in education. | S56: What limits the generalizability of research on generative AI in entrepreneurship education, and what kind of research would give deeper insight? | T56: What makes it unclear whether results about generative AI in entrepreneurship education carry over to settings outside universities, and what kind of research would address this? | U56: pilot | V56: toward-understanding-the-role-of-generative-ai:0033:q1 | W56: accept
A57: 56 | B57: =FALSE() -> FALSE | F57: In research on generative-AI-enabled entrepreneurship education, what mediating and moderating factors are proposed to shape the effect of generative-AI personalized feedback on entrepreneurial intention? | G57: The effect of generative-AI-enabled personalized feedback on entrepreneurial intention is proposed to be mediated by entrepreneurial self-efficacy. It is proposed to be moderated by institutional support, digital literacy, and prior entrepreneurial experience. | H57: Research Proposition 1: The effect of GAI-enabled personalized feedback on entrepreneurial intention is mediated by entrepreneurial self-efficacy and moderated by institutional support, digital literacy, and prior entrepreneurial experience. Future studies could test this proposition using SEM and randomized controlled trials, comparing GAI-driven and traditional instructional strategies to establish causality and assess long-term outcomes. | I57: Toward understanding the role of generative AI in entrepreneurship education: A systematic review, p. 19 | J57: =TRUE() -> TRUE | K57: =TRUE() -> TRUE | M57: definition | N57: medium | O57: teaching_learning | P57: 5 | Q57: 4 | R57: The answer restates the proposition exactly: entrepreneurial self-efficacy is the mediator, and institutional support, digital literacy and prior entrepreneurial experience are the moderators. | The question names its research area and its variables explicitly, so it is clear without the source. | value: This is a useful, somewhat specific research proposition about how AI feedback affects outcomes in entrepreneurship education. | S57: Which mediator and which moderators are proposed to govern how generative-AI personalized feedback influences students' entrepreneurial intention in entrepreneurship education? | T57: In generative-AI entrepreneurship education research, what variable is proposed to mediate, and what variables to moderate, the impact of AI-driven personalized feedback on entrepreneurial intention? | U57: pilot | V57: toward-understanding-the-role-of-generative-ai:0033:q2 | W57: accept
A58: 57 | B58: =FALSE() -> FALSE | F58: What do the four K-12 AI curricula, three mapped by UNESCO and one developed by T. K. F. Chiu in 2021, primarily introduce to K-12 students and teachers? | G58: They primarily introduce basic AI concepts to K-12 students and teachers. | H58: Four K-12 AI curricula, three mapped by UNESCO (UNESCO, 2022; 2024a; 2024b) and the other developed by T. K. F. Chiu (2021), primarily introduce basic AI concepts to K-12 students and teachers. | I58: Be AIware! An AI Competency Model for K-12 Education, p. 3 | J58: =TRUE() -> TRUE | K58: =FALSE() -> FALSE | M58: definition | N58: easy | O58: student_ai_literacy | P58: 5 | Q58: 3 | R58: The answer directly restates the evidence: the curricula primarily introduce basic AI concepts. | The question names the curricula by content (UNESCO-mapped and Chiu 2021) without presupposing an unseen source. | value: This is an acceptable but narrow fact about the focus of K-12 AI curricula, which is tangential to higher education. | S58: What is the main content that four K-12 AI curricula, three mapped by UNESCO and one by Chiu (2021), introduce to K-12 students and teachers? | T58: What is the main content that the four K-12 AI curricula, three of which UNESCO mapped and one that T. K. F. Chiu developed in 2021, present to K-12 students and teachers? | U58: pilot | V58: be-aiware-an-ai-competency-model-for-k-12:0004:q0 | W58: borderline | X58: low_value | Y58: Very thin answer (one short clause).
A59: 58 | B59: =FALSE() -> FALSE | F59: What risks does generative AI pose for younger K-12 students who can use these tools on their own? | G59: Generative AI presents distinct concerns for younger students who can use the tools independently. Key issues include algorithmic bias, hallucinations (plausible but false information), and over-reliance, which can lead to inaccuracies and affect learning outcomes. | H59: While overlapping with general AI risks, GAI presents distinct concerns for younger students who can independently use these tools. Key issues include algorithmic bias, hallucinations (plausible but false information), and over-reliance, which can lead to inaccuracies and impact learning outcomes. | I59: Be AIware! An AI Competency Model for K-12 Education, p. 2 | J59: =TRUE() -> TRUE | K59: =FALSE() -> FALSE | M59: factual | N59: easy | O59: student_ai_literacy | P59: 5 | Q59: 3 | R59: The answer restates the evidence almost verbatim: bias, hallucinations and over-reliance leading to inaccuracies and effects on learning. | The question is clear and self-contained, and K-12 is a widely understood term. | value: The question covers relevant AI risks, but its K-12 focus sits outside the core higher-education scope. | S59: Which concerns arise when younger K-12 students independently use generative AI tools? | T59: What key issues does generative AI raise for younger school students using it independently? | U59: pilot | V59: be-aiware-an-ai-competency-model-for-k-12:0002:q0 | W59: accept
A60: 59 | B60: =FALSE() -> FALSE | F60: A secondary school teacher in grades 7-9 lets students use a chatbot and an image generator for a project. What difficulties with students' handling of these outputs should the teacher expect? | G60: Middle school learners often struggle to critically evaluate AI-generated responses and may over-trust misleading outputs. Image generators have also been shown to reinforce biased representations. | H60: For middle school students (grades 7-9), studies show that learners often struggle to critically evaluate AI-generated responses and may over-trust misleading outputs (Abdelghani et al., 2025). In parallel, tools like image generators have been shown to reinforce biased representations. | I60: Be AIware! An AI Competency Model for K-12 Education, p. 2 | J60: =TRUE() -> TRUE | K60: =FALSE() -> FALSE | M60: application | N60: hard | O60: student_ai_literacy | P60: 5 | Q60: 4 | R60: Both statements (struggles with critical evaluation and over-trust; image generators reinforcing biased representations) are directly stated in the evidence. | The question describes a concrete scenario, and the grade range and tools are spelled out, with no reference to an unseen source. | value: Over-trust in AI and biased outputs among young learners are useful, practical AI-literacy risks for educators. | S60: A teacher of grades 7-9 has students use a chatbot and an image generator on a project. What problems in how students deal with the outputs should be anticipated? | T60: Middle school students in grades 7-9 are using a chatbot and an image generator for a project. What student difficulties with the AI outputs should their teacher expect? | U60: pilot | V60: be-aiware-an-ai-competency-model-for-k-12:0002:q1 | W60: accept
A61: 60 | B61: =FALSE() -> FALSE | F61: A high school in grades 10-12 notices students increasingly using generative AI for writing, coding, and ideation. What ethical issues arise, and what is essential in response? | G61: This use raises ethical issues such as over-reliance on AI-generated content, blurred authorship, and uncritical acceptance of outputs. Age-appropriate competencies are essential to support critical engagement, promote ethical awareness, and ensure students can responsibly use generative AI tools in learning. | H61: High school students (grades 10-12) increasingly use GAI tools to support writing, coding, and ideation. This raises ethical issues such as over-reliance on AI-generated content, blurred authorship, and uncritical acceptance of outputs (Kasneci et al., 2023). Age-appropriate competencies are therefore essential to support critical engagement, promote ethical awareness, and ensure students can responsibly use GAI tools in learning. | I61: Be AIware! An AI Competency Model for K-12 Education, p. 2 | J61: =TRUE() -> TRUE | K61: =FALSE() -> FALSE | M61: application | N61: hard | O61: student_ai_literacy | P61: 5 | Q61: 4 | R61: The answer restates the three ethical issues and the call for age-appropriate competencies exactly as the evidence gives them. | The question sets up a self-contained scenario and does not refer to any unseen source. | value: It covers useful responsible-AI knowledge, though it concerns secondary education rather than higher education. | S61: Students in grades 10-12 are using generative AI more for writing, coding, and ideation. Which ethical issues does this raise and what is essential? | T61: What ethical problems follow when high schoolers increasingly use generative AI for writing, coding, and ideation, and what response is essential? | U61: pilot | V61: be-aiware-an-ai-competency-model-for-k-12:0002:q2 | W61: accept
A62: 61 | B62: =FALSE() -> FALSE | F62: A teacher wants to use an AI detector to catch AI-written student work and also lets students make images with a generator. What concerns about detection and about generative AI more broadly should the teacher weigh? | G62: Teachers struggle with detecting AI-generated work because current detection tools are unreliable. Generative AI also raises concerns about reduced creativity, data privacy, and the growing presence of AI-generated content like deepfakes and fake news on social media. | H62: Teachers also struggle with detecting AI-generated work, as current detection tools are unreliable. Additionally, GAI raises concerns about reduced creativity, data privacy, and the increasing presence of AIgenerated content like deepfakes and fake news on social media. | I62: Be AIware! An AI Competency Model for K-12 Education, p. 2 | J62: =TRUE() -> TRUE | K62: =FALSE() -> FALSE | M62: application | N62: hard | O62: assessment | P62: 5 | Q62: 4 | R62: Every statement in the answer is a close restatement of the evidence, with no additions. | The question is self-contained, uses no undefined acronyms and does not presuppose a source. | value: It covers useful concerns about AI detector reliability and the broader risks of generative AI in education. | S62: A teacher plans to rely on an AI detector for student work and allows image generation by students. Which concerns about detectors and generative AI generally apply? | T62: What detection-related and wider generative AI concerns should a teacher consider when using an AI detector and permitting student image generators? | U62: pilot | V62: be-aiware-an-ai-competency-model-for-k-12:0002:q3 | W62: accept
A63: 62 | B63: =FALSE() -> FALSE | F63: What can happen when AI systems are trained on biased data, and how might AI-driven recruitment systems illustrate this? | G63: AI systems trained on biased data can unintentionally reinforce stereotypes or unfairly exclude certain groups. For example, AI-driven recruitment systems may favor particular demographics if historical data reflects biased hiring practices, perpetuating inequalities. | H63: AI systems trained on biased data can unintentionally reinforce stereotypes or unfairly exclude certain groups. For example, AI-driven recruitment systems may favor particular demographics if historical data reflects biased hiring practices, perpetuating inequalities. | I63: Be AIware! An AI Competency Model for K-12 Education, p. 2 | J63: =TRUE() -> TRUE | K63: =TRUE() -> TRUE | M63: factual | N63: easy | O63: equity_accessibility | P63: 5 | Q63: 5 | R63: The answer reproduces the evidence verbatim, with no added claims. | The question is self-contained, uses no source references, and has no undefined terms. | value: Algorithmic bias and its illustration through recruitment systems is core responsible-AI knowledge. | S63: What can result from training AI systems on biased data, and how do AI recruitment systems show this? | T63: How can biased training data affect AI systems, for instance in AI-driven hiring? | U63: pilot | V63: be-aiware-an-ai-competency-model-for-k-12:0002:q4 | W63: accept
A64: 63 | B64: =FALSE() -> FALSE | F64: What does it mean that the Be AIware AI competency model for K-12 education was designed to be modular and mappable? | G64: The Be AIware model was designed to be modular and mappable to existing subjects and educational frameworks. | H64: To address this, the model was designed to be modular and mappable to existing subjects and educational frameworks. | I64: Be AIware! An AI Competency Model for K-12 Education, p. 5 | J64: =TRUE() -> TRUE | K64: =TRUE() -> TRUE | M64: definition | N64: easy | O64: teaching_learning | P64: 4 | Q64: 3 | R64: The answer restates the evidence that the model is modular and mappable to existing subjects and frameworks. The evidence says only "the model" and does not itself name Be AIware, though the answer adds nothing else unsupported. | The question names the specific Be AIware model and its K-12 context, so it is understandable without the source. | value: A narrow design detail of a K-12 AI competency model that is only somewhat tied to AI in higher education. | S64: What is meant by the Be AIware K-12 AI competency model being modular and mappable? | T64: In the Be AIware AI competency model for K-12 schools, what do the design features modular and mappable involve? | U64: pilot | V64: be-aiware-an-ai-competency-model-for-k-12:0008:q0 | W64: reject | X64: unclear | Y64: Circular: answer just restates the question ('designed to be modular and mappable'). Repaired.
A65: 64 | B65: =FALSE() -> FALSE | F65: A school district is designing a K-12 AI curriculum and wants to include competencies such as GANs and heuristic searches for all students. What does the Be AIware competency model work indicate about such items? | G65: Items like GANs, algorithm explanation, model training types, and heuristic searches were considered too advanced for K-12 learners without specialized preparation, so they were removed. This aligns with Blikstein (2018), who cautions against introducing deep computer science topics without sufficient scaffolding. | H65: For example, items like GANs, algorithm explanation, model training types, and heuristic searches were considered too advanced for K-12 learners without specialized preparation. This decision aligns with findings from Blikstein (2018), who cautions against introducing deep computer science topics without sufficient scaffolding. … This process resulted in refining the competencies from 140 to 98 by excluding duplicates and renaming some. | I65: Be AIware! An AI Competency Model for K-12 Education, p. 5 | J65: =TRUE() -> TRUE | K65: =FALSE() -> FALSE | M65: application | N65: hard | O65: teaching_learning | P65: 4 | Q65: 4 | R65: The evidence says these items were considered too advanced and refers to 'this decision.' The explicit claim that they were removed is a slight inference from that phrasing, though a reasonable one. | The question names the Be AIware competency model and sets up a concrete scenario. GANs is a widely known term in the AI domain. | value: Useful guidance on how age-appropriate K-12 AI competencies should be scoped. | S65: A K-12 district plans to teach all students GANs and heuristic searches as AI competencies. What did the Be AIware model development find about such items? | T65: If a school system wants to add GANs and heuristic search to a general K-12 AI curriculum, what does the Be AIware model's refinement say about them? | U65: pilot | V65: be-aiware-an-ai-competency-model-for-k-12:0008:q2 | W65: accept
A66: 65 | B66: =FALSE() -> FALSE | F66: Why does a granular competency structure matter for the Be AIware K-12 AI competency model? | G66: Insights from practice confirmed that a granular structure improves alignment with school-based needs and curricular integration. The model was also designed to be modular and mappable to existing subjects and educational frameworks. | H66: To address this, the model was designed to be modular and mappable to existing subjects and educational frameworks. … Insights from practice also confirmed that a granular structure improves alignment with school-based needs and curricular integration. | I66: Be AIware! An AI Competency Model for K-12 Education, p. 5 | J66: =TRUE() -> TRUE | K66: =TRUE() -> TRUE | M66: explanation | N66: medium | O66: teaching_learning | P66: 5 | Q66: 3 | R66: Both statements, the benefit of granularity and the modular, mappable design, are directly stated in the evidence. | The question names the specific Be AIware K-12 AI competency model and needs no unseen context. | value: This is a narrow design point about a K-12 AI competency model, only tangential to higher education. | S66: What benefit of a granular structure for K-12 AI competencies was confirmed by practical insights in the Be AIware model? | T66: In the Be AIware K-12 AI competency model, why was a granular competency structure valuable? | U66: pilot | V66: be-aiware-an-ai-competency-model-for-k-12:0008:q3 | W66: borderline | X66: low_value | Y66: Repaired; thin explanation, overlaps #70.
A67: 66 | B67: =FALSE() -> FALSE | F67: What classroom concerns about AI did teachers raise in interviews for the Be AIware K-12 competency model? | G67: Teachers highlighted the risks of over-reliance on AI tools, the importance of independent thinking, and the integration of ethical reasoning into subjects like philosophy and social studies. | H67: Teachers highlighted classroom-relevant concerns, including the risks of over-reliance on AI tools, the importance of independent thinking, and the integration of ethical reasoning into subjects like philosophy and social studies (Teacher 1, June 5, 2023; Teacher 2, July 12, 2023; Teacher 3, July 13, 2023; Teacher 4, July 15, 2023). | I67: Be AIware! An AI Competency Model for K-12 Education, p. 5 | J67: =TRUE() -> TRUE | K67: =FALSE() -> FALSE | M67: factual | N67: easy | O67: student_ai_literacy | P67: 5 | Q67: 3 | R67: The answer restates the three concerns exactly as given in the evidence. It adds no inference or extra detail. | It names the Be AIware K-12 competency model by its content and asks a clear question without referring to an unseen source. | value: These are relevant AI-in-education concerns, but they come from a narrow K-12 interview context rather than higher education. | S67: Which AI-related classroom concerns did teachers highlight when the Be AIware K-12 model was developed? | T67: What worries about AI in the classroom did teachers voice in the Be AIware interviews? | U67: pilot | V67: be-aiware-an-ai-competency-model-for-k-12:0008:q4 | W67: accept
A68: 67 | B68: =FALSE() -> FALSE | F68: What tendency do multiple studies document in how AI systems assign grades to student work? | G68: Multiple studies document a consistent tendency toward leniency. AI systems assign higher marks and under-penalize weak submissions. | H68: Multiple studies document a consistent tendency toward leniency, wherein AI systems assign higher marks and under-penalize weak submissions (Jukiewicz, 2024; Crosthwaite & Ma, 2025). | I68: Reliable but not rigorous: Evaluating ChatGPT's reliability, validity, and bias in automated academic grading, p. 2 | J68: =TRUE() -> TRUE | K68: =FALSE() -> FALSE | M68: factual | N68: easy | O68: assessment | P68: 5 | Q68: 5 | R68: The answer directly restates the evidence: a consistent leniency tendency, with higher marks and under-penalized weak submissions. | The question clearly asks about a documented tendency in AI grading of student work and does not refer to an unseen source. | value: AI grading leniency is a core risk for assessment in higher education. | S68: What grading tendency have multiple studies found in AI systems? | T68: How do AI grading systems tend to behave when marking student submissions, according to multiple studies? | U68: extra:assessment | V68: reliable-but-not-rigorous-evaluating-chatgpt-s:0002:q0 | W68: accept
A69: 68 | B69: =FALSE() -> FALSE | F69: What benefits can AI-based grading systems offer instructors and students? | G69: AI-based systems can reduce instructor workload, improve scoring consistency, and provide faster feedback. | H69: AI-based systems can reduce instructor workload, improve scoring consistency, and provide faster feedback (Seneviratne & Manathunga, 2025). | I69: Reliable but not rigorous: Evaluating ChatGPT's reliability, validity, and bias in automated academic grading, p. 2 | J69: =TRUE() -> TRUE | K69: =FALSE() -> FALSE | M69: factual | N69: easy | O69: assessment | P69: 5 | Q69: 4 | R69: The answer restates the evidence almost verbatim: reduced instructor workload, improved scoring consistency and faster feedback. | The question is clear without the source and contains no source references or undefined terms. | value: These are useful, commonly cited benefits of AI-assisted assessment in higher education. | S69: What advantages have been reported for AI-based grading systems? | T69: In what ways can AI-based grading systems help both instructors and students? | U69: extra:assessment | V69: reliable-but-not-rigorous-evaluating-chatgpt-s:0002:q1 | W69: accept
A70: 69 | B70: =FALSE() -> FALSE | F70: What three possible explanations for AI grading leniency do prior studies often fail to tell apart? | G70: Prior research often fails to differentiate whether leniency represents an inherent model bias, a reflection of training data distributions, or limitations of rubric application. | H70: Importantly, prior research often fails to differentiate whether this leniency represents an inherent model bias, a reflection of training data distributions, or limitations of rubric application (Lalor et al., 2024). … Multiple studies document a consistent tendency toward leniency, wherein AI systems assign higher marks and under-penalize weak submissions (Jukiewicz, 2024; Crosthwaite & Ma, 2025). | I70: Reliable but not rigorous: Evaluating ChatGPT's reliability, validity, and bias in automated academic grading, p. 2 | J70: =TRUE() -> TRUE | K70: =FALSE() -> FALSE | M70: definition | N70: medium | O70: assessment | P70: 5 | Q70: 4 | R70: The answer directly restates the three explanations named in the evidence: inherent model bias, training data distributions and rubric application limitations. | The question is self-contained and clear about AI grading leniency, and it does not refer to any unseen source. | value: It covers useful knowledge about the possible causes of bias in AI grading. | S70: Which three possible sources of leniency in AI grading are often not distinguished in earlier research? | T70: When AI graders are lenient, what three possible causes does prior research often not differentiate? | U70: extra:assessment | V70: reliable-but-not-rigorous-evaluating-chatgpt-s:0002:q2 | W70: accept
A71: 70 | B71: =FALSE() -> FALSE | F71: How does the type of assignment affect the accuracy of AI grading? | G71: AI performs reliably in structured tasks, but its accuracy declines in open-ended or creative assignments. Those assignments require nuanced contextual understanding. | H71: While AI performs reliably in structured tasks, its accuracy declines in openended or creative assignments, where nuanced contextual understanding is required (Lo et al., 2025). | I71: Reliable but not rigorous: Evaluating ChatGPT's reliability, validity, and bias in automated academic grading, p. 2 | J71: =TRUE() -> TRUE | K71: =FALSE() -> FALSE | M71: explanation | N71: medium | O71: assessment | P71: 5 | Q71: 4 | R71: Both statements directly restate the evidence: reliable in structured tasks, declining accuracy in open-ended or creative assignments that require nuanced contextual understanding. | The question is self-contained and refers to no unseen source or context. | value: This is a useful, practical finding about the limits of AI-assisted assessment in higher education. | S71: In what way does assignment type change how accurate AI grading is? | T71: In what way does the kind of assignment being graded influence how accurate AI grading is? | U71: extra:assessment | V71: reliable-but-not-rigorous-evaluating-chatgpt-s:0002:q4 | W71: accept
A72: 71 | B72: =FALSE() -> FALSE | F72: Why does a lack of cybersecurity training among students, faculty, and staff make universities more vulnerable, and what should institutions do about it? | G72: A lack of cybersecurity training among students, faculty, and staff exacerbates vulnerabilities and makes individuals more susceptible to cyberattacks. Institutions must prioritize ongoing security awareness education to mitigate human error-related risks. | H72: A lack of cybersecurity training among students, faculty, and staff exacerbates vulnerabilities, making individuals more susceptible to cyberattacks. Institutions must prioritize ongoing security awareness education to mitigate human error-related risks. | I72: AI and Security in China’s Higher Education, p. 36 | J72: =TRUE() -> TRUE | K72: =FALSE() -> FALSE | M72: explanation | N72: medium | O72: faculty_readiness | P72: 5 | Q72: 4 | R72: The answer restates the evidence nearly verbatim, with no added claims. | The question is self-contained and makes no reference to a source. | value: It covers a useful institutional risk and recommendation on cybersecurity awareness in universities. | S72: How does missing cybersecurity training for students, faculty, and staff increase a university's exposure to cyberattacks, and what response is called for? | T72: What is the effect of untrained students, faculty, and staff on university cyber vulnerability, and what should institutions prioritize? | U72: extra:procurement_technology | V72: ai-and-security-in-china-s-higher-education:0016:q0 | W72: accept
A73: 72 | B73: =FALSE() -> FALSE | F73: A university plans to build up its cybersecurity culture so that students, faculty, and staff understand their responsibilities. What measures should it adopt, and what benefits follow from a pervasive information security culture? | G73: Universities should embed cybersecurity norms through sustained awareness campaigns, role-based education, and continuous training, so students, faculty, and staff understand their responsibilities and practice policies proactively. A pervasive information security culture builds shared accountability, reduces human-factor breaches, and strengthens institutional resilience against evolving threats. | H73: Universities should embed cybersecurity norms through sustained awareness campaigns, role-based education, and continuous training so students, faculty, and staff understand their responsibilities and practice policies proactively. A pervasive ISC builds shared accountability, reduces human-factor breaches, and strengthens institutional resilience against evolving threats (Li et al., 2021; Wang, 2019). | I73: AI and Security in China’s Higher Education, p. 36 | J73: =TRUE() -> TRUE | K73: =FALSE() -> FALSE | M73: application | N73: hard | O73: student_ai_literacy | P73: 5 | Q73: 4 | R73: The answer restates the evidence almost verbatim; it only expands the ISC acronym to information security culture. | The question describes a clear scenario, contains no source references, and spells out information security culture rather than using an acronym. | value: These are useful institutional cybersecurity culture recommendations for higher education, though only tangential to AI. | S73: A campus wants staff, faculty, and students to understand and practice their security responsibilities. Which measures should it embed, and what does a pervasive information security culture deliver? | T73: If a university aims to foster an information security culture, what activities should it use and what outcomes does such a culture bring? | U73: extra:procurement_technology | V73: ai-and-security-in-china-s-higher-education:0016:q1 | W73: accept
A74: 73 | B74: =FALSE() -> FALSE | F74: What are malware and ransomware attacks on universities? | G74: Malware and ransomware attacks are increasingly common, as attackers infiltrate university networks, encrypt files, and demand ransom payments for the return of critical data. These attacks can cause significant financial and operational disruptions. | H74: Malware and ransomware attacks are increasingly common, as attackers infiltrate university networks, encrypt files, and demand ransom payments for the return of critical data. These attacks can cause significant financial and operational disruptions. | I74: AI and Security in China’s Higher Education, p. 36 | J74: =TRUE() -> TRUE | K74: =FALSE() -> FALSE | M74: definition | N74: easy | O74: privacy_security | P74: 5 | Q74: 4 | R74: The answer reproduces the evidence verbatim. | The question is clear without the source and refers to no unseen context. | value: Cybersecurity risks to universities are useful knowledge about the institutional context. | S74: How do malware and ransomware attacks against universities work? | T74: What happens in a malware or ransomware attack on a university? | U74: extra:procurement_technology | V74: ai-and-security-in-china-s-higher-education:0016:q2 | W74: accept
A75: 74 | B75: =FALSE() -> FALSE | F75: How can poorly managed cloud services lead to data leaks at universities, and what must institutions do to reduce this risk? | G75: Poorly managed cloud services with weak access controls and configuration errors can lead to data leaks. Institutions must ensure that cloud service providers comply with security protocols to mitigate these risks. | H75: Poorly managed cloud services with weak access controls and configuration errors can lead to data leaks. Institutions must ensure that cloud service providers comply with security protocols to mitigate these risks. | I75: AI and Security in China’s Higher Education, p. 36 | J75: =TRUE() -> TRUE | K75: =FALSE() -> FALSE | M75: explanation | N75: medium | O75: procurement_technology | P75: 5 | Q75: 4 | R75: The answer repeats the evidence nearly verbatim. It names weak access controls and configuration errors as causes, and provider compliance with security protocols as the mitigation. | The question is self-contained and makes no reference to an unseen source. | value: Cloud security risks to institutional data are useful, practical knowledge for higher education. | S75: Why can badly managed cloud services cause data leaks in universities, and what must institutions ensure? | T75: In what ways can badly managed cloud services cause data leaks in universities, and what steps do institutions need to take to lower that risk? | U75: extra:procurement_technology | V75: ai-and-security-in-china-s-higher-education:0016:q3 | W75: accept
A76: 75 | B76: =FALSE() -> FALSE | F76: What does aligning data governance with laws such as GDPR and FERPA involve for universities? | G76: Institutions should align data governance with laws like GDPR and FERPA, covering secure collection, processing, and storage. They should also educate staff and students on their rights and duties so policies are consistently followed in practice. | H76: Institutions should align data governance with laws like GDPR and FERPA-covering secure collection, processing, and storage-while educating staff and students on their rights and duties so policies are consistently followed in practice (Liu, 2021; Xiao, 2006). | I76: AI and Security in China’s Higher Education, p. 36 | J76: =TRUE() -> TRUE | K76: =FALSE() -> FALSE | M76: definition | N76: medium | O76: governance | P76: 5 | Q76: 4 | R76: The answer restates the evidence nearly verbatim; secure collection, processing and storage, together with educating staff and students, are all directly stated. | GDPR and FERPA are well-known named laws, and the question does not refer to any unseen source. | value: This is useful knowledge on data governance compliance in higher education. | S76: What should universities do when aligning their data governance with GDPR and FERPA? | T76: For universities, what is involved in making their data governance consistent with regulations such as GDPR and FERPA? | U76: extra:procurement_technology | V76: ai-and-security-in-china-s-higher-education:0016:q4 | W76: accept
A77: 76 | B77: =FALSE() -> FALSE | F77: In a higher-education module on AI in business environments, what is meant by "AI Capital", and what is the final assessment designed to let students demonstrate? | G77: AI Capital is the combined technical proficiency and strategic insight required for responsible, value-driven AI deployment in contemporary businesses. The assessment was designed to enable students to demonstrate this AI Capital. | H77: Ultimately, this assessment was designed to enable students to demonstrate their AI Capital, that is, the combined technical proficiency and strategic insight required for responsible, value-driven AI deployment in contemporary businesses. | I77: The formation of AI Capital in higher education: Enhancing students’ academic performance and employment rates, p. 8 | J77: =TRUE() -> TRUE | K77: =FALSE() -> FALSE | M77: definition | N77: medium | O77: student_ai_literacy | P77: 5 | Q77: 3 | R77: The definition and the assessment's purpose are both stated directly in the evidence. The answer adds no unsupported statements. | The question describes the module by its content and explains the term in quotes, so it is understandable without the source, even though it refers to "the final assessment" of a described module. | value: The concept of AI capital is relevant, but the pair is narrowly tied to one module's assessment. | S77: How is "AI Capital" defined in an AI in Business Environments module, and what does its assessment let students demonstrate? | T77: What does "AI Capital" mean in a university business AI module, and what is the assignment meant to enable students to show? | U77: extra:leadership_strategy | V77: the-formation-of-ai-capital-in-higher-education:0012:q0 | W77: accept
A78: 77 | B78: =FALSE() -> FALSE | F78: Why does the model development report in the AI in Business Environments module require students to discuss ethical implications and propose strategies for transparency and fairness? | G78: The report required students to discuss the ethical implications of AI applications and propose strategies to enhance model transparency and fairness. These themes reflected the module's emphasis on ethical and responsible AI. | H78: The report required students to interpret AI-driven insights (LO9, LO29), discuss the ethical implications of AI applications (LO13, LO14, LO15, LO16), and propose strategies to enhance model transparency and fairness (LO20). These themes reflected the module's emphasis on ethical and responsible AI. | I78: The formation of AI Capital in higher education: Enhancing students’ academic performance and employment rates, p. 7 | J78: =TRUE() -> TRUE | K78: =FALSE() -> FALSE | M78: explanation | N78: medium | O78: teaching_learning | P78: 5 | Q78: 3 | R78: Both sentences of the answer are stated almost verbatim in the evidence, including the link to the module's emphasis on ethical and responsible AI. | The question names the module and the specific report by content, so it can be understood without seeing the source. | value: It is acceptable but narrow, concerning the rationale behind one module's assessment design. | S78: What is the reason the AI in Business Environments module's model development report asks students to address ethical implications and propose transparency and fairness strategies? | T78: Why are students in the AI in Business Environments module required to cover ethics, model transparency and fairness in their model development report? | U78: extra:leadership_strategy | V78: the-formation-of-ai-capital-in-higher-education:0012:q1 | W78: accept
... A82: 81 | B82: =FALSE() -> FALSE | F82: Which key areas does foundational AI literacy cover, which is considered vital for all individuals? | G82: Foundational AI literacy covers AI concepts, applications, affectiveness for human emotions, safety and security, and responsible usage. It is considered vital for all individuals. | H82: As mentioned in the last section, a foundational literacy in AI - covering the key areas of AI concepts, applications, affectiveness for human emotions, safety and security, and responsible usage - is vital for all individuals. | I82: Generative AI in Higher Education: The ChatGPT Effect, p. 62 | J82: =TRUE() -> TRUE | K82: =FALSE() -> FALSE | M82: factual | N82: easy | O82: student_ai_literacy | P82: 5 | Q82: 4 | R82: The answer directly restates the five areas and the claim that this literacy is vital for all individuals, all of which appear in the evidence. | The question is self-contained and uses no references to a source or unseen context. | value: It gives useful domain knowledge about the components of AI literacy. | S82: What key areas make up the foundational AI literacy that is vital for everyone? | T82: Foundational AI literacy, considered vital for all individuals, spans which key areas? | U82: extra:faculty_readiness | V82: cecilia-ka-yuk-chan-2024-generative-ai-in:0035:q3 | W82: accept
A83: 82 | B83: =FALSE() -> FALSE | F83: In the DAILM model of AI literacy, which seven additional literacy aspects are expected of university teachers beyond foundational AI literacy? | G83: The DAILM model expects the additional literacy aspects for university teachers to be Pedagogical Innovation; Ethical, Social, and Policy Awareness; AI for Social Good; Career and Industry Alignment; Continuous Professional Development; Research and Scholarly Engagement; and Responsible AI Usage and Development. | H83: Based on the DAILM model, the additional literacy aspects for university teacher are expected to be: (1) Pedagogical Innovation; (2) Ethical, Social, and Policy Awareness; (3) AI for Social Good; (4) Career and Industry Alignment; (5) Continuous Professional Development; (6) Research and Scholarly Engagement; and (7) Responsible AI Usage and Development. | I83: Generative AI in Higher Education: The ChatGPT Effect, p. 63 | J83: =TRUE() -> TRUE | K83: =TRUE() -> TRUE | M83: definition | N83: medium | O83: faculty_readiness | P83: 5 | Q83: 4 | R83: The answer lists exactly the seven additional literacy aspects for university teachers that the evidence states under the DAILM model. | The question names a specific framework (the DAILM model) and asks a clear question without presupposing an unseen source. | value: It gives useful, framework-specific knowledge about AI literacy expectations for university teachers. | S83: What seven extra AI literacy aspects does the DAILM model set out for university teachers on top of foundational literacy? | T83: Beyond foundational AI literacy, which seven aspects does the DAILM model expect university teachers to have? | U83: extra:faculty_readiness | V83: cecilia-ka-yuk-chan-2024-generative-ai-in:0035:q4 | W83: accept
A84: 83 | B84: =FALSE() -> FALSE | F84: In a survey of 1280 undergraduates at 12 Chinese universities, how were institutional culture, AI-based assessment practices and students' meta-skills related to one another? | G84: Institutional culture was positively associated with AI-based assessment practices (β = .49, R2 = .24) and with meta-skills (β = .21). AI-based assessment practices were strongly associated with meta-skills (β = .58, R2 = .55). | H84: Institutional culture was positively associated with AI-based assessment practices (β = .49, R 2 = .24) and meta-skills (β = .21), while AI-based assessment practices were strongly associated with meta-skills (β = .58, R 2 = .55). | I84: AI-enabled assessment in higher education: Institutional culture and student meta-skill readiness across university tiers, p. 1 | J84: =TRUE() -> TRUE | K84: =TRUE() -> TRUE | M84: explanation | N84: medium | O84: assessment | P84: 5 | Q84: 4 | R84: Every coefficient and relationship in the answer is stated directly in the evidence, with only trivial rewording. | The question identifies the study by its sample and constructs, so it is understandable without seeing the source. | value: It is a useful empirical finding linking institutional culture and AI-based assessment to student meta-skills. | S84: What associations did a survey of 1280 undergraduates at 12 Chinese universities find among institutional culture, AI-based assessment practices and meta-skills? | T84: Among 1280 undergraduates from 12 universities in China who were surveyed, what was the relationship linking institutional culture, AI-based assessment practices and students' meta-skills? | U84: extra:assessment | V84: ai-enabled-assessment-in-higher-education:0000:q0 | W84: accept
A85: 84 | B85: =FALSE() -> FALSE | F85: Which meta-skills are universities under pressure to foster while they integrate AI? | G85: Universities are under growing pressure to integrate AI while fostering meta-skills such as adaptability, collaboration, creativity and strategic thinking. | H85: Universities are under growing pressure to integrate artificial intelligence (AI) while fostering meta-skills such as adaptability, collaboration, creativity and strategic thinking. | I85: AI-enabled assessment in higher education: Institutional culture and student meta-skill readiness across university tiers, p. 1 | J85: =TRUE() -> TRUE | K85: =FALSE() -> FALSE | M85: definition | N85: medium | O85: student_ai_literacy | P85: 5 | Q85: 4 | R85: The answer restates the evidence almost verbatim. Every statement in it is directly supported. | The question is self-contained and does not refer to any source. | value: It names the meta-skills universities are expected to build alongside AI integration, which is useful domain knowledge. | S85: Which meta-skills must universities foster alongside integrating AI, given growing pressure? | T85: While integrating AI, what meta-skills are universities expected to develop in students? | U85: extra:assessment | V85: ai-enabled-assessment-in-higher-education:0000:q1 | W85: accept
A86: 85 | B86: =FALSE() -> FALSE | F86: A university wants AI-based assessment to build students' meta-skills and is deciding whether to treat it as a purely technical rollout. What does research on 12 Chinese universities indicate about how it should be viewed and what strengthens its effect? | G86: The findings position AI-enabled assessment as a culturally mediated dimension of academic management rather than a purely technical add-on. Governance and ethics readiness significantly strengthened the relationship between AI-based assessment practices and students' meta-skills. | H86: These findings position AI-enabled assessment as a culturally mediated dimension of academic management rather than a purely technical add-on. … Governance and ethics readiness significantly strengthened the AI-based assessment-meta-skills relationship, and cross-tier comparisons showed a stronger culture-to-practice pathway in national key universities. | I86: AI-enabled assessment in higher education: Institutional culture and student meta-skill readiness across university tiers, p. 1 | J86: =TRUE() -> TRUE | K86: =FALSE() -> FALSE | M86: application | N86: hard | O86: governance | P86: 4 | Q86: 4 | R86: Both statements in the answer are directly supported by the evidence with only light rewording. The evidence does not itself state that the study covered 12 Chinese universities, though that detail appears only in the question. | The question names the study by its content (research on 12 Chinese universities) and sets out a clear scenario. It does not refer to unseen context. | value: It gives a useful finding that AI assessment is a culturally mediated part of academic management and that governance and ethics readiness strengthens its effect. | S86: A university is considering AI-based assessment as a purely technical add-on to build meta-skills. What do findings from 12 Chinese universities say about how to view it and what strengthens its effect? | T86: If a university plans AI-based assessment to develop student meta-skills, what do findings from 12 Chinese universities say about treating it as a technical add-on and about what strengthens its effect? | U86: extra:assessment | V86: ai-enabled-assessment-in-higher-education:0000:q2 | W86: accept
A87: 86 | B87: =FALSE() -> FALSE | F87: How did the pathway from institutional culture to AI-based assessment practice differ across university tiers in a study of Chinese universities? | G87: Cross-tier comparisons showed a stronger culture-to-practice pathway in national key universities than in other university tiers. | H87: Governance and ethics readiness significantly strengthened the AI-based assessment-meta-skills relationship, and cross-tier comparisons showed a stronger culture-to-practice pathway in national key universities. | I87: AI-enabled assessment in higher education: Institutional culture and student meta-skill readiness across university tiers, p. 1 | J87: =TRUE() -> TRUE | K87: =FALSE() -> FALSE | M87: explanation | N87: medium | O87: leadership_strategy | P87: 4 | Q87: 3 | R87: The answer restates the evidence nearly verbatim; adding "than in other university tiers" is a trivial clarification of the comparison. | The question identifies the study by its content (Chinese universities, tiers, AI-based assessment) and does not rely on unseen context. | value: This is a narrow, study-specific finding about AI assessment adoption, though it is still relevant to the domain. | S87: In a study of Chinese universities, how did the culture-to-practice pathway for AI-based assessment vary by university tier? | T87: Which university tier showed a stronger link from institutional culture to AI-based assessment practice in research on Chinese universities? | U87: extra:assessment | V87: ai-enabled-assessment-in-higher-education:0000:q3 | W87: accept
A88: 87 | B88: =FALSE() -> FALSE | F88: What does it mean to view AI-enabled assessment as a culturally mediated dimension of academic management? | G88: It means seeing AI-enabled assessment as a culturally mediated dimension of academic management rather than a purely technical add-on. Institutional culture was positively associated with AI-based assessment practices (β = .49). | H88: These findings position AI-enabled assessment as a culturally mediated dimension of academic management rather than a purely technical add-on. … Institutional culture was positively associated with AI-based assessment practices (β = .49, R 2 = .24) and meta-skills (β = .21), while AI-based assessment practices were strongly associated with meta-skills (β = .58, R 2 = .55). | I88: AI-enabled assessment in higher education: Institutional culture and student meta-skill readiness across university tiers, p. 1 | J88: =TRUE() -> TRUE | K88: =FALSE() -> FALSE | M88: definition | N88: medium | O88: leadership_strategy | P88: 4 | Q88: 4 | R88: Both statements are drawn directly from the evidence. The answer partly restates the question, and linking the β to the concept's meaning is a light connective move. | The question names a concept without referring to an unseen source. | value: This is a useful conceptual framing of AI assessment within institutional culture. | S88: What is meant by treating AI-enabled assessment as a culturally mediated dimension of academic management? | T88: How is AI-enabled assessment positioned when it is seen as culturally mediated and part of academic management? | U88: extra:assessment | V88: ai-enabled-assessment-in-higher-education:0000:q4 | W88: borderline | X88: unclear | Y88: Near-circular: answer restates the phrase the question asks about.
A89: 88 | B89: =FALSE() -> FALSE | F89: Why has the potential of MOOC course review data remained largely untapped for educational research? | G89: The potential of MOOC review data remains largely untapped because there is no structured and comprehensive repository of it that is accessible for educational research and analysis. | H89: However, the potential of this data remains largely untapped, due to the lack of a structured and comprehensive repository, accessible for educational research and analysis. | I89: Artificial Intelligence in Education. Posters and Late Breaking Results, Workshops and Tutorials, Industry and Innovation Tracks, Practitioners, Doctoral Consortium and Blue Sky, p. 169 | J89: =TRUE() -> TRUE | K89: =FALSE() -> FALSE | M89: explanation | N89: medium | O89: general | P89: 4 | Q89: 3 | R89: The answer restates the evidence's stated reason: the lack of a structured, comprehensive and accessible repository. The evidence only says 'this data', so its identification as MOOC review data is a trivial contextual step. | The question clearly asks why MOOC review data is underused in educational research. MOOC is a widely known term, and nothing refers to unseen context. | value: This is acceptable but narrow knowledge about a data-infrastructure gap in educational research, rather than core responsible-AI content. | S89: What explains why MOOC review data has largely gone unused in educational research? | T89: What explains the fact that the potential of MOOC course review data has mostly not been exploited in educational research? | U89: extra:procurement_technology | V89: artificial-intelligence-bceaf5:0124:q0 | W89: accept
A90: 89 | B90: =FALSE() -> FALSE | F90: What six challenges does the MOOCRev data repository for MOOC reviews target? | G90: MOOCRev targets: thorough, research-based anonymisation to ensure user privacy and data integrity; dealing with class (rating) bias; addressing language diversity and platform-specific rating systems; processing emojis and emoticons; providing text weights; and tagging reviews with Parts of Speech. | H90: MOOCRev targets the following challenges (1) thorough, research-based anonymisation of the data to ensure user privacy and data integrity, (2) dealing with class (rating) bias, (3) addressing language diversity and platform-specific rating systems, (4) processing emojis and emoticons, (5) providing text weights (6) and tagging the reviews with the corresponding Parts of Speech (POS). | I90: Artificial Intelligence in Education. Posters and Late Breaking Results, Workshops and Tutorials, Industry and Innovation Tracks, Practitioners, Doctoral Consortium and Blue Sky, p. 168 | J90: =TRUE() -> TRUE | K90: =FALSE() -> FALSE | M90: definition | N90: medium | O90: privacy_security | P90: 5 | Q90: 3 | R90: All six listed challenges are stated directly in the evidence, with only trivial rewording. | The question names the specific repository (MOOCRev, for MOOC reviews) and needs no unseen context; MOOC is a widely known acronym. | value: These are design challenges for one specific educational review dataset, so the pair is relevant but narrow. | S90: Which six challenges is MOOCRev designed to address? | T90: What are the six issues that the MOOCRev review repository tackles? | U90: extra:procurement_technology | V90: artificial-intelligence-bceaf5:0124:q2 | W90: borderline | X90: low_value | Y90: Dataset feature list (MOOCRev); marginal domain value.
A91: 90 | B91: =FALSE() -> FALSE | F91: Why is text analytics of learner-generated text on MOOC and other online learning platforms considered an essential but complicated task? | G91: Text analytics in education is an essential but complicated task because of three distinct challenges. The first is the specific nature of textual data and the volume of information learners generate on online learning platforms. The second is that annotating learners' opinions, feedback and sentiments in MOOCs is time-consuming and labour-intensive. The third is that cultural and linguistic variations can further complicate text annotation and analysis. | H91: Text analytics, particularly in the education domain, is an essential but complicated task, due to some distinct challenges. This includes (1) the specific nature of textual data and the volume of information learners generate on online learning platforms [5], (2) annotating learners' expressed opinions, feedback and sentiments in MOOCs, which is known to be a time-consuming and labourintensive task [6, 7], and (3) the cultural and linguistic variations which can further complicate text annotations and analysis [8, 9]. | I91: Artificial Intelligence in Education. Posters and Late Breaking Results, Workshops and Tutorials, Industry and Innovation Tracks, Practitioners, Doctoral Consortium and Blue Sky, p. 169 | J91: =TRUE() -> TRUE | K91: =TRUE() -> TRUE | M91: explanation | N91: medium | O91: general | P91: 5 | Q91: 4 | R91: All three challenges in the answer are stated directly in the evidence, with only light rewording. | The question names its topic, text analytics of learner text on MOOCs, without referring to any unseen source. | value: Useful domain knowledge about the challenges of educational text analytics. | S91: What makes analyzing text written by learners on MOOC and other online learning platforms both essential and complicated? | T91: Why do researchers regard text analytics of learner-generated text on MOOCs and similar online learning platforms as a task that is essential yet complicated? | U91: extra:procurement_technology | V91: artificial-intelligence-bceaf5:0124:q3 | W91: accept
A92: 91 | B92: =FALSE() -> FALSE | F92: What kind of dataset is needed to build reliable real-world models for educational text analytics, given its challenges? | G92: The challenges of educational text analytics underscore the need for a generalisable, cross-platform and non-biased dataset. Such a dataset can be used to build reliable models in real-world applications. | H92: These challenges underscore the need for a generalisable cross-platform and nonbiased dataset that can be further used to build reliable models in real-world applications. … Text analytics, particularly in the education domain, is an essential but complicated task, due to some distinct challenges. This includes (1) the specific nature of textual data and the volume of information learners generate on online learning platforms [5], (2) annotating learners' expressed opinions, feedback and sentiments in MOOCs, which is known to be a time-consuming and labourintensive task [6, 7], and (3) the cultural and linguistic variations which can further complicate text annotations and analysis [8, 9]. | I92: Artificial Intelligence in Education. Posters and Late Breaking Results, Workshops and Tutorials, Industry and Innovation Tracks, Practitioners, Doctoral Consortium and Blue Sky, p. 169 | J92: =TRUE() -> TRUE | K92: =FALSE() -> FALSE | M92: definition | N92: medium | O92: equity_accessibility | P92: 5 | Q92: 3 | R92: The answer directly restates the evidence: a generalisable, cross-platform, non-biased dataset is needed and can be used to build reliable real-world models. | The question names its topic, educational text analytics, explicitly. It contains no source references or undefined terms. | value: This is acceptable but narrow domain knowledge about dataset needs in educational text analytics. | S92: Given the challenges of educational text analytics, what type of dataset is needed for reliable real-world models? | T92: What characteristics should a dataset have so reliable real-world educational text models can be built on it? | U92: extra:procurement_technology | V92: artificial-intelligence-bceaf5:0124:q4 | W92: accept
A93: 92 | B93: =FALSE() -> FALSE | F93: What kinds of specialized training does preparing higher education faculty for artificial intelligence require? | G93: Preparing faculty for AI requires specialized training in adaptive learning, automated assessment, and data-driven instructional design. It also requires ethical frameworks that ensure alignment with institutional values and the public interest. | H93: Addressing this challenge requires specialized training in adaptive learning, automated assessment, and data-driven instructional design, as well as ethical frameworks that ensure alignment with institutional values and the public interest (Ciarra Tejada & Parra S´anchez, 2024). | I93: Stakeholder engagement and strategic innovation in higher education through AI competency, p. 4 | J93: =TRUE() -> TRUE | K93: =FALSE() -> FALSE | M93: factual | N93: easy | O93: faculty_readiness | P93: 4 | Q93: 4 | R93: The answer restates the listed training areas and ethical frameworks. However, the evidence refers only to 'this challenge', so linking it to faculty preparation for AI is a slight contextual assumption. | The question is self-contained, clearly asks about training needs for higher education faculty regarding AI, and does not refer to any unseen source. | value: These are useful recommendations on faculty AI training in higher education. | S93: Which specialized training areas are needed to get university faculty ready for AI? | T93: To prepare faculty in higher education for AI, what specialized training is needed? | U93: extra:leadership_strategy | V93: stakeholder-engagement-and-strategic-innovation:0006:q0 | W93: accept
A94: 93 | B94: =FALSE() -> FALSE | F94: How do Stakeholder Theory and Human Capital Theory each contribute to understanding the strategic role of faculty in higher education institutions? | G94: Stakeholder Theory highlights faculty legitimacy and influence in shaping institutional strategies. Human Capital Theory emphasizes targeted investment in faculty competency as a driver of productivity, innovation, and institutional relevance. | H94: Stakeholder Theory highlights their legitimacy and influence in shaping institutional strategies, while Human Capital Theory emphasizes targeted investment in faculty competency as a driver of productivity, innovation, and institutional relevance. | I94: Stakeholder engagement and strategic innovation in higher education through AI competency, p. 4 | J94: =TRUE() -> TRUE | K94: =FALSE() -> FALSE | M94: definition | N94: medium | O94: leadership_strategy | P94: 5 | Q94: 4 | R94: Both statements are taken directly from the evidence, with "their" rendered as "faculty". | The question names both theories and the topic explicitly and does not refer to any unseen source. | value: These are useful theoretical framings of the faculty's strategic role in higher education. | S94: What does each of Stakeholder Theory and Human Capital Theory emphasize about faculty's strategic role in universities? | T94: In explaining faculty's strategic role in higher education, what does each of the two theories, Stakeholder Theory and Human Capital Theory, highlight? | U94: extra:leadership_strategy | V94: stakeholder-engagement-and-strategic-innovation:0006:q1 | W94: accept
A95: 94 | B95: =FALSE() -> FALSE | F95: What is Stakeholder Theory's view of organizations? | G95: Stakeholder Theory conceptualizes organizations as entities embedded within complex environments composed of multiple actors with distinct interests, varying degrees of influence, and legitimate claims on organizational outcomes. In contrast to shareholder-centric models, it advocates inclusive governance that responds to the expectations of diverse stakeholders. | H95: Stakeholder Theory conceptualizes organizations as entities embedded within complex environments composed of multiple actors who possess distinct interests, varying degrees of influence, and legitimate claims on organizational outcomes (Freeman, 1984; Freeman & McVea, 2005). In contrast to shareholder-centric models, it advocates for inclusive governance that responds to the expectations of diverse stakeholders. | I95: Stakeholder engagement and strategic innovation in higher education through AI competency, p. 4 | J95: =TRUE() -> TRUE | K95: =FALSE() -> FALSE | M95: definition | N95: easy | O95: governance | P95: 5 | Q95: 3 | R95: Every statement in the answer is taken almost verbatim from the evidence. | The question names Stakeholder Theory directly and needs no source context to be understood. | value: This is a general management theory that is only indirectly relevant to AI in higher education. | S95: How does Stakeholder Theory conceptualize organizations? | T95: How does Stakeholder Theory conceive of organizations? | U95: extra:leadership_strategy | V95: stakeholder-engagement-and-strategic-innovation:0006:q2 | W95: accept
A96: 95 | B96: =FALSE() -> FALSE | F96: What change has AI brought to the traditional teacher-student relationship in higher education? | G96: AI has shifted the traditional teacher-student relationship into a more complex teacher-AI-student dynamic. | H96: There is no doubt that AI has shifted the traditional teacher-student relationship into a more complex teacher-AI-student dynamic. | I96: Higher Education in the Arab World, p. 98 | J96: =TRUE() -> TRUE | K96: =FALSE() -> FALSE | M96: definition | N96: easy | O96: teaching_learning | P96: 5 | Q96: 4 | R96: The answer restates the evidence almost verbatim, so every statement is directly supported. | The question is self-contained and clearly asks how AI has changed the teacher-student relationship in higher education, with no reference to an unseen source. | value: Useful conceptual point about how AI reshapes pedagogical relationships, though stated briefly. | S96: In what way has artificial intelligence transformed the conventional relationship between instructors and students in universities? | T96: How has the arrival of AI modified the long-standing teacher-student relationship in higher education? | U96: extra:faculty_readiness | V96: higher-education-in-arab:0053:q0 | W96: accept
A97: 96 | B97: =FALSE() -> FALSE | F97: What do Saudi Vision 2030 and Oman Vision 2040 direct with respect to AI? | G97: These visions explore digital transformation and the importance of using AI projects. They give clear directives to launch national programs for the adoption and localization of AI and to accelerate the development of legislation that will enable AI technologies to become an effective force in development sectors. They also provide the required funding. | H97: These visions explore digital transformation and the importance of using AI projects. They offer clear directives to launch national programs for the adoption and localization of AI, and to accelerate the development of legislation that will enable AI technologies to become an effective force in the development sectors of these countries, and they provide the required funding. | I97: Higher Education in the Arab World, p. 97 | J97: =TRUE() -> TRUE | K97: =FALSE() -> FALSE | M97: definition | N97: easy | O97: leadership_strategy | P97: 4 | Q97: 3 | R97: The answer is a near-verbatim restatement of the evidence. It only rewords slightly ('offer' to 'give') and drops 'of these countries'. | The question names specific national visions and needs no unseen context. | value: National AI policy directives are relevant institutional context but narrow and not specific to higher education. | S97: What directives on AI are contained in Saudi Vision 2030 and Oman Vision 2040? | T97: What AI-related measures do the national visions of Saudi Arabia and Oman call for? | U97: extra:faculty_readiness | V97: higher-education-in-arab:0053:q1 | W97: accept
A98: 97 | B98: =FALSE() -> FALSE | F98: Which Gulf Cooperation Council states have put in place policies and regulations for the ethical use of AI? | G98: GCC states such as the UAE, KSA, Qatar and Oman have put in place policies and regulations for the ethical use of AI, and they have implemented AI in all aspects of HEI work. | H98: For example, the Gulf Cooperation Council (GCC) states, such as the UAE, KSA, Qatar and Oman, have put in place policies and regulations for the ethical use of AI, and they have implemented AI in all aspects of HEI work. However, some Arab countries have limited resources with which to explore AI and have an inadequate understanding about how to use AI in teaching and learning, or about any other uses of AI in HE. | I98: Higher Education in the Arab World, p. 98 | J98: =TRUE() -> TRUE | K98: =FALSE() -> FALSE | M98: factual | N98: easy | O98: governance | P98: 5 | Q98: 3 | R98: The answer restates the evidence almost verbatim, including the 'such as' qualifier and the claim about implementing AI in all aspects of HEI work. | The question spells out Gulf Cooperation Council and asks a clear, self-contained question without referencing the source. | value: This is a narrow regional fact about which countries have ethical AI policies, though it gives relevant policy context for AI in higher education. | S98: Which member nations of the Gulf Cooperation Council have implemented policies and regulations governing the ethical use of artificial intelligence? | T98: What Gulf Cooperation Council states have introduced policies and regulations concerning the ethical use of AI? | U98: extra:faculty_readiness | V98: higher-education-in-arab:0053:q2 | W98: accept
A99: 98 | B99: =FALSE() -> FALSE | F99: What limitations do some Arab countries face in using AI in higher education, in contrast to the Gulf Cooperation Council (GCC) states? | G99: Some Arab countries have limited resources with which to explore AI and an inadequate understanding of how to use AI in teaching and learning or in other higher education uses. By contrast, Gulf Cooperation Council states such as the UAE, KSA, Qatar and Oman have put in place policies and regulations for the ethical use of AI and have implemented AI in all aspects of higher education institution work. | H99: For example, the Gulf Cooperation Council (GCC) states, such as the UAE, KSA, Qatar and Oman, have put in place policies and regulations for the ethical use of AI, and they have implemented AI in all aspects of HEI work. However, some Arab countries have limited resources with which to explore AI and have an inadequate understanding about how to use AI in teaching and learning, or about any other uses of AI in HE. | I99: Higher Education in the Arab World, p. 98 | J99: =TRUE() -> TRUE | K99: =TRUE() -> TRUE | M99: definition | N99: medium | O99: leadership_strategy | P99: 5 | Q99: 4 | R99: Every statement in the answer is taken directly from the evidence, which covers both the limited resources of some Arab countries and the GCC states' policies and implementation. | The question is self-contained: the acronym GCC is spelled out and the question does not refer to any source. | value: It gives useful regional context on how ready institutions are to adopt AI in higher education. | S99: What constraints hold back some Arab countries from using AI in higher education, unlike the Gulf Cooperation Council states? | T99: Compared with the Gulf Cooperation Council (GCC) states, what constraints hinder certain Arab countries from adopting AI in higher education? | U99: extra:faculty_readiness | V99: higher-education-in-arab:0053:q3 | W99: borderline | X99: other | Y99: Overlaps #112 and #114 (same GCC vs other Arab states passage); answer dedup missed it.
A100: 99 | B100: =FALSE() -> FALSE | F100: A ministry in an Arab state with limited resources and understanding of AI wants to improve higher education AI readiness. What actions should such states take? | G100: Arab states with limited resources and inadequate understanding of AI need an urgent solution. They should invest in AI, establish public-private partnerships for AI regulation, reskill and upskill their workforces, and collaborate with other Arab countries for mutual support. | H100: For example, the Gulf Cooperation Council (GCC) states, such as the UAE, KSA, Qatar and Oman, have put in place policies and regulations for the ethical use of AI, and they have implemented AI in all aspects of HEI work. However, some Arab countries have limited resources with which to explore AI and have an inadequate understanding about how to use AI in teaching and learning, or about any other uses of AI in HE. … This requires an urgent solution and these Arab states should: Invest in AI Establish public-private partnerships for AI regulation Reskill and upskill their workforces Collaborate with other Arab countries for mutual support. | I100: Higher Education in the Arab World, pp. 97-98 | J100: =TRUE() -> TRUE | K100: =FALSE() -> FALSE | M100: application | N100: hard | O100: leadership_strategy | P100: 5 | Q100: 4 | R100: The answer restates the evidence's description of these states and its four recommended actions without adding anything. | The question describes the scenario fully without referring to an unseen source. | value: These are useful policy recommendations for AI readiness in higher education in a specific regional context. | S100: What should an Arab country with limited AI capacity do to prepare its higher education sector for AI? | T100: Which actions should an Arab country with scarce resources and a limited grasp of AI take to strengthen the AI readiness of its higher education sector? | U100: extra:faculty_readiness | V100: higher-education-in-arab:0053:q4 | W100: accept
A101: 100 | B101: =FALSE() -> FALSE | F101: A university language department worries that students will submit AI-generated work and wants to reform its assessment. What assessment changes did EFL teachers at Ha'il University propose to ensure ethical AI use? | G101: Teachers proposed reformulating grading and assessment. One teacher suggested exams conducted only in person, or at least on campus and supervised by a member of staff. Another said assessment will not be reliable and valid unless more marks go to discussion and debate, with marks given only to those who take part in the discussions. | H101: Teacher 4 added, "exams only conducted in person, or at least in the university campus supervised by member of staff." Teacher 7 mentioned, "Our assessment will not reliable and valid unless we devote more marks on discussion and debate. Only those who take part in the discussions are given marks". | I101: Ethical and pedagogical implications of AI in language education: An empirical study at Ha'il University, p. 5 | J101: =TRUE() -> TRUE | K101: =FALSE() -> FALSE | M101: application | N101: hard | O101: assessment | P101: 4 | Q101: 4 | R101: The specific proposals (in-person or supervised exams, more marks for discussion and debate) match the quoted teachers. The opening framing that teachers proposed 'reformulating grading and assessment' is a summary the evidence does not state verbatim. | The question names Ha'il University and EFL teachers. EFL is a widely understood term, so the question is clear without the source. | value: Assessment redesign to counter AI misuse is useful, practical higher-education knowledge. | S101: An EFL department fears students will hand in AI-written assignments. Which grading and assessment reforms did teachers at Ha'il University suggest for ethical AI use? | T101: What changes to grading and assessment did Ha'il University EFL teachers propose so that students use AI ethically? | U101: extra:assessment | V101: ethical-and-pedagogical-implications-of-ai-in:0011:q0 | W101: accept
A102: 101 | B102: =FALSE() -> FALSE | F102: What did EFL teachers at Ha'il University say educators should use to check student assignments in order to promote ethical AI use? | G102: Educators reported the need to check students' assignments using AI-based plagiarism detectors. This prevents students from completely depending on AI to do their assignments. | H102: To use AI ethically, educators reported the need to check students' assignments using AI-based plagiarism detectors. This prevents students from completely depending on AI to do their assignments. | I102: Ethical and pedagogical implications of AI in language education: An empirical study at Ha'il University, p. 5 | J102: =TRUE() -> TRUE | K102: =FALSE() -> FALSE | M102: factual | N102: easy | O102: assessment | P102: 5 | Q102: 3 | R102: Both statements in the answer are taken almost verbatim from the evidence. The evidence itself does not name Ha'il University, but the answer does not assert anything beyond what the evidence states. | The question names a specific population (EFL teachers at Ha'il University) and defines its topic clearly. EFL is a widely known acronym. | value: It gives a narrow but relevant practitioner recommendation on ethical AI use in assessment. | S102: Which tools did Ha'il University EFL teachers say should be used to check students' assignments for ethical AI use? | T102: To encourage ethical use of AI, which tools did English as a foreign language instructors at Ha'il University say educators ought to use when reviewing students' assignments? | U102: extra:assessment | V102: ethical-and-pedagogical-implications-of-ai-in:0011:q1 | W102: accept
A103: 102 | B103: =FALSE() -> FALSE | F103: Why did EFL teachers at Ha'il University say AI use should be built into the learning outcomes of the curriculum? | G103: Teachers reported that to ensure ethical use of AI, it is important to regulate the learning environment. This finding indicates that students should be integrated into using AI as part of the learning outcomes of their curriculum. Kim et al. (2022) similarly argued that integrating AI in education should rest on a curriculum built on ethical instruction, interdisciplinary learning and capacity building. | H103: Teachers also reported that to ensure ethical use of AI, it is important to regulate the learning environment. This finding indicates that students should be integrated into using AI as part of the learning outcomes of their curriculum. … This finding aligns with Kim et al. (2022) who pointed out that integrating AI in education should be based on designing a curriculum built on ethical instruction, interdisciplinary learning and capacity building. | I103: Ethical and pedagogical implications of AI in language education: An empirical study at Ha'il University, p. 5 | J103: =TRUE() -> TRUE | K103: =FALSE() -> FALSE | M103: explanation | N103: medium | O103: teaching_learning | P103: 4 | Q103: 4 | R103: The answer closely restates the evidence with only trivial rewording. One caveat: the evidence presents the curriculum-integration point as the researchers' interpretation of the teachers' report, not as something the teachers themselves said. | The question names the specific group (EFL teachers at Ha'il University) and the topic clearly, with no references to unseen context. | value: Concerns ethical AI integration into curriculum learning outcomes, useful but context-specific domain knowledge. | S103: What reasoning led Ha'il University EFL teachers to conclude that AI use belongs in curriculum learning outcomes? | T103: What reason did English as a foreign language instructors at Ha'il University give for saying that AI use should be embedded in the curriculum's learning outcomes? | U103: extra:assessment | V103: ethical-and-pedagogical-implications-of-ai-in:0011:q2 | W103: accept
...

Sheet Agreement
A1: Review progress
A2: Rows reviewed | B2: =COUNTIF(Review!$C$2:$C$126,"accept")+COUNTIF(Review!$C$2:$C$126,"reject") -> 0
A3: Priority rows reviewed (of 20) | B3: =COUNTIFS(Review!$B$2:$B$126,TRUE(),Review!$C$2:$C$126,"accept")+COUNTIFS(Review!$B$2:$B$126,TRUE(),Review!$C$2:$C$126,"reject") -> 0
A4: Human accept rate among filter-passed pairs | B4: =IFERROR(COUNTIFS(Review!$J$2:$J$126,TRUE(),Review!$C$2:$C$126,"accept")/(COUNTIFS(Review!$J$2:$J$126,TRUE(),Review!$C$2:$C$126,"accept")+COUNTIFS(Review!$J$2:$J$126,TRUE(),Review!$C$2:$C$126,"reject")),"")
A6: You vs automatic filters (reviewed rows)
B7: Human accept | C7: Human reject
A8: Filters passed | B8: =COUNTIFS(Review!$J$2:$J$126,TRUE(),Review!$C$2:$C$126,"accept") -> 0 | C8: =COUNTIFS(Review!$J$2:$J$126,TRUE(),Review!$C$2:$C$126,"reject") -> 0
A9: Filters rejected | B9: =COUNTIFS(Review!$J$2:$J$126,FALSE(),Review!$C$2:$C$126,"accept") -> 0 | C9: =COUNTIFS(Review!$J$2:$J$126,FALSE(),Review!$C$2:$C$126,"reject") -> 0
A10: Observed agreement | B10: =IFERROR((B8+C9)/(B8+C8+B9+C9),"")
A11: Cohen's kappa | B11: =IFERROR(((B8+C9)/(B8+C8+B9+C9)-((B8+C8)*(B8+B9)+(B9+C9)*(C8+C9))/(B8+C8+B9+C9)^2)/(1-((B8+C8)*(B8+B9)+(B9+C9)*(C8+C9))/(B8+C8+B9+C9)^2),"")
A13: You vs Claude pre-screen (reviewed rows; Claude 'borderline' excluded)
B14: Human accept | C14: Human reject
A15: Claude accept | B15: =COUNTIFS(Review!$W$2:$W$126,"accept",Review!$C$2:$C$126,"accept") -> 0 | C15: =COUNTIFS(Review!$W$2:$W$126,"accept",Review!$C$2:$C$126,"reject") -> 0
A16: Claude reject | B16: =COUNTIFS(Review!$W$2:$W$126,"reject",Review!$C$2:$C$126,"accept") -> 0 | C16: =COUNTIFS(Review!$W$2:$W$126,"reject",Review!$C$2:$C$126,"reject") -> 0
A17: Claude borderline: you accepted / rejected | B17: =COUNTIFS(Review!$W$2:$W$126,"borderline",Review!$C$2:$C$126,"accept") -> 0 | C17: =COUNTIFS(Review!$W$2:$W$126,"borderline",Review!$C$2:$C$126,"reject") -> 0
A18: Observed agreement | B18: =IFERROR((B15+C16)/(B15+C15+B16+C16),"")
A20: Your reject categories
A21: incorrect | B21: =COUNTIF(Review!$D$2:$D$126,"incorrect") -> 0
A22: unsupported | B22: =COUNTIF(Review!$D$2:$D$126,"unsupported") -> 0
A23: not_standalone | B23: =COUNTIF(Review!$D$2:$D$126,"not_standalone") -> 0
A24: low_value | B24: =COUNTIF(Review!$D$2:$D$126,"low_value") -> 0
A25: unclear | B25: =COUNTIF(Review!$D$2:$D$126,"unclear") -> 0
A26: other | B26: =COUNTIF(Review!$D$2:$D$126,"other") -> 0
A28: Kappa above ~0.6 = the judge broadly matches your standard. Claude (Opus 5.5) is the same model as the judge, so the Claude comparison is not an independent rater.
