Workbook

Sheet Instructions
A1: Pilot v1 QA review
A3: What to do
A4: 1. Go to the Review sheet. Rows marked priority = TRUE (top 40, highlighted) are a stratified sample: 25 passed + 15 rejected pairs across all question types and reject reasons. Review those first; the rest are optional.
A5: 2. For each row, read the question, answer and evidence, then pick accept or reject in human_verdict (yellow column, dropdown).
A6: 3. If you reject, pick a reject_category (dropdown) and add a few words in human_notes.
A7: 4. The Agreement sheet updates automatically: your accept rate and how often you agree with the automatic filters.
A9: Accept a pair only if all three are true
A10: Correct: the answer is fully supported by the evidence, with nothing added.
A11: Standalone: the question makes sense to someone who has never seen the source.
A12: Worth learning: it is about the domain (responsible AI, higher education), not trivia or study methodology.
A14: Reject categories
A15: incorrect — answer contradicts or misreads the evidence
... A23: Save this file (keep .xlsx). Copy it into the project, e.g. data/qa_pairs/pilot_review_v1_reviewed.xlsx, and tell Claude Code to merge human_verdict, reject_category and human_notes into its review data by qa_id (sheet "Review").

Sheet Review
A1: # | B1: priority | C1: human_verdict | D1: reject_category | E1: human_notes | F1: question | G1: answer | H1: evidence | I1: passed_filters | J1: reject_reason | K1: q_type | L1: difficulty | M1: dimension | N1: grounding | O1: standalone | P1: judge_rationale | Q1: paraphrase_1 | R1: paraphrase_2 | S1: qa_id
A2: 1 | B2: =TRUE() -> TRUE | F2: How many students are enrolled in Argentina's university system, and what share of them attend state-run institutions? | G2: Argentina's university system enrolls about 2,164,500 students. Of these, 93% are undergraduate students, and about 80% are in state-run institutions, whether national or provincial. (Socially Responsible Higher Education, p. 50) | H2: Considering the population, the Argentine university system brings together 2,164,500 students, of which 93% are undergraduate students, and about 80% are in state-run institutions (national or provincial). | I2: =TRUE() -> TRUE | K2: factual | L2: easy | M2: general | N2: 5 | O2: =TRUE() -> TRUE | P2: Every claim in the answer is stated directly in the evidence: 2,164,500 students, 93% undergraduate, and about 80% in state-run institutions, whether national or provincial. | Q2: What is the total enrollment of the Argentine university system, and roughly what proportion is in state-run institutions? | R2: How large is the student population of Argentine universities, and what percentage studies in national or provincial public institutions? | S2: budd-l-hall-rajesh-2021-socially-responsible:0027:q0
A3: 2 | B3: =TRUE() -> TRUE | F3: Why are dropout rates in Argentine higher education especially high among young people from lower-income backgrounds? | G3: Dropout levels are high, particularly for young people from lower-income socioeconomic sectors. The reason given is that higher education is associated with the cultural capital of the family. It also depends on whether young people have been able to access quality high school education. (Socially Responsible Higher Education, p. 50) | H3: However, as García de Fanelli (2014, p. 290) points out, levels of abandonment are high, particularly for young people from lower-income socioeconomic sectors, given that "[higher education] is associated with the cultural capital of the family and with the possibilities of young people having access to quality high school education". | I3: =TRUE() -> TRUE | K3: explanation | L3: medium | M3: equity_accessibility | N3: 5 | O3: =TRUE() -> TRUE | P3: Every claim in the answer is stated directly in the evidence. The answer gives the high abandonment among lower-income youth and attributes it to family cultural capital and to access to quality high school education. | Q3: What explains the high levels of university abandonment among low-income young people in Argentina? | R3: Why do lower-income socioeconomic groups in Argentina leave higher education at high rates? | S3: budd-l-hall-rajesh-2021-socially-responsible:0027:q1
A4: 3 | B4: =TRUE() -> TRUE | F4: Why is Brazil's higher education system characterized by heterogeneous institutions and unequal student access? | G4: The historical evolution of Brazil's national higher education system was marked by structuring inequalities in the country's economic, social and cultural formation. These inequalities were decisive in the complexity and heterogeneity of institutions. They also shaped the inequality of the students who accessed that level of schooling. (Socially Responsible Higher Education, p. 50) | H4: The historical evolution of the national system of higher education was marked by the structuring inequalities in Brazil's economic, social and cultural formation, which were decisive in the complexity and heterogeneity of institutions and in the inequality of the students who accessed that level of schooling. | I4: =TRUE() -> TRUE | K4: explanation | L4: medium | M4: equity_accessibility | N4: 5 | O4: =TRUE() -> TRUE | P4: Every claim in the answer restates the evidence almost verbatim, including the structuring inequalities and their effects on institutions and students. | Q4: What historical factors made Brazilian higher education institutions complex and its students unequal in access? | R4: How did Brazil's national formation shape the diversity of its institutions and inequality among its students? | S4: budd-l-hall-rajesh-2021-socially-responsible:0027:q3
A5: 4 | B5: =TRUE() -> TRUE | F5: What have been the main inclusion policies of the Argentine university system? | G5: One of the main inclusion policies has been the territorial expansion of university offerings. It has also involved a sustained increase in enrollment. These have been accompanied by some scholarship and tutoring programmes for courses. (Socially Responsible Higher Education, p. 50) | H5: One of the main policies of inclusion in the Argentine university system has been the territorial expansion of offerings and the sustained increase in enrollment, along with some scholarship and tutoring programmes for courses. | I5: =TRUE() -> TRUE | K5: definition | L5: easy | M5: equity_accessibility | N5: 4 | O5: =TRUE() -> TRUE | P5: The answer matches the evidence closely. However, it splits a single "main policy" (territorial expansion plus increased enrollment, along with scholarships and tutoring) into separate items, which slightly reframes how the source groups them. | Q5: Which policies have Argentina mainly used to promote inclusion in its universities? | R5: What does inclusion policy in Argentine higher education mainly consist of? | S5: budd-l-hall-rajesh-2021-socially-responsible:0027:q4
A6: 5 | B6: =TRUE() -> TRUE | F6: In the Times Higher Education World University Rankings 2020, how many of the 'top 300' universities are located in Europe, North America, Australia and New Zealand? | G6: In the 2020 Times Higher Education World University Rankings, 270 of the 'top 300' universities (90%) are in Europe, North America, Australia and New Zealand. Of the remainder, 25 are from a small number of East Asian countries and only 5 are from the rest of the world. (Socially Responsible Higher Education, p. 95) | H6: of the purportedly 'top 300' universities in the world, 270 (90%) are located in Europe, North America, Australia and New Zealand. Of the remainder, 25 are from a small number of East Asian countries and there are only 5 from the rest of the world. | I6: =TRUE() -> TRUE | K6: factual | L6: easy | M6: equity_accessibility | N6: 4 | O6: =TRUE() -> TRUE | P6: The counts (270 of the top 300, 90%; 25 East Asian; 5 from the rest of the world) are directly stated. However, the quoted evidence never names the Times Higher Education 2020 rankings, so the answer's attribution to them rests only on the question's premise. | Q6: How many of the 300 highest-ranked institutions in the 2020 Times Higher Education World University Rankings are in Europe, North America, Australia or New Zealand? | R6: In the 2020 THE world rankings' top 300, what number and share of universities come from Europe, North America, Australia and New Zealand? | S6: budd-l-hall-rajesh-2021-socially-responsible:0055:q0
A7: 6 | B7: =TRUE() -> TRUE | F7: What does fairness require of a personalized learning AI system in education? | G7: Fairness requires the system to consider each student's individual needs and characteristics. It must also avoid reinforcing educational inequalities. (Towards Ethical and Socially Responsible Explainable AI, p. 68) | H7: Fairness requires the system to consider each student's individual needs and characteristics and avoid reinforcing educational inequalities | I7: =TRUE() -> TRUE | K7: definition | L7: easy | M7: equity_accessibility | N7: 5 | O7: =TRUE() -> TRUE | P7: Both claims, considering each student's individual needs and characteristics and avoiding reinforcing educational inequalities, are stated directly in the evidence. | Q7: How is fairness characterized for personalized learning AI used with students? | R7: What must an educational personalized learning system do in order to be fair? | S7: towards-ethical:0028:q2
A8: 7 | B8: =TRUE() -> TRUE | F8: Why does developing explainable AI require balancing transparency against confidentiality? | G8: AI systems often use sensitive or confidential data, such as personal or financial information, which must be protected from unauthorized access. At the same time, transparency is essential for building trust and ensuring that decisions are fair and unbiased. Ethical and socially responsible explainable AI must therefore balance the two. (Towards Ethical and Socially Responsible Explainable AI, p. 103) | H8: AI systems often involve sensitive or confidential data, such as personal or financial information, and these data must be protected from unauthorized access. However, transparency is also essential in building trust and ensuring that the decisions made by AI systems are fair and unbiased. | I8: =TRUE() -> TRUE | K8: explanation | L8: medium | M8: governance | N8: 4 | O8: =TRUE() -> TRUE | P8: Both the need to protect sensitive data and the role of transparency in trust and fairness are stated directly. The concluding 'must therefore balance the two' is an obvious inference from the quoted passage, not an explicit statement in it. | Q8: What tension exists between transparency and confidentiality when building explainable AI systems? | R8: Why must designers of explainable AI weigh openness about decisions against protection of sensitive data? | S8: towards-ethical:0051:q0
A9: 8 | B9: =TRUE() -> TRUE | F9: At what stage of their studies do almost all Peruvian law schools place legal clinical education, and what prerequisites are often required? | G9: Almost all Peruvian law schools implement legal clinical education towards the end of a student's education. They often require students to have passed a certain set of classes, usually related to procedural law, in order to participate. (Socially Responsible Higher Education, p. 222) | H9: almost all universities have chosen to implement legal clinical education towards the end of a student's education, often requiring them to have passed a certain set of classes (usually related to procedural law) in order to participate. | I9: =TRUE() -> TRUE | K9: factual | L9: easy | M9: teaching_learning | N9: 4 | O9: =TRUE() -> TRUE | P9: The answer matches the evidence closely, but the evidence says "almost all universities" and never mentions Peru explicitly. Reading those universities as Peruvian law schools is a small inference from context. | Q9: When in a Peruvian law student's education is clinical legal education usually offered, and what must they have passed first? | R9: What is the usual timing and prerequisite structure for legal clinics in Peruvian law schools? | S9: budd-l-hall-rajesh-2021-socially-responsible:0120:q3
A10: 9 | B10: =TRUE() -> TRUE | F10: What proportion of 50 surveyed Peruvian universities in a 2017 ENARSU Network study treated social responsibility as a central pillar, and how many were incorporating it into curriculums and campus life? | G10: The 2017 ENARSU Network study found that only 43% of the 50 universities surveyed considered SRHEI a central pillar of their institution. Only 36% of the universities studied were incorporating it into curriculums and campus life. (Socially Responsible Higher Education, p. 220) | H10: a 2017 study by Peru's ENARSU Network (Network of the National Meeting on Social Responsibility in Higher Education) found that only 43% of the 50 universities surveyed considered SRHEI as a central pillar in their institution (Stojnic Chávez & Jungbluth Melgar, 2017, p. 4). This last report also found that only 36% of universities studied were incorporating SRHEI into curriculums and campus life | I10: =TRUE() -> TRUE | K10: factual | L10: easy | M10: monitoring_improvement | N10: 5 | O10: =TRUE() -> TRUE | P10: Both figures, 43% treating SRHEI as a central pillar and 36% incorporating it into curriculums and campus life, are stated directly in the evidence for the 2017 ENARSU study of 50 universities. | Q10: In the 2017 ENARSU Network survey of 50 Peruvian universities, what percentages treated SRHEI as a central pillar and integrated it into curriculums and campus life? | R10: What did the 2017 ENARSU study report about Peruvian universities making social responsibility a central pillar and embedding it in curriculums and campus life? | S10: budd-l-hall-rajesh-2021-socially-responsible:0118:q4
A11: 10 | B11: =TRUE() -> TRUE | F11: Why is it essential for AI systems to adhere to applicable laws and regulations? | G11: Ensuring that AI systems adhere to applicable laws and regulations is essential for protecting user rights. It also helps ensure fairness and prevents unintended consequences. (Towards Ethical and Socially Responsible Explainable AI, p. 171) | H11: Ensuring that AI systems adhere to applicable laws and regulations is essential for protecting user rights, ensuring fairness, and preventing unintended consequences [28]. | I11: =TRUE() -> TRUE | K11: explanation | L11: easy | M11: governance | N11: 5 | O11: =TRUE() -> TRUE | P11: The evidence directly states every part of the answer: protecting user rights, ensuring fairness, and preventing unintended consequences. | Q11: What is the importance of making sure AI systems comply with relevant laws and regulations? | R11: Why does legal and regulatory adherence matter for AI systems? | S11: towards-ethical:0090:q0
A12: 11 | B12: =TRUE() -> TRUE | F12: Which two review questions in a PAGER scoping review of generative AI in nursing education address types of evidence and successful integration? | G12: The Evidence question asks what types of evidence exist regarding the use and outcomes of generative AI in nursing education. The Recommendations question asks what recommendations can be made to integrate generative AI in nursing education successfully. (Patterns, advances, and gaps in using ChatGPT and similar technologies in nursing education: A PAGER scoping review, p. 2) | H12: What types of evidence exist regarding the use and outcomes of GenAI in nursing education? What recommendations can be made to integrate GenAI in nursing education successfully? | I12: =TRUE() -> TRUE | K12: factual | L12: medium | M12: monitoring_improvement | N12: 4 | O12: =TRUE() -> TRUE | P12: Both questions are quoted almost verbatim in the evidence. The labels "Evidence" and "Recommendations" are not in the quoted text, but they are an obvious inference from the content of each question. | Q12: What do the Evidence and Recommendations questions ask in a scoping review of generative AI in nursing education? | R12: In a PAGER review on generative AI in nursing education, how are the Evidence and Recommendations questions worded? | S12: patterns-advances-and-gaps-in-using-chatgpt-and:0003:q4
A13: 12 | B13: =TRUE() -> TRUE | F13: What methodology did a scoping review of generative AI in nursing education follow to map and synthesise evidence, and where was its protocol registered? | G13: The review followed the JBI methodology for scoping reviews to map and synthesise evidence on generative AI in nursing education. Its protocol was registered in the Open Science Framework registry. (Patterns, advances, and gaps in using ChatGPT and similar technologies in nursing education: A PAGER scoping review, p. 2) | H13: We followed the JBI methodology for scoping reviews (Peters et al., 2020) to map and synthesise evidence on GenAI in nursing education. A protocol was registered in the Open Science Framework (OSF) registry (doi:10.17605/OSF.IO/PNUE8). | I13: =TRUE() -> TRUE | K13: definition | L13: easy | M13: monitoring_improvement | N13: 5 | O13: =TRUE() -> TRUE | P13: Both claims, that the review followed the JBI scoping review methodology and that its protocol was registered in the OSF registry, are stated directly in the evidence. | Q13: Which scoping review methodology guided a nursing-education generative AI review, and in which registry was its protocol recorded? | R13: What approach and registration did a review of generative AI in nursing education use for its protocol? | S13: patterns-advances-and-gaps-in-using-chatgpt-and:0004:q2
... A26: 25 | B26: =TRUE() -> TRUE | F26: Which group of focus group participants made the most substantial changes to the draft K-12 AI competency list, and what perspective guided them? | G26: The second focus group, made up of university teachers from diverse backgrounds, implemented the more substantial changes. Their changes were influenced by their perspective on what students should know before entering university. The third focus group of mainly school teachers largely agreed with these changes. (Be AIware! An AI Competency Model for K-12 Education, p. 5) | H26: The second focus group, consisting of university teachers from diverse backgrounds, implemented more substantial changes influenced by their perspective on what students should know before entering university (Focus Group 2, personal communication, November 9, 2023). The third focus group, primarily including school teachers, largely agreed with the changes proposed by the university teachers (Focus Group 3, personal communication, March 7-8, 2024). This process resulted in refining the competencies from 140 to 98 by excluding duplicates and renaming some. | I26: =TRUE() -> TRUE | K26: factual | L26: medium | M26: teaching_learning | N26: 5 | O26: =TRUE() -> TRUE | P26: Every claim is stated directly in the evidence: the second group's composition, its more substantial changes, its pre-university perspective, and the third group's agreement. | Q26: In developing a K-12 AI competency model, which focus group introduced the biggest changes, and what viewpoint influenced them? | R26: Who made the most significant revisions to the K-12 AI competency list during focus groups, and on what basis? | S26: be-aiware-an-ai-competency-model-for-k-12:0008:q1
A27: 26 | B27: =TRUE() -> TRUE | F27: By how much did the number of private and public higher education institutions in Brazil grow between 2000 and 2018? | G27: Brazil's private institutions grew by 123%, from 1,004 to 2,238 institutions. Public institutions grew by 70%, from 176 to 299. (Socially Responsible Higher Education, p. 50) | H27: In the period from 2000 to 2018, the number of private institutions grew by 123%, from 1,004 to 2,238 institutions, whereas the number of public/state institutions grew by | I27: =FALSE() -> FALSE | J27: grounding(3) | K27: factual | L27: easy | M27: general | N27: 3 | O27: =TRUE() -> TRUE | P27: The private-institution figures (123%, 1,004 to 2,238) match the evidence. The evidence is cut off before any public-institution numbers, so the claim that public institutions grew by 70% from 176 to 299 is unsupported. | Q27: What were the growth rates of private versus public higher education institutions in Brazil from 2000 to 2018? | R27: Between 2000 and 2018, how much did Brazil's private institutions expand compared with its public ones? | S27: budd-l-hall-rajesh-2021-socially-responsible:0027:q2
A28: 27 | B28: =TRUE() -> TRUE | F28: What two sources can give rise to bias in AI systems used in fields such as healthcare, finance, criminal justice and education? | G28: Biases may arise from historical data, such as historical patient data in healthcare, or from a lack of diversity in the training data. These sources apply across domains including healthcare, finance, criminal justice and education. (Towards Ethical and Socially Responsible Explainable AI, p. 67) | H28: Biases may arise from historical patient data or a lack of diversity in training data | I28: =FALSE() -> FALSE | J28: grounding(3) | K28: factual | L28: easy | M28: equity_accessibility | N28: 3 | O28: =TRUE() -> TRUE | P28: The evidence supports historical patient data and a lack of diversity in training data as sources of bias. However, the claim that these sources apply across finance, criminal justice and education is not in the quoted evidence, which mentions only patient (healthcare) data. | Q28: Where can biases in AI systems across healthcare, finance, criminal justice and education originate? | R28: Which two causes are named for bias in AI systems deployed in domains like education and healthcare? | S28: towards-ethical:0028:q0
A29: 28 | B29: =TRUE() -> TRUE | F29: What is data masking in the context of balancing transparency and confidentiality in AI systems? | G29: Data masking is a technique in which confidential information is concealed in a way that does not affect the overall outcome of the decision-making process. It helps AI systems remain transparent about their decisions while still protecting confidential data. (Towards Ethical and Socially Responsible Explainable AI, p. 103) | H29: This can be achieved through techniques such as data masking, where confidential information is concealed in a way that does not affect the overall outcome of the decisionmaking process. | I29: =FALSE() -> FALSE | J29: grounding(3) | K29: definition | L29: easy | M29: privacy_security | N29: 3 | O29: =TRUE() -> TRUE | P29: The definition of data masking (concealing confidential information without affecting the overall outcome of decision-making) is directly supported. However, the claim that it helps AI systems stay transparent about their decisions while protecting confidential data is not stated in the evidence. The quote only says 'This can be achieved', without identifying what 'this' refers to. | Q29: How is data masking defined as a way to protect confidential information in AI decision-making? | R29: What does data masking mean when AI systems need to stay transparent while protecting confidential data? | S29: towards-ethical:0051:q2
A30: 29 | B30: =TRUE() -> TRUE | F30: What did a 2018 URSULA study find about how Peruvian universities were performing in executing socially responsible initiatives? | G30: The 2018 URSULA study found that all 18 Peruvian universities surveyed had difficulty executing socially responsible initiatives. Their results were below the regional average. (Socially Responsible Higher Education, p. 220) | H30: a 2018 study by Unión de Responsabilidad Social Universitaria Latinoamericana - URSULA (Latin American Social Responsibility in Higher Education Union) found that all 18 Peruvian universities surveyed had difficulty in executing socially responsible initiatives, with results below the regional average (p. 17). | I30: =FALSE() -> FALSE | J30: not_standalone | K30: factual | L30: easy | M30: monitoring_improvement | N30: 5 | O30: =FALSE() -> FALSE | P30: The evidence directly states both claims: all 18 surveyed Peruvian universities had difficulty executing socially responsible initiatives, and their results were below the regional average. | Q30: According to a 2018 survey by the Latin American Social Responsibility in Higher Education Union, how did Peruvian universities fare in carrying out socially responsible initiatives? | R30: What were the results of the 2018 URSULA study on Peruvian universities' execution of social responsibility initiatives? | S30: budd-l-hall-rajesh-2021-socially-responsible:0118:q0
A31: 30 | B31: =TRUE() -> TRUE | F31: Why has implementation of the social responsibility obligations in Peru's Law 30220 of 2014 been uneven and difficult? | G31: Implementation has been disparate and difficult largely because the Act was not accompanied by further regulations, policies or government-sponsored programmes. Without such accompanying support, universities were left to implement the obligations on their own. (Socially Responsible Higher Education, p. 220) | H31: However, the obligations set out in the Act have had a disparate and difficult implementation. This may be due in large part to the lack of further regulations, policies or government sponsored programmes to accompany the Act. | I31: =FALSE() -> FALSE | J31: grounding(3) | K31: explanation | L31: medium | M31: governance | N31: 3 | O31: =TRUE() -> TRUE | P31: The evidence supports the lack of further regulations, policies or government-sponsored programmes as a cause, though the source hedges with "may be due" and the answer states it as fact. The claim that universities were "left to implement the obligations on their own" is an added inference not stated in the evidence. | Q31: What explains the disparate and difficult implementation of the social responsibility duties set out in Peru's 2014 university law? | R31: Why have Peruvian universities struggled to put the social responsibility obligations of Law 30220 into practice? | S31: budd-l-hall-rajesh-2021-socially-responsible:0118:q1
A32: 31 | B32: =TRUE() -> TRUE | F32: How do ethical guidelines and practices strengthen the accountability of AI systems? | G32: Ethical guidelines and practices enhance accountability by addressing the broader societal impact of AI technologies. This extends accountability beyond what is strictly required by legal compliance. (Towards Ethical and Socially Responsible Explainable AI, pp. 171-172) | H32: Ethical guidelines and practices enhance accountability by addressing the broader societal impact of AI technologies. … Ensuring that AI systems adhere to applicable laws and regulations is essential for protecting user rights, ensuring fairness, and preventing unintended consequences [28]. | I32: =FALSE() -> FALSE | J32: grounding(3) | K32: explanation | L32: medium | M32: governance | N32: 3 | O32: =TRUE() -> TRUE | P32: The first sentence is quoted directly from the evidence. The claim that ethics extends accountability beyond what legal compliance strictly requires is not stated; the evidence discusses legal compliance separately and never sets up that contrast. | Q32: In what way do ethical guidelines contribute to AI accountability? | R32: What role do ethical practices play in making AI accountable? | S32: towards-ethical:0090:q1
A33: 32 | B33: =TRUE() -> TRUE | F33: What does accountability in AI encompass? | G33: Accountability in AI encompasses legal and regulatory compliance, ethical considerations, and defining liability and responsibility. (Towards Ethical and Socially Responsible Explainable AI, p. 171) | H33: It encompasses legal and regulatory compliance, ethical considerations, and defining liability and responsibility [4, 9, 12, 14, 27]. | I33: =FALSE() -> FALSE | J33: format(sentences=1,paraphrases=2) | K33: definition | L33: easy | M33: governance | N33: 4 | O33: =TRUE() -> TRUE | P33: The evidence lists exactly the three elements given in the answer. It refers to accountability only as "It", so tying the statement to AI accountability is an obvious inference from context rather than something stated outright. | Q33: What components make up the concept of accountability in AI? | R33: How is accountability in AI defined in terms of its scope? | S33: towards-ethical:0090:q2
A34: 33 | B34: =TRUE() -> TRUE | F34: What example is given of auditing and monitoring as an accountability aspect for AI systems? | G34: The example is periodic third-party audits of AI algorithms used in financial decision-making processes. Auditing and monitoring more broadly means conducting regular audits and monitoring to ensure compliance, performance, and ethical standards. (Towards Ethical and Socially Responsible Explainable AI, p. 152) | H34: | Auditing and monitoring | Conducting regular audits and monitoring of AI systems to ensure compliance, performance, and ethical standards | Periodic third-party audits of AI algorithms used in financial decision-making processes | | I34: =FALSE() -> FALSE | J34: not_standalone | K34: factual | L34: easy | M34: monitoring_improvement | N34: 5 | O34: =FALSE() -> FALSE | P34: Both the example (periodic third-party audits of AI algorithms in financial decision-making) and the definition (regular audits and monitoring for compliance, performance and ethical standards) are stated directly in the evidence table. | Q34: Which example illustrates regular auditing and monitoring of AI systems under accountability? | R34: How is auditing and monitoring of AI illustrated with a concrete case in the accountability framework? | S34: towards-ethical:0077:q2
A35: 34 | B35: =TRUE() -> TRUE | F35: What does the Patterns review question ask in a scoping review of generative AI in nursing education? | G35: The Patterns question asks what patterns emerge in how generative AI is discussed, studied and applied in nursing education. (Patterns, advances, and gaps in using ChatGPT and similar technologies in nursing education: A PAGER scoping review, p. 2) | H35: What patterns emerge in how GenAI are discussed, studied and applied in nursing education? | I35: =FALSE() -> FALSE | J35: format(sentences=1,paraphrases=2) | K35: factual | L35: easy | M35: teaching_learning | N35: 5 | O35: =TRUE() -> TRUE | P35: The answer restates the quoted review question almost verbatim. The only change is expanding 'GenAI' to 'generative AI'. | Q35: Which question addresses patterns in a PAGER scoping review of generative AI in nursing education? | R35: What is the Patterns question posed in a review of how generative AI is used in nursing education? | S35: patterns-advances-and-gaps-in-using-chatgpt-and:0003:q3
A36: 35 | B36: =TRUE() -> TRUE | F36: Why did the authors of a scoping review of generative AI in nursing education add the PAGER framework to their review protocol? | G36: The PAGER framework was selected because it provides systematic, actionable insights. It also helps identify knowledge gaps. This suits the complex and rapidly evolving landscape of generative AI. (Patterns, advances, and gaps in using ChatGPT and similar technologies in nursing education: A PAGER scoping review, p. 2) | H36: This framework was specifically selected to provide systematic, actionable insights and identify knowledge gaps in GenAI's complex and rapidly evolving landscape (Bradbury-Jones et al., 2022). | I36: =FALSE() -> FALSE | J36: duplicate(cos=0.960 of patterns-advances-and-gaps-in-using-chatgpt-and:0003:q0) | K36: explanation | L36: medium | M36: monitoring_improvement | N36: 5 | O36: =TRUE() -> TRUE | P36: Every claim in the answer is directly stated in the evidence: PAGER was chosen for systematic, actionable insights, for identifying knowledge gaps, and to suit the complex, rapidly evolving landscape of generative AI. | Q36: What was the rationale for using the PAGER framework as a mapping tool in a nursing-education generative AI scoping review? | R36: Why was PAGER selected to structure a scoping review on generative AI in nursing education? | S36: patterns-advances-and-gaps-in-using-chatgpt-and:0004:q1
A37: 36 | B37: =TRUE() -> TRUE | F37: What kind of research on generative AI in nursing education do the recommendations say should be prioritised when comparing teaching approaches? | G37: Comparative effectiveness research between AI-enhanced and conventional teaching methods should be given priority. This sits alongside longitudinal studies evaluating the impact of GenAI use on student outcomes and ethical decision-making. (Patterns, advances, and gaps in using ChatGPT and similar technologies in nursing education: A PAGER scoping review, p. 8) | H37: Longitudinal studies are needed to evaluate the impact of GenAI use on student outcomes and ethical decision-making. Comparative effectiveness research between AI-enhanced and conventional teaching methods should be given priority. | I37: =FALSE() -> FALSE | J37: not_standalone | K37: definition | L37: easy | M37: monitoring_improvement | N37: 5 | O37: =FALSE() -> FALSE | P37: Both statements, the priority on comparative effectiveness research and the need for longitudinal studies, are stated directly in the evidence. | Q37: Which type of comparative research does the nursing education scoping review prioritise regarding GenAI? | R37: What comparison should research prioritise to evaluate generative AI in nursing teaching? | S37: patterns-advances-and-gaps-in-using-chatgpt-and:0016:q2
A38: 37 | B38: =TRUE() -> TRUE | F38: How did a systematic review of generative AI in entrepreneurship education score each study's quality? | G38: Each study was scored against predefined criteria: 2 points for fully meeting the standards, 1 point for partially meeting them, and 0 points for failing to meet them. The total score classified quality as high (5 points or more), moderate (3-4 points), or low (fewer than 3 points). The criteria concerned the descriptions of methodology, data collection and data analysis. (Toward understanding the role of generative AI in entrepreneurship education: A systematic review, p. 3) | H38: Each study was scored based on predefined criteria: 2 points for fully meeting the standards, 1 point for partially meeting them, and 0 points for failing to meet them (Zhang & Ramayah, 2024). Based on the total score, research quality was categorized as high (≥5 points), moderate (3-4 points), or low (<3 points). | I38: =FALSE() -> FALSE | J38: grounding(3) | K38: definition | L38: medium | M38: monitoring_improvement | N38: 3 | O38: =TRUE() -> TRUE | P38: The 2/1/0 point scheme and the high/moderate/low thresholds are directly supported. The final sentence, saying the criteria concerned descriptions of methodology, data collection and data analysis, is not in the evidence. | Q38: What scoring scheme did a review of generative AI in entrepreneurship education apply to rate the quality of included studies? | R38: How were points assigned to studies when assessing research quality in a systematic review on generative AI in entrepreneurship education? | S38: toward-understanding-the-role-of-generative-ai:0005:q1
A39: 38 | B39: =TRUE() -> TRUE | F39: A secondary school plans to let students use a streaming-style recommender system for a political education unit. What risk does the evidence suggest the teachers should anticipate? | G39: Teachers should anticipate information bubbles and echo chambers. Recommender systems improve personalization but can limit exposure to diverse perspectives and reinforce existing beliefs. This can hinder critical thinking, which is an especially serious concern in the political education of K-12 students. (Be AIware! An AI Competency Model for K-12 Education, p. 2) | H39: While these systems enhance personalization, they can create information bubbles by limiting exposure to diverse perspectives and reinforcing existing beliefs (Areeb et al., 2023; Kidwai et al., 2023). This can hinder critical thinking and create echo chambers, an especially serious concern in the political education of K-12 students | I39: =FALSE() -> FALSE | J39: not_standalone | K39: application | L39: medium | M39: teaching_learning | N39: 5 | O39: =FALSE() -> FALSE | P39: Every claim in the answer is stated directly in the evidence: information bubbles, limited exposure to diverse perspectives, reinforcement of existing beliefs, hindered critical thinking, echo chambers, and the particular concern for political education of K-12 students. | Q39: A K-12 teacher wants students to research political topics using platforms driven by recommendation algorithms. What concern should the teacher keep in mind? | R39: What problem might arise if school students in a political education course rely on personalized recommender systems for information? | S39: be-aiware-an-ai-competency-model-for-k-12:0002:q0
A40: 39 | B40: =TRUE() -> TRUE | F40: What difficulty do teachers face in detecting AI-generated student work, according to the discussion of generative AI challenges in K-12 education? | G40: Teachers struggle with detecting AI-generated work because current detection tools are unreliable. This is listed among the challenges teachers face with generative AI, alongside reduced creativity, data privacy concerns, deepfakes and fake news, and copyright issues. (Be AIware! An AI Competency Model for K-12 Education, p. 2) | H40: Teachers also struggle with detecting AI-generated work, as current detection tools are unreliable. | I40: =FALSE() -> FALSE | J40: grounding(3) | K40: factual | L40: easy | M40: assessment | N40: 3 | O40: =TRUE() -> TRUE | P40: The core claim, that detection tools are unreliable, is directly stated. The list of other challenges (reduced creativity, data privacy concerns, deepfakes and fake news, copyright issues) does not appear in the quoted evidence. | Q40: Why do teachers struggle to identify AI-generated work from students? | R40: What is the problem with current tools for detecting AI-generated work in K-12 classrooms? | S40: be-aiware-an-ai-competency-model-for-k-12:0002:q4
A41: 40 | B41: =TRUE() -> TRUE | F41: How does the Data characteristics knowledge competency progress in the AIware K-12 AI competency model? | G41: The competency moves from recognizing data characteristics to critically evaluating the quality and relevance of data sets. (Be AIware! An AI Competency Model for K-12 Education, p. 39) | H41: Moves from recognizing data characteristics to critically evaluating the quality and relevance of data sets. | I41: =FALSE() -> FALSE | J41: format(sentences=1,paraphrases=2) | K41: factual | L41: easy | M41: student_ai_literacy | N41: 5 | O41: =TRUE() -> TRUE | P41: The answer repeats the evidence almost word for word: the competency progresses from recognizing data characteristics to critically evaluating the quality and relevance of data sets. Nothing is added. | Q41: What is the progression of the Data characteristics competency in the Be AIware K-12 model? | R41: In the AIware K-12 model, how does learners' knowledge of data characteristics develop over levels? | S41: be-aiware-an-ai-competency-model-for-k-12:0057:q4
A42: 41 | B42: =FALSE() -> FALSE | F42: Why does the geographic distribution of the Times Higher Education top 300 universities suggest that rankings reflect a Global North concentration of 'quality'? | G42: In the THE top 300, 282 universities (94%) are in the 'Global North' of high-income countries as defined by the World Bank. Since global rankings imply that 'world class' status, quality or excellence are concentrated in specific places, this distribution suggests that excellence is absent elsewhere. (Socially Responsible Higher Education, pp. 95-96) | H42: 282 (94%) are located in the so-called 'Global North' of high income countries as specified by the World Bank (2019). … The message seems clear - 'world class' status, 'quality', or 'excellence' are highly concentrated in specific places. It is therefore, by implication, not present in others. | I42: =TRUE() -> TRUE | K42: explanation | L42: medium | M42: equity_accessibility | N42: 4 | O42: =TRUE() -> TRUE | P42: The 282 (94%) figure and the claim that excellence is implicitly absent elsewhere are directly supported. Linking the figure to the THE top 300 is an obvious inference (282/300 = 94%), but the quoted evidence does not name the ranking explicitly. | Q42: What does the geographic makeup of the THE top 300 reveal about how rankings concentrate 'quality' in the Global North? | R42: How does the location of the top 300 universities in the THE rankings show a Global North bias in who is deemed excellent? | S42: budd-l-hall-rajesh-2021-socially-responsible:0055:q1
A43: 42 | B43: =FALSE() -> FALSE | F43: How many institutions represent the entire African continent in the Times Higher Education top 300, and where are they located? | G43: The entire continent of Africa is represented by three institutions, all of which are in South Africa. By comparison, only one university comes from the whole of Latin America, one from the Middle East, and none from Central Asia. (Socially Responsible Higher Education, p. 95) | H43: The entire continent of Africa is represented by three institutions, all of which are in South Africa. There is only one university from the whole of Latin America, one from the Middle East, and not a single institution from Central Asia. | I43: =TRUE() -> TRUE | K43: factual | L43: easy | M43: equity_accessibility | N43: 5 | O43: =TRUE() -> TRUE | P43: Every statement in the answer (three African institutions, all in South Africa, one from Latin America, one from the Middle East, none from Central Asia) is directly stated in the evidence. The evidence does not itself name the Times Higher Education top 300, but the answer makes no claim about the ranking. | Q43: Which and how many African universities appear in the THE top 300 rankings? | R43: In the THE top 300, how is Africa represented, and in which country are its universities? | S43: budd-l-hall-rajesh-2021-socially-responsible:0055:q2
A44: 43 | B44: =FALSE() -> FALSE | F44: Why can the geographic bias in university rankings not be dismissed as a quirk of a single ranking system such as Times Higher Education? | G44: THE is not alone in this bias. The Academic Ranking of World Universities (ARWU) and the QS World University Rankings are more geographically inclusive, but only by a few percentage points. The bias is therefore shared across the major global rankings. (Socially Responsible Higher Education, p. 95) | H44: THE is not alone in this bias - the Academic Ranking of World Universities (ARWU, 2019) and QS World University Rankings (QS, 2019) are more geographically inclusive, but only by a few percentage points. | I44: =TRUE() -> TRUE | K44: explanation | L44: medium | M44: equity_accessibility | N44: 4 | O44: =TRUE() -> TRUE | P44: The answer's first two sentences are stated directly in the evidence. The conclusion that the bias is shared across the major global rankings is an obvious inference from them. | Q44: Why is the Global North skew in rankings not limited to just the THE ranking? | R44: How do other major rankings show that THE's geographic bias is not unique? | S44: budd-l-hall-rajesh-2021-socially-responsible:0055:q3
A45: 44 | B45: =FALSE() -> FALSE | F45: Why is the dominance of already-advantaged institutions in global rankings not simply evidence that the best universities rise to the top? | G45: Rankings reflect a system in which already-advantaged institutions identify themselves as better and use systemic processes to stay on top. Underlying structures create, maintain and often exacerbate social inequalities. The argument also frames rankings as a question of sovereignty and control, where power, status and funding rest with a small minority of majority-white countries and institutions. (Socially Responsible Higher Education, p. 96) | H45: underlying structures invariably create, maintain and often exacerbate social inequalities. In other words, it is not about the cream rising to the top, but rather about the presence of a system in which the cream identifies itself as better and utilises systemic processes to stay there. … rankings are a question of sovereignty, of control, where the balance of power - and therefore status and funding - rests in the hands of a small minority of majority white countries and institutions. | I45: =TRUE() -> TRUE | K45: explanation | L45: hard | M45: equity_accessibility | N45: 4 | O45: =TRUE() -> TRUE | P45: Every claim matches the evidence apart from small rewordings: 'already-advantaged institutions' stands in for 'the cream', and 'invariably' is dropped. Nothing in the answer goes beyond what is quoted. | Q45: How do rankings reflect structural inequality rather than the best universities naturally rising? | R45: Why is it misleading to read top rankings as 'cream rising to the top'? | S45: budd-l-hall-rajesh-2021-socially-responsible:0055:q4
A46: 45 | B46: =FALSE() -> FALSE | F46: Which kinds of data should decision-making in an educational AI system draw on to be considered transparent and well-founded? | G46: Decision-making processes in educational AI should be transparent and based on all relevant data. This includes student performance, demographic information and behavioural factors. (Towards Ethical and Socially Responsible Explainable AI, p. 67) | H46: Decision-making processes should be transparent and based on all relevant data, including student performance, demographic information and behavioural factors | I46: =TRUE() -> TRUE | K46: factual | L46: easy | M46: governance | N46: 5 | O46: =TRUE() -> TRUE | P46: The evidence directly states that decision-making should be transparent and based on all relevant data, and it names student performance, demographic information and behavioural factors. The answer adds nothing beyond the evidence. | Q46: What data should educational AI decisions be based on? | R46: According to guidance on transparent educational AI, what relevant data should inform its decisions? | S46: towards-ethical:0028:q1
A47: 46 | B47: =FALSE() -> FALSE | F47: What should an explanation from an educational personalized learning AI contain about its recommendations for an individual student? | G47: The system should explain how it arrived at recommendations for individual students. That explanation should include the factors considered and the goals of the recommendations. (Towards Ethical and Socially Responsible Explainable AI, p. 68) | H47: Explanations of how the system arrived at recommendations for individual students, including the factors considered and the goals of those recommendations | I47: =TRUE() -> TRUE | K47: definition | L47: medium | M47: teaching_learning | N47: 5 | O47: =TRUE() -> TRUE | P47: Every statement in the answer is directly stated in the evidence: how the system arrived at recommendations for individual students, the factors considered and the goals of the recommendations. | Q47: What does explainability look like for a personalized learning AI's recommendations to individual students? | R47: What elements should explanations of personalized learning AI recommendations include? | S47: towards-ethical:0028:q3
A48: 47 | B48: =FALSE() -> FALSE | F48: Which types of laws should educational AI systems comply with according to guidance on ethical AI in education? | G48: Educational AI systems should comply with educational regulations and laws. These include student privacy laws and anti-discrimination laws. (Towards Ethical and Socially Responsible Explainable AI, p. 68) | H48: Compliance with educational regulations and laws, including student privacy laws and anti-discrimination laws | I48: =TRUE() -> TRUE | K48: factual | L48: easy | M48: privacy_security | N48: 5 | O48: =TRUE() -> TRUE | P48: The evidence names compliance with educational regulations and laws, including student privacy and anti-discrimination laws, which the answer restates directly. | Q48: What legal requirements are named for educational AI systems? | R48: With which regulations and laws should AI systems in education be compliant? | S48: towards-ethical:0028:q4
A49: 48 | B49: =FALSE() -> FALSE | F49: In which kinds of settings may high transparency be necessary, and in which may confidentiality take priority, for AI decision-making? | G49: High transparency may be necessary in contexts such as medical diagnosis or financial decision-making, to build trust and ensure accountability. In contexts such as national security or defense, confidentiality may be paramount, and transparency may need to be limited to protect sensitive information. (Towards Ethical and Socially Responsible Explainable AI, p. 104) | H49: In some cases, such as medical diagnosis or financial decision-making, a high level of transparency may be necessary to build trust and ensure accountability. In other cases, such as national security or defense, confidentiality may be paramount, and transparency may need to be limited to protect sensitive information [1, 9, 12]. | I49: =TRUE() -> TRUE | K49: factual | L49: easy | M49: governance | N49: 5 | O49: =TRUE() -> TRUE | P49: Every statement in the answer is taken directly from the evidence. This covers medical diagnosis and financial decision-making needing high transparency for trust and accountability, and national security and defense where confidentiality is paramount and transparency is limited to protect sensitive information. | Q49: Which domains call for a high level of AI transparency, and which may limit transparency in favor of confidentiality? | R49: Where is strong transparency needed in AI decisions, and where might confidentiality be paramount? | S49: towards-ethical:0051:q1
A50: 49 | B50: =FALSE() -> FALSE | F50: Why should clear guidelines and standards for confidentiality and transparency be established for AI development and deployment? | G50: What counts as confidential information differs among stakeholders. For example, a company may consider something confidential that a regulatory body or the public does not. Because of this difference, clear guidelines and standards are needed for confidentiality and transparency in AI development and deployment. (Towards Ethical and Socially Responsible Explainable AI, p. 104) | H50: For example, what is considered confidential information by a company may be different from what is considered confidential information by a regulatory body or the public. Therefore, it is essential to establish clear guidelines and standards for confidentiality and transparency in the development and deployment of AI systems [97, 98]. | I50: =TRUE() -> TRUE | K50: explanation | L50: medium | M50: governance | N50: 5 | O50: =TRUE() -> TRUE | P50: Every claim in the answer is stated in the evidence. The evidence gives the example that companies, regulators and the public view confidential information differently, and draws the conclusion that clear guidelines are therefore essential. | Q50: What justifies setting clear standards on confidentiality and transparency for AI systems? | R50: Why is it essential to define shared guidelines on confidentiality and transparency in AI? | S50: towards-ethical:0051:q3
A51: 50 | B51: =FALSE() -> FALSE | F51: How many of 31 surveyed Peruvian law schools have implemented public interest clinics rather than free legal aid clinics? | G51: Only 3 of the 31 Peruvian law schools surveyed have implemented public interest clinics. The remainder opted for free legal aid clinics. These often function as alternatives to internships that give students educational credit, which was reported by 27 institutions. (Socially Responsible Higher Education, p. 222) | H51: of the 31 institutions surveyed, only 3 have implemented public interest clinics, while the remainder have opted for free legal aid clinics. The latter often function as alternatives to internships, where students can get educational credit and recognition for internship work (27 institutions). | I51: =TRUE() -> TRUE | K51: factual | L51: easy | M51: teaching_learning | N51: 4 | O51: =TRUE() -> TRUE | P51: The answer is fully supported by the evidence. Two details are inferred rather than stated: that the 31 institutions are Peruvian law schools (likely from context but absent from the quoted passage), and that the 27-institution figure refers to internship credit (an interpretation of a parenthetical). | Q51: Out of 31 law schools surveyed in Peru, how many run public interest clinics instead of free legal aid clinics? | R51: What number of the 31 Peruvian law schools studied have set up public interest clinics? | S51: budd-l-hall-rajesh-2021-socially-responsible:0120:q0
A52: 51 | B52: =FALSE() -> FALSE | F52: How are free legal aid clinics and public interest clinics distributed across Peruvian universities? | G52: Free legal aid clinics are evenly distributed across public and private universities throughout the country. Public interest clinics, by contrast, are concentrated in three private universities in Lima, the capital. (Socially Responsible Higher Education, p. 222) | H52: The research shows that free legal aid clinics are evenly distributed in public and private universities throughout the country, while public interest clinics are concentrated in three private universities in Lima, Peru's capital. | I52: =TRUE() -> TRUE | K52: factual | L52: easy | M52: equity_accessibility | N52: 5 | O52: =TRUE() -> TRUE | P52: Every statement in the answer is stated directly in the evidence: the even public/private, nationwide distribution of free legal aid clinics and the concentration of public interest clinics in three private universities in Lima. | Q52: Where in Peru are free legal aid clinics and public interest clinics located, and in which types of universities? | R52: What is the geographic and public/private distribution of the two clinic types in Peruvian law schools? | S52: budd-l-hall-rajesh-2021-socially-responsible:0120:q1
A53: 52 | B53: =FALSE() -> FALSE | F53: Why might public interest clinics in Peruvian law schools be concentrated in Lima? | G53: The concentration could be because Peru has only a few dedicated public interest lawyers. In addition, the country's high courts, the Supreme Court and the Constitutional Court, are both located in Lima. (Socially Responsible Higher Education, p. 222) | H53: This could be because there only few dedicated public interest lawyers in Peru, and the high courts of Peru (Supreme Court and Constitutional Court) are both in Lima. | I53: =TRUE() -> TRUE | K53: explanation | L53: medium | M53: general | N53: 5 | O53: =TRUE() -> TRUE | P53: Both reasons given in the answer, the scarcity of public interest lawyers and the location of the Supreme Court and Constitutional Court in Lima, are stated directly in the evidence. | Q53: What reasons are suggested for public interest clinics clustering in Peru's capital? | R53: How can the Lima concentration of public interest clinics in Peruvian legal education be explained? | S53: budd-l-hall-rajesh-2021-socially-responsible:0120:q2
... A89: 88 | B89: =FALSE() -> FALSE | F89: How was the K-12 AI competency model designed so that it could be used across different educational scenarios, and why does a granular structure help? | G89: The model was designed to be modular and mappable to existing subjects and educational frameworks, so it can be used across different educational scenarios. Insights from practice confirmed that a granular structure improves alignment with school-based needs and curricular integration. (Be AIware! An AI Competency Model for K-12 Education, p. 5) | H89: To address this, the model was designed to be modular and mappable to existing subjects and educational frameworks. … Insights from practice also confirmed that a granular structure improves alignment with school-based needs and curricular integration. | I89: =TRUE() -> TRUE | K89: explanation | L89: medium | M89: teaching_learning | N89: 4 | O89: =TRUE() -> TRUE | P89: The modular, mappable design and the benefit of granularity are stated directly. Linking the design to use 'across different educational scenarios' is a mild inference, because the evidence says only 'To address this' without showing what 'this' refers to. | Q89: What design features let the K-12 AI competency model fit varied educational contexts, and what is the benefit of granularity? | R89: Why is the K-12 AI competency model modular and granular, and how does this support use in schools? | S89: be-aiware-an-ai-competency-model-for-k-12:0008:q4
A90: 89 | B90: =FALSE() -> FALSE | F90: What does the European Union's General Data Protection Regulation set out that relates to transparency in AI? | G90: The GDPR sets standards for data protection and privacy in the EU. These include requirements for transparency and accountability in the use of personal data. It is cited as an initiative promoting transparency and confidentiality in AI. (Towards Ethical and Socially Responsible Explainable AI, p. 104) | H90: the European Union's General Data Protection Regulation (GDPR) [99] sets standards for data protection and privacy in the EU, including requirements for transparency and accountability in the use of personal data. | I90: =FALSE() -> FALSE | J90: grounding(3) | K90: factual | L90: easy | M90: privacy_security | N90: 3 | O90: =TRUE() -> TRUE | P90: The first two sentences match the evidence. The claim that the GDPR is cited as an initiative promoting transparency and confidentiality in AI does not appear in the quoted evidence. | Q90: Which standards does the EU's GDPR establish that bear on transparency and accountability? | R90: What requirements does the GDPR impose regarding personal data use? | S90: towards-ethical:0051:q4
A91: 90 | B91: =FALSE() -> FALSE | F91: Which case types do free legal aid clinics at Peruvian law schools most commonly handle, according to a survey of 31 institutions? | G91: Most free legal aid clinics (22 universities) accept cases of varying nature. Of the 31 clinics, 24 provided services in family law and 16 in criminal law. Only 15 handle civil law and 10 administrative cases, even though civil law is the most common practice area and citizens struggle with state bureaucracy. (Socially Responsible Higher Education, p. 223) | H91: most free legal aid clinics (22 universities) accept cases of varying nature. Out of the 31 clinics, 24 free legal aid clinics provided services in family law and 16 provided representation in criminal law cases. | I91: =FALSE() -> FALSE | J91: grounding(3) | K91: factual | L91: medium | M91: general | N91: 3 | O91: =TRUE() -> TRUE | P91: The claims about 15 clinics handling civil law and 10 handling administrative cases, along with the remarks that civil law is the most common practice area and that citizens struggle with state bureaucracy, do not appear in the evidence. The remaining statements are directly supported. | Q91: In a survey of 31 Peruvian law schools, what kinds of cases do free legal aid clinics take, and how many offer family and criminal law? | R91: What areas of law do Peruvian free legal aid clinics cover, and how many provide civil and administrative services? | S91: budd-l-hall-rajesh-2021-socially-responsible:0120:q4
A92: 91 | B92: =FALSE() -> FALSE | F92: Why do some scholars argue that Peru's Law 30220 requires universities to build a social responsibility component into all their programmes, rather than only managing their impact? | G92: The argument is that, read systematically, the Act obliges all universities to construct all their programmes with a social responsibility component. Focusing only on impact management under Article 124 would breach Articles 5, 6 and 130. Those articles set guiding principles such as inclusion and community engagement, and require a University Social Service Programme. (Socially Responsible Higher Education, pp. 219-220) | H92: we posit that the Act in fact obliges all universities to construct all their programmes with a social responsibility component. … Articles 5 and 6 establish that pluralism, inclusion, intercultural dialogue and commitment to the country's development are the guiding principles of higher education, and universities should strive to interact with the community and engage in socially relevant teaching and research. … Article 130 establishes the obligation to implement SRHEI. Per this article, every university should create a Programa de Servicio Social Universitario (University Social Service Programme), through which students apply knowledge in a way that improves the quality of life of people in traditionally marginalised groups. | I92: =FALSE() -> FALSE | J92: grounding(3) | K92: explanation | L92: hard | M92: governance | N92: 3 | O92: =TRUE() -> TRUE | P92: The evidence supports the obligation to give every programme a social responsibility component, the principles in Articles 5 and 6, and Article 130's University Social Service Programme. It never mentions Article 124, a 'systematic' reading, or any claim that impact management alone would breach those articles. | Q92: On what reasoning is it claimed that Peru's 2014 university law obliges social responsibility in every university programme? | R92: Why would focusing only on impact management under Article 124 of Law 30220 be considered insufficient? | S92: budd-l-hall-rajesh-2021-socially-responsible:0118:q2
A93: 92 | B93: =FALSE() -> FALSE | F93: How does Article 124 of Peru's Law 30220 define social responsibility in higher education (SRHEI)? | G93: Article 124 defines SRHEI as the ethical and effective management of the impact generated by the university in society. This includes impacts arising from the relationship between the university community, the environment and other public and private organisations. (Socially Responsible Higher Education, p. 219) | H93: Article 124 defines SRHEI as "the ethical and effective management of the impact generated by the university in society" | I93: =FALSE() -> FALSE | J93: grounding(3) | K93: definition | L93: easy | M93: governance | N93: 3 | O93: =TRUE() -> TRUE | P93: The first sentence matches the quoted definition. The second sentence, about impacts arising from relationships between the university community, the environment and public and private organisations, is not in the evidence. | Q93: What is the legal definition of SRHEI in Article 124 of Peru's 2014 university law? | R93: According to Peru's Law 30220, what does social responsibility in higher education mean? | S93: budd-l-hall-rajesh-2021-socially-responsible:0118:q3
A94: 93 | B94: =FALSE() -> FALSE | F94: Why does a PAGER-based scoping review of generative AI in nursing education ask about gaps in current knowledge and practice? | G94: The Gaps question asks what gaps exist in current knowledge and practice regarding the use and integration of generative AI. This fits the review's broader aim of highlighting gaps in current evidence on how tools like ChatGPT are implemented in nursing education. (Patterns, advances, and gaps in using ChatGPT and similar technologies in nursing education: A PAGER scoping review, p. 2) | H94: What gaps exist in current knowledge and practice regarding GenAI use and integration? … This scoping review examines how GenAI tools such as ChatGPT are implemented in nursing education. It seeks to identify common implementation patterns, document technological advances, highlight gaps in current evidence, summarise practice-based findings, and propose recommendations for responsible integration. | I94: =FALSE() -> FALSE | J94: duplicate(cos=0.922 of patterns-advances-and-gaps-in-using-chatgpt-and:0003:q0) | K94: explanation | L94: medium | M94: monitoring_improvement | N94: 5 | O94: =TRUE() -> TRUE | P94: Both statements are directly stated in the evidence: the Gaps question wording and the review's aim to highlight gaps in current evidence on how GenAI tools such as ChatGPT are implemented in nursing education. | Q94: What is the purpose of the Gaps question in a PAGER scoping review of generative AI in nursing education? | R94: How does the Gaps question fit into a PAGER review of generative AI use in nursing education? | S94: patterns-advances-and-gaps-in-using-chatgpt-and:0003:q2
A95: 94 | B95: =FALSE() -> FALSE | F95: Why do reviewed studies recommend preserving traditional teaching methods when integrating AI into nursing curricula? | G95: Studies recommend systematically integrating AI while preserving traditional teaching methods so that innovation stays balanced with established pedagogical practices. This balance is maintained through integrating ethics and data literacy. Such integration was also noted as able to strengthen student writing skills. (Patterns, advances, and gaps in using ChatGPT and similar technologies in nursing education: A PAGER scoping review, p. 7) | H95: studies recommend systematically integrating AI into nursing education while preserving traditional teaching methods, noting that such integration can strengthen student writing skills (Parker et al., 2023) while maintaining balance between innovation and established pedagogical practices through ethics and data literacy integration | I95: =FALSE() -> FALSE | J95: not_standalone | K95: explanation | L95: medium | M95: teaching_learning | N95: 4 | O95: =FALSE() -> FALSE | P95: All three claims (the balance between innovation and established pedagogy, the role of ethics and data literacy integration, and the strengthening of writing skills) appear in the evidence. However, the answer frames 'balance' as the purpose ("so that"), a causal reading the evidence only implies. | Q95: How should nursing programs balance AI integration with traditional teaching, according to the reviewed studies? | R95: What is the rationale for keeping established pedagogy alongside AI in nursing education? | S95: patterns-advances-and-gaps-in-using-chatgpt-and:0013:q2
A96: 95 | B96: =FALSE() -> FALSE | F96: What four major domains of generative AI use in entrepreneurship education were identified in a systematic review of 50 peer-reviewed articles published between 2019 and early 2025? | G96: The review found four major domains: personalized and adaptive instruction, simulation-based entrepreneurial training, ethical and psychological concerns, and ecosystem integration through intelligent systems. (Toward understanding the role of generative AI in entrepreneurship education: A systematic review, p. 1) | H96: The findings reveal four major domains in GAIenabled EE: personalized and adaptive instruction, simulation-based entrepreneurial training, ethical and psychological concerns, and ecosystem integration through intelligent systems. | I96: =FALSE() -> FALSE | J96: format(sentences=1,paraphrases=2) | K96: factual | L96: easy | M96: teaching_learning | N96: 4 | O96: =TRUE() -> TRUE | P96: All four domains match the evidence verbatim. The details about 50 peer-reviewed articles from 2019 to early 2025 are not in the quoted evidence, but they appear only in the question framing, not as claims in the answer. | Q96: Which four domains of generative AI-enabled entrepreneurship education emerged from a review of 50 peer-reviewed articles from 2019 to early 2025? | R96: According to a systematic review of 50 articles covering 2019 to early 2025, what are the main areas in which generative AI is used in entrepreneurship education? | S96: toward-understanding-the-role-of-generative-ai:0000:q0
A97: 96 | B97: =FALSE() -> FALSE | F97: Why does the thematic-analysis design of the review limit what can be concluded about how generative AI improves entrepreneurial competencies? | G97: The review used thematic analysis and did not include a meta-analysis, which could have given a quantitative assessment of generative AI's influence. Its reliance on prior research also limits the ability to establish causal relationships. Future work should integrate systematic meta-analyses and longitudinal empirical studies to validate the mechanisms through which generative AI improves entrepreneurial competencies. (Toward understanding the role of generative AI in entrepreneurship education: A systematic review, p. 19) | H97: This study employs thematic analysis to synthesize existing research and identify key trends; however, it does not include a meta-analysis, which could provide a quantitative assessment of GAI's influence. Moreover, reliance on prior research limits the ability to establish causal relationships. Future research should integrate systematic meta-analyses and longitudinal empirical studies to validate the mechanisms through which GAI improves entrepreneurial competencies and outcomes. | I97: =FALSE() -> FALSE | J97: not_standalone | K97: explanation | L97: medium | M97: monitoring_improvement | N97: 5 | O97: =FALSE() -> FALSE | P97: Every claim in the answer is stated in the evidence: thematic analysis without a meta-analysis, reliance on prior research limiting causal claims, and the call for meta-analyses and longitudinal studies. | Q97: How does using thematic analysis without meta-analysis restrict conclusions about generative AI's effect on entrepreneurial competencies? | R97: What methodological constraints of the review prevent causal claims about generative AI and entrepreneurial competencies, and what is suggested? | S97: toward-understanding-the-role-of-generative-ai:0033:q4
A98: 97 | B98: =FALSE() -> FALSE | F98: A university uses an AI recruitment screening tool trained on past hiring records, and staff notice it favors particular demographic groups. What does the evidence suggest explains this? | G98: AI systems trained on biased data can unintentionally reinforce stereotypes or unfairly exclude certain groups. If historical hiring data reflects biased hiring practices, a recruitment system may favor particular demographics. This perpetuates inequalities. (Be AIware! An AI Competency Model for K-12 Education, p. 2) | H98: AI systems trained on biased data can unintentionally reinforce stereotypes or unfairly exclude certain groups. For example, AI-driven recruitment systems may favor particular demographics if historical data reflects biased hiring practices, perpetuating inequalities. | I98: =FALSE() -> FALSE | J98: not_standalone | K98: application | L98: medium | M98: equity_accessibility | N98: 5 | O98: =FALSE() -> FALSE | P98: Every statement in the answer is taken almost verbatim from the evidence: biased training data reinforces stereotypes and exclusion, historical biased hiring data leads recruitment systems to favor certain demographics, and this perpetuates inequalities. | Q98: An AI hiring tool trained on historical hiring data keeps favoring certain demographics. Why might this be happening? | R98: A college HR office finds its AI recruitment system disadvantages some groups. What underlying cause does the evidence point to? | S98: be-aiware-an-ai-competency-model-for-k-12:0002:q3
A99: 98 | B99: =FALSE() -> FALSE | F99: In the Be AIware K-12 AI competency model, how does the Tables skill progress across levels? | G99: The Tables skill develops from basic data table comprehension to designing and interpreting complex tabular datasets. (Be AIware! An AI Competency Model for K-12 Education, p. 39) | H99: Develops from basic data table comprehension to designing and interpreting complex tabular datasets. | I99: =FALSE() -> FALSE | J99: format(sentences=1,paraphrases=2) | K99: factual | L99: easy | M99: student_ai_literacy | N99: 5 | O99: =TRUE() -> TRUE | P99: The answer restates the evidence nearly verbatim, so every claim is directly supported. | Q99: What progression does the Tables skill follow in the AIware AI competency model for K-12 education? | R99: In the K-12 AI competency model called Be AIware, what does development of the Tables skill look like from basic to advanced? | S99: be-aiware-an-ai-competency-model-for-k-12:0057:q0
A100: 99 | B100: =FALSE() -> FALSE | F100: A secondary school teacher wants students to move beyond making simple charts toward using visualizations to support strategic decisions. Which competency in the AIware K-12 AI competency model does this match, and what does its progression involve? | G100: This matches the Visualization of datasets skill. It advances from creating simple visual representations of data to designing and interpreting complex visualizations that enhance understanding and support strategic decision-making. (Be AIware! An AI Competency Model for K-12 Education, p. 39) | H100: Advances from creating simple visual representations of data to designing and interpreting complex visualizations that enhance understanding and support strategic decision-making. | I100: =FALSE() -> FALSE | J100: grounding(3) | K100: application | L100: medium | M100: teaching_learning | N100: 3 | O100: =TRUE() -> TRUE | P100: The progression description is quoted directly from the evidence. However, the skill name 'Visualization of datasets', which is central to the answer, does not appear in the quoted evidence. | Q100: A K-12 teacher aims to take students from basic charts to visuals that inform strategic decisions. Which AIware competency fits, and how does it progress? | R100: Which skill in the Be AIware K-12 model should a teacher target when students should progress from simple data graphics to complex visualizations guiding decisions, and what is its progression? | S100: be-aiware-an-ai-competency-model-for-k-12:0057:q1
A101: 100 | B101: =FALSE() -> FALSE | F101: In the AIware K-12 AI competency model, what does the Structured and unstructured data competency involve? | G101: It involves distinguishing between data with well-defined structures and data without a predefined data model. (Be AIware! An AI Competency Model for K-12 Education, p. 39) | H101: Distinguishing between data with well-defined structures and data without a predefined data model. | I101: =FALSE() -> FALSE | J101: format(sentences=1,paraphrases=2) | K101: definition | L101: easy | M101: student_ai_literacy | N101: 5 | O101: =TRUE() -> TRUE | P101: The answer reproduces the evidence verbatim, so nothing in it is unsupported. | Q101: What does the Structured and unstructured data competency mean in the Be AIware K-12 model? | R101: In the AIware competency model for K-12, what is learners' task under the Structured and unstructured data competency? | S101: be-aiware-an-ai-competency-model-for-k-12:0057:q3

Sheet Agreement
A1: Review progress
A2: Rows reviewed | B2: =COUNTIF(Review!$C$2:$C$101,"accept")+COUNTIF(Review!$C$2:$C$101,"reject") -> 0
A3: Priority rows reviewed (of 40) | B3: =COUNTIFS(Review!$B$2:$B$101,TRUE(),Review!$C$2:$C$101,"accept")+COUNTIFS(Review!$B$2:$B$101,TRUE(),Review!$C$2:$C$101,"reject") -> 0
A4: Human accept rate | B4: =IFERROR(COUNTIF(Review!$C$2:$C$101,"accept")/B2,"")
A5: Human accept rate among filter-passed pairs | B5: =IFERROR(COUNTIFS(Review!$I$2:$I$101,TRUE(),Review!$C$2:$C$101,"accept")/(COUNTIFS(Review!$I$2:$I$101,TRUE(),Review!$C$2:$C$101,"accept")+COUNTIFS(Review!$I$2:$I$101,TRUE(),Review!$C$2:$C$101,"reject")),"")
A7: Confusion matrix (reviewed rows only)
B8: Human accept | C8: Human reject
A9: Filters passed | B9: =COUNTIFS(Review!$I$2:$I$101,TRUE(),Review!$C$2:$C$101,"accept") -> 0 | C9: =COUNTIFS(Review!$I$2:$I$101,TRUE(),Review!$C$2:$C$101,"reject") -> 0
A10: Filters rejected | B10: =COUNTIFS(Review!$I$2:$I$101,FALSE(),Review!$C$2:$C$101,"accept") -> 0 | C10: =COUNTIFS(Review!$I$2:$I$101,FALSE(),Review!$C$2:$C$101,"reject") -> 0
A12: Observed agreement | B12: =IFERROR((B9+C10)/(B9+C9+B10+C10),"")
A13: Cohen's kappa | B13: =IFERROR(((B9+C10)/(B9+C9+B10+C10)-((B9+C9)*(B9+B10)+(B10+C10)*(C9+C10))/(B9+C9+B10+C10)^2)/(1-((B9+C9)*(B9+B10)+(B10+C10)*(C9+C10))/(B9+C9+B10+C10)^2),"")
A15: Human reject categories
A16: incorrect | B16: =COUNTIF(Review!$D$2:$D$101,"incorrect") -> 0
A17: unsupported | B17: =COUNTIF(Review!$D$2:$D$101,"unsupported") -> 0
A18: not_standalone | B18: =COUNTIF(Review!$D$2:$D$101,"not_standalone") -> 0
A19: low_value | B19: =COUNTIF(Review!$D$2:$D$101,"low_value") -> 0
A20: unclear | B20: =COUNTIF(Review!$D$2:$D$101,"unclear") -> 0
A21: other | B21: =COUNTIF(Review!$D$2:$D$101,"other") -> 0
A23: Rows 9-10 = automatic filter decision; columns B-C = your verdict. Kappa above ~0.6 means the judge broadly matches your standard.
